Workbook

Sheet Cover
A1: DOMS INDUSTRIES LIMITED
A2: Three-Statement Financial Model - Harsh Vijay
A3: Model Date: February 26, 2026 | TASK SUBMISSION PHI CAPITAL
A5: COMPANY OVERVIEW
A6: Sector: | B6: Stationery, Art Materials & Baby Hygiene (Consumer Brand / FMCG-lite)
A7: Listing: | B7: NSE: DOMS | BSE | IPO Price ₹790/share; Listed Dec 20, 2023 @ ₹1400 (~77% Premium)
A8: Market Cap: | B8: ~₹14,000 Cr (Feb 2026) | CMP: ~₹2,350 | P/E: ~61.5x (TTM)
A9: Promoters: | B9: RR Group (Raveshia-Rajani) + F.I.L.A. S.p.A (Italy) | Combined ~70.4%
A10: Shares O/S: | B10: ~6.07 Cr equity shares (post-IPO + ESOP)
A12: VALUATION FRAMING: CONSUMER BRAND / FMCG-LITE
A13: Rationale: | B13: DOMS commands 'pester power' (child-led brand choice), 145K+ retail outlets, FMCG-like distribution moat
B14: Diversifying into baby hygiene (Uniclan/Wowper), bags (Seven JV); moves beyond pure stationery
B15: Comparable to Pidilite, Colgate-type branded consumer plays with school/kirana distribution
A16: Implication: | B16: Justifies premium multiples (50-70x P/E) vs. pure stationery peers (25-30x P/E)
A18: MODEL CONTENTS
A19: Tab | B19: Description
A20: 1. Revenue Build | B20: Segment-wise forecast: Stationery, Hygiene, Exports - with detailed Y-o-Y demand drivers
A21: 2. Assumptions | B21: All hardcoded inputs: growth rates, margins, WACC, multiples (Blue font = input)
A22: 3. Income Statement | B22: Consolidated P&L: FY22–FY25 (Actuals) + FY26E–FY30E (Projected)
A23: 4. Balance Sheet | B23: Consolidated BS: Historical + Projected, linked to IS & CFS
A24: 5. Cash Flow Statement | B24: Indirect method CFS with Free Cash Flow derivation
A25: 6. Working Capital | B25: Days-based WC schedule driving Balance Sheet items
A26: 7. Debt Schedule | B26: Debt roll-forward, interest expense, repayments
A27: 8. DCF Valuation | B27: FCFF-based DCF | WACC: 12.4% | Terminal Growth: 6.5% | Sensitivity table
A28: 9. Trading Comps | B28: DOMS vs. Flair, Kokuyo Camlin, Linc, Navneet + FMCG lateral comps
A29: 10. Precedent Transactions | B29: FILA-DOMS (2012-15), Kokuyo-Camlin (2011), Linc-Mitsubishi (2025)
A30: 11. Returns Analysis | B30: PE-style: Entry valuation, IRR, MOIC, scenario analysis
A31: 12. Investment Thesis | B31: Key thesis, risks, mitigants, due diligence focus (within Returns tab)
A33: COLOR CODE LEGEND
A34: Hardcoded Input | B34: Blue font = assumptions user can change
A35: Formula / Calculation | B35: Black font = formula-driven
A36: Cross-sheet Link | B36: Green font = pulls from another tab
A37: Key Assumption | B37: Yellow highlight = key assumption needing attention

Sheet Revenue Build
A1: DOMS INDUSTRIES LTD — REVENUE BUILD
B3: FY22A | C3: FY23A | D3: FY24A | E3: FY25A | F3: FY26E | G3: FY27E | H3: FY28E | I3: FY29E | J3: FY30E | K3: FY31E | L3: FY32E | M3: FY33E | N3: FY34E | O3: FY35E
A4: PRODUCT CATEGORY REVENUE (₹ Cr)
A5: Scholastic Stationery (pencils, erasers, etc.) | B5: 246 | C5: 435 | D5: 523 | E5: 650 | F5: =E5*(1+F29) -> 781.84543 | G5: =F5*(1+G29) -> 936.03019 | H5: =G5*(1+H29) -> 1108.1479 | I5: =H5*(1+I29) -> 1303.9563 | J5: =I5*(1+J29) -> 1527.1375 | K5: =J5*(1+K29) -> 1775.1521 | L5: =K5*(1+L29) -> 2046.9953 | M5: =L5*(1+M29) -> 2345.0309 | ... O5: =N5*(1+O29) -> 3025.0213
A6: Scholastic Art Material (colors, crayons) | B6: 178 | C6: 316 | D6: 398 | E6: 460 | F6: =E6*(1+F30) -> 551.89089 | G6: =F6*(1+G30) -> 667.02152 | H6: =G6*(1+H30) -> 796.10625 | I6: =H6*(1+I30) -> 943.96838 | J6: =I6*(1+J30) -> 1112.1001 | K6: =J6*(1+K30) -> 1301.1115 | L6: =K6*(1+L30) -> 1511.9965 | M6: =L6*(1+M30) -> 1744.023 | ... O6: =N6*(1+O30) -> 2273.016
A7: Office Supplies (pens, markers, boards) | B7: 43 | C7: 76 | D7: 110 | E7: 160 | F7: =E7*(1+F31) -> 203.95968 | G7: =F7*(1+G31) -> 258.00832 | H7: =G7*(1+H31) -> 324.04325 | I7: =H7*(1+I31) -> 401.98653 | J7: =I7*(1+J31) -> 493.04439 | K7: =J7*(1+K31) -> 597.05116 | L7: =K7*(1+L31) -> 711.99835 | M7: =L7*(1+M31) -> 837.01103 | ... O7: =N7*(1+O31) -> 1119.0079
A8: Paper Stationery (notebooks, diaries) | B8: 68 | C8: 121 | D8: 146 | E8: 180 | F8: =E8*(1+F32) -> 219.95651 | G8: =F8*(1+G32) -> 266.00858 | H8: =G8*(1+H32) -> 318.04245 | I8: =H8*(1+I32) -> 378.9873 | J8: =I8*(1+J32) -> 446.04016 | K8: =J8*(1+K32) -> 522.04474 | L8: =K8*(1+L32) -> 606.99859 | M8: =L8*(1+M32) -> 700.00923 | ... O8: =N8*(1+O32) -> 912.00642
A9: Kits & Combos | B9: 59 | C9: 106 | D9: 138 | E9: 175 | F9: =E9*(1+F33) -> 214.9575 | G9: =F9*(1+G33) -> 261.00842 | H9: =G9*(1+H33) -> 315.04204 | I9: =H9*(1+I33) -> 376.98737 | J9: =I9*(1+J33) -> 447.04025 | K9: =J9*(1+K33) -> 523.04482 | L9: =K9*(1+L33) -> 607.99859 | M9: =L9*(1+M33) -> 701.00924 | ... O9: =N9*(1+O33) -> 913.00643
A10: Hobby & Craft + Fine Art | B10: 27 | C10: 48 | D10: 62 | E10: 80 | F10: =E10*(1+F34) -> 99.980234 | G10: =F10*(1+G34) -> 124.004 | H10: =G10*(1+H34) -> 152.02029 | I10: =H10*(1+I34) -> 183.99384 | J10: =I10*(1+J34) -> 220.01981 | K10: =J10*(1+K34) -> 261.02237 | L10: =K10*(1+L34) -> 306.99929 | M10: =L10*(1+M34) -> 357.00471 | ... O10: =N10*(1+O34) -> 470.00331
A11: Hygiene (Uniclan - Wowper Diapers) | B11: 0 | C11: 0 | D11: 0 | E11: 88 | F11: =E11*(1+F35) -> 132.97371 | G11: =F11*(1+G35) -> 176.00568 | H11: =G11*(1+H35) -> 227.0303 | I11: =H11*(1+I35) -> 284.99045 | J11: =I11*(1+J35) -> 350.03152 | K11: =J11*(1+K35) -> 424.03634 | L11: =K11*(1+L35) -> 505.99883 | M11: =L11*(1+M35) -> 596.00786 | ... O11: =N11*(1+O35) -> 799.00562
A12: Other (Bags JV, Toys, Misc) | B12: 63 | C12: 110 | D12: 161 | E12: 120 | F12: =E12*(1+F36) -> 146.97094 | G12: =F12*(1+G36) -> 182.00587 | H12: =G12*(1+H36) -> 218.0291 | I12: =H12*(1+I36) -> 257.99136 | J12: =I12*(1+J36) -> 302.02719 | K12: =J12*(1+K36) -> 351.03008 | L12: =K12*(1+L36) -> 404.99906 | M12: =L12*(1+M36) -> 463.0061 | ... O12: =N12*(1+O36) -> 596.00419
A14: TOTAL REVENUE | B14: =SUM(B5:B12) -> 684 | C14: =SUM(C5:C12) -> 1212 | D14: =SUM(D5:D12) -> 1538 | E14: =SUM(E5:E12) -> 1913 | F14: =SUM(F5:F12) -> 2352.5349 | G14: =SUM(G5:G12) -> 2870.0926 | H14: =SUM(H5:H12) -> 3458.4616 | I14: =SUM(I5:I12) -> 4132.8616 | ... O14: =SUM(O5:O12) -> 10107.071
A15: Δ vs Top-Down Assumptions (should be ~0) | B15: =B14-Assumptions!B5 -> -2.2 | C15: =C14-Assumptions!C5 -> 0.11 | D15: =D14-Assumptions!D5 -> 0.86 | E15: =E14-Assumptions!E5 -> 0.37
A17: REVENUE FORECAST ASSUMPTIONS; FOR DETAILED Y-O-Y GROWTH ASSUMPTIONS SEE CELL COMMENTS
A18: Scholastic Stationery: | B18: Core pencil franchise growing 15-17% driven by (1) wooden pencil capacity scaling to 7M/day from 5.5M, (2) polymer pencil gains, (3) price increases post-GST normalization. Pencil share declining from 32% to 28% of mix as other categories grow faster.
A19: Scholastic Art Material: | B19: 20%+ growth driven by new product launches (premium color pencils, sketch pens), school art competitions (DOMS Art League reach expanding), and FILA technology transfer for high-end art supplies.
A20: Office Supplies: | B20: Fastest growing segment (25%+ growth). New pen plant operational, highlighters/markers launched. Capacity was constraint - third plant now running. Share gaining from Cello/Reynolds.
A21: Paper Stationery: | B21: 20% growth via Super Treads acquisition (51% stake). Notebooks business scales in East India. Margin accretive as paper procurement integrated.
A22: Kits & Combos: | B22: High-growth (~20%) back-to-school segment. SKIDO subsidiary (bags, packaging) supports kit assembly. Premium kit pricing improves realization.
A23: Hobby & Craft: | B23: Niche but high-margin. Growing 22%+ as 'creative play' trend gains. Leverages FILA's art product portfolio (Giotto, Lyra technology).
A24: Hygiene (Uniclan): | B24: Baby diaper market ~₹8,000 Cr, growing 15%+ CAGR. Wowper brand reaches 8 states via DOMS distribution. Capacity expanding. EBITDA margin to stabilize at 7.5-8%. Target ₹300+ Cr by FY30.
A25: Bags & Others: | B25: Seven S.p.A JV (50:50) for premium backpacks. Manufacturing from Q1 FY27. ClapJoy toys (30% stake) growing 35% YoY. Combined small base but high optionality.
A26: Export Strategy: | B26: FILA distribution agreement drives repeat orders globally. Exports at 11-13% of revenue, targeting 13-15% by FY30. US tariff risk managed via geographic diversification.
A28: SEGMENT GROWTH RATES ASSUMPTIONS (% YoY)
A29: Scholastic Stationery | C29: =IF(B5>0,(C5-B5)/B5,0) -> 0.76829268 | D29: =IF(C5>0,(D5-C5)/C5,0) -> 0.20229885 | E29: =IF(D5>0,(E5-D5)/D5,0) -> 0.24282983 | F29: 0.20283912 | G29: 0.1972062 | H29: 0.1838805 | I29: 0.17669883 | J29: 0.17115694 | K29: 0.1624049 | L29: 0.15313794 | M29: 0.14559665 | N29: 0.13727944 | O29: 0.13426015
A30: Scholastic Art Material | C30: =IF(B6>0,(C6-B6)/B6,0) -> 0.7752809 | D30: =IF(C6>0,(D6-C6)/C6,0) -> 0.25949367 | E30: =IF(D6>0,(E6-D6)/D6,0) -> 0.15577889 | F30: 0.1997628 | G30: 0.20861121 | H30: 0.19352409 | I30: 0.18573166 | J30: 0.17811163 | K30: 0.16995895 | L30: 0.16208066 | M30: 0.15345703 | N30: 0.1444612 | O30: 0.1388046
A31: Office Supplies | C31: =IF(B7>0,(C7-B7)/B7,0) -> 0.76744186 | D31: =IF(C7>0,(D7-C7)/C7,0) -> 0.44736842 | E31: =IF(D7>0,(E7-D7)/D7,0) -> 0.45454545 | F31: 0.27474798 | G31: 0.26499672 | H31: 0.25594106 | I31: 0.2405336 | J31: 0.22651967 | K31: 0.21094809 | L31: 0.19252486 | M31: 0.17558002 | N31: 0.1600609 | O31: 0.15244755
A32: Paper Stationery | C32: =IF(B8>0,(C8-B8)/B8,0) -> 0.77941176 | D32: =IF(C8>0,(D8-C8)/C8,0) -> 0.20661157 | E32: =IF(D8>0,(E8-D8)/D8,0) -> 0.23287671 | F32: 0.22198063 | G32: 0.20936896 | H32: 0.19560972 | I32: 0.19162493 | J32: 0.17692639 | K32: 0.1703985 | L32: 0.16273291 | M32: 0.15323039 | N32: 0.14425151 | O32: 0.13860382
A33: Kits & Combos | C33: =IF(B9>0,(C9-B9)/B9,0) -> 0.79661017 | D33: =IF(C9>0,(D9-C9)/C9,0) -> 0.30188679 | E33: =IF(D9>0,(E9-D9)/D9,0) -> 0.26811594 | F33: 0.22832859 | G33: 0.21423266 | H33: 0.20701871 | I33: 0.19662559 | J33: 0.18582288 | K33: 0.17001729 | L33: 0.16242159 | M33: 0.15297839 | N33: 0.14404569 | O33: 0.13843102
A34: Hobby & Craft | C34: =IF(B10>0,(C10-B10)/B10,0) -> 0.77777778 | D34: =IF(C10>0,(D10-C10)/C10,0) -> 0.29166667 | E34: =IF(D10>0,(E10-D10)/D10,0) -> 0.29032258 | F34: 0.24975292 | G34: 0.24028516 | H34: 0.22593052 | I34: 0.21032422 | J34: 0.19579989 | K34: 0.18635848 | L34: 0.17614169 | M34: 0.16288447 | N34: 0.15122609 | O34: 0.14357947
A35: Hygiene (Uniclan) | C35: =IF(B11>0,(C11-B11)/B11,0) -> 0 | D35: =IF(C11>0,(D11-C11)/C11,0) -> 0 | E35: =IF(D11>0,(E11-D11)/D11,0) -> 0 | F35: 0.5110649 | G35: 0.32361259 | H35: 0.28990327 | I35: 0.255297 | J35: 0.2282219 | K35: 0.21142331 | L35: 0.1932912 | M35: 0.17788387 | N35: 0.16103912 | O35: 0.1546517
A36: Other | C36: =IF(B12>0,(C12-B12)/B12,0) -> 0.74603175 | D36: =IF(C12>0,(D12-C12)/C12,0) -> 0.46363636 | E36: =IF(D12>0,(E12-D12)/D12,0) -> -0.25465839 | F36: 0.22475786 | G36: 0.23837996 | H36: 0.19792343 | I36: 0.18328866 | J36: 0.17068725 | K36: 0.16224661 | L36: 0.15374461 | M36: 0.14322759 | N36: 0.13603516 | O36: 0.13310675
A38: REVENUE MIX (% of Total)
A39: Scholastic Stationery | B39: =IF(B14>0,B5/B14,0) -> 0.35964912 | C39: =IF(C14>0,C5/C14,0) -> 0.35891089 | D39: =IF(D14>0,D5/D14,0) -> 0.34005202 | E39: =IF(E14>0,E5/E14,0) -> 0.33978045 | F39: =IF(F14>0,F5/F14,0) -> 0.33234169 | G39: =IF(G14>0,G5/G14,0) -> 0.3261324 | H39: =IF(H14>0,H5/H14,0) -> 0.32041643 | I39: =IF(I14>0,I5/I14,0) -> 0.31550932 | ... O39: =IF(O14>0,O5/O14,0) -> 0.29929752
A40: Scholastic Art Material | B40: =IF(B14>0,B6/B14,0) -> 0.26023392 | C40: =IF(C14>0,C6/C14,0) -> 0.26072607 | D40: =IF(D14>0,D6/D14,0) -> 0.25877763 | E40: =IF(E14>0,E6/E14,0) -> 0.24046001 | F40: =IF(F14>0,F6/F14,0) -> 0.23459414 | G40: =IF(G14>0,G6/G14,0) -> 0.23240418 | H40: =IF(H14>0,H6/H14,0) -> 0.23019086 | I40: =IF(I14>0,I6/I14,0) -> 0.22840552 | ... O40: =IF(O14>0,O6/O14,0) -> 0.22489364
A41: Office Supplies | B41: =IF(B14>0,B7/B14,0) -> 0.062865497 | C41: =IF(C14>0,C7/C14,0) -> 0.062706271 | D41: =IF(D14>0,D7/D14,0) -> 0.071521456 | E41: =IF(E14>0,E7/E14,0) -> 0.083638265 | F41: =IF(F14>0,F7/F14,0) -> 0.086697833 | G41: =IF(G14>0,G7/G14,0) -> 0.08989547 | H41: =IF(H14>0,H7/H14,0) -> 0.093695778 | I41: =IF(I14>0,I7/I14,0) -> 0.097265909 | ... O41: =IF(O14>0,O7/O14,0) -> 0.11071535
A42: Paper Stationery | B42: =IF(B14>0,B8/B14,0) -> 0.099415205 | C42: =IF(C14>0,C8/C14,0) -> 0.099834983 | D42: =IF(D14>0,D8/D14,0) -> 0.094928479 | E42: =IF(E14>0,E8/E14,0) -> 0.094093048 | F42: =IF(F14>0,F8/F14,0) -> 0.093497663 | G42: =IF(G14>0,G8/G14,0) -> 0.092682927 | H42: =IF(H14>0,H8/H14,0) -> 0.091960671 | I42: =IF(I14>0,I8/I14,0) -> 0.091700944 | ... O42: =IF(O14>0,O8/O14,0) -> 0.090234491
A43: Kits & Combos | B43: =IF(B14>0,B9/B14,0) -> 0.08625731 | C43: =IF(C14>0,C9/C14,0) -> 0.087458746 | D43: =IF(D14>0,D9/D14,0) -> 0.089726918 | E43: =IF(E14>0,E9/E14,0) -> 0.091479352 | F43: =IF(F14>0,F9/F14,0) -> 0.091372716 | G43: =IF(G14>0,G9/G14,0) -> 0.090940767 | H43: =IF(H14>0,H9/H14,0) -> 0.091093117 | I43: =IF(I14>0,I9/I14,0) -> 0.091217034 | ... O43: =IF(O14>0,O9/O14,0) -> 0.090333432
A44: Hobby & Craft | B44: =IF(B14>0,B10/B14,0) -> 0.039473684 | C44: =IF(C14>0,C10/C14,0) -> 0.03960396 | D44: =IF(D14>0,D10/D14,0) -> 0.040312094 | E44: =IF(E14>0,E10/E14,0) -> 0.041819132 | F44: =IF(F14>0,F10/F14,0) -> 0.042498938 | G44: =IF(G14>0,G10/G14,0) -> 0.043205575 | H44: =IF(H14>0,H10/H14,0) -> 0.043956044 | I44: =IF(I14>0,I10/I14,0) -> 0.044519719 | ... O44: =IF(O14>0,O10/O14,0) -> 0.046502424
A45: Hygiene (Uniclan) | B45: =IF(B14>0,B11/B14,0) -> 0 | C45: =IF(C14>0,C11/C14,0) -> 0 | D45: =IF(D14>0,D11/D14,0) -> 0 | E45: =IF(E14>0,E11/E14,0) -> 0.046001045 | F45: =IF(F14>0,F11/F14,0) -> 0.056523587 | G45: =IF(G14>0,G11/G14,0) -> 0.061324042 | H45: =IF(H14>0,H11/H14,0) -> 0.065644881 | I45: =IF(I14>0,I11/I14,0) -> 0.068957174 | ... O45: =IF(O14>0,O11/O14,0) -> 0.079054121
A46: Other | B46: =IF(B14>0,B12/B14,0) -> 0.092105263 | C46: =IF(C14>0,C12/C14,0) -> 0.090759076 | D46: =IF(D14>0,D12/D14,0) -> 0.1046814 | E46: =IF(E14>0,E12/E14,0) -> 0.062728698 | F46: =IF(F14>0,F12/F14,0) -> 0.062473438 | G46: =IF(G14>0,G12/G14,0) -> 0.063414634 | H46: =IF(H14>0,H12/H14,0) -> 0.063042221 | I46: =IF(I14>0,I12/I14,0) -> 0.062424389 | ... O46: =IF(O14>0,O12/O14,0) -> 0.058969031
A47: TOTAL | B47: =SUM(B39:B46) -> 1 | C47: =SUM(C39:C46) -> 1 | D47: =SUM(D39:D46) -> 1 | E47: =SUM(E39:E46) -> 1 | F47: =SUM(F39:F46) -> 1 | G47: =SUM(G39:G46) -> 1 | H47: =SUM(H39:H46) -> 1 | I47: =SUM(I39:I46) -> 1 | ... O47: =SUM(O39:O46) -> 1

Sheet Assumptions
A1: DOMS INDUSTRIES LTD — KEY ASSUMPTIONS
A2: Blue font = hardcoded input | Yellow = key assumption | Black = formula
B3: FY22A | C3: FY23A | D3: FY24A | E3: FY25A | F3: FY26E | G3: FY27E | H3: FY28E | I3: FY29E | J3: FY30E | K3: FY31E | L3: FY32E | M3: FY33E | N3: FY34E | O3: FY35E
A4: REVENUE ASSUMPTIONS
A5: Consolidated Revenue (₹ Cr) | B5: 686.2 | C5: 1211.89 | D5: 1537.14 | E5: 1912.63 | F5: ='Income Statement'!F4 -> 2352.5349 | G5: ='Income Statement'!G4 -> 2870.0926 | H5: ='Income Statement'!H4 -> 3458.4616 | I5: ='Income Statement'!I4 -> 4132.8616 | J5: ='Income Statement'!J4 -> 4897.4409 | K5: ='Income Statement'!K4 -> 5754.4931 | L5: ='Income Statement'!L4 -> 6703.9845 | M5: ='Income Statement'!M4 -> 7743.1021 | ... O5: ='Income Statement'!O4 -> 10107.071
A6: Revenue YoY Growth (%) | C6: =(C5-B5)/B5 -> 0.7660886 | D6: 0.2683 | E6: 0.2443 | F6: =(F5-E5)/E5 -> 0.23 | G6: =(G5-F5)/F5 -> 0.22 | H6: =(H5-G5)/G5 -> 0.205 | I6: =(I5-H5)/H5 -> 0.195 | J6: =(J5-I5)/I5 -> 0.185 | K6: =(K5-J5)/J5 -> 0.175 | L6: =(L5-K5)/K5 -> 0.165 | M6: =(M5-L5)/L5 -> 0.155 | ... O6: =(O5-N5)/N5 -> 0.14
A7: Note: Revenue & growth are derived from bottom-up Revenue Build (segment-level). Margins below remain as key assumptions.
A8: Domestic Revenue Share (%) | B8: 0.87 | C8: 0.87 | D8: 0.87 | E8: 0.887 | F8: 0.885 | G8: 0.88 | H8: 0.875 | I8: 0.87 | J8: 0.865 | K8: 0.86 | L8: 0.855 | M8: 0.85 | N8: 0.845 | O8: 0.84
A9: Export Revenue Share (%) | B9: 0.13 | C9: 0.13 | D9: 0.13 | E9: 0.113 | F9: 0.115 | G9: 0.12 | H9: 0.125 | I9: 0.13 | J9: 0.135 | K9: 0.14 | L9: 0.145 | M9: 0.15 | N9: 0.155 | O9: 0.16
A11: MARGIN ASSUMPTIONS
A12: Gross Margin (%) | B12: 0.31 | C12: 0.356 | D12: 0.4192 | E12: 0.435 | F12: 0.435 | G12: 0.44 | H12: 0.445 | I12: 0.448 | J12: 0.45 | K12: 0.45 | L12: 0.452 | M12: 0.453 | N12: 0.455 | O12: 0.455
A13: EBITDA Margin (%) | B13: =B12-B15-B16 -> 0.102 | C13: =C12-C15-C16 -> 0.154 | D13: =D12-D15-D16 -> 0.1774 | E13: =E12-E15-E16 -> 0.1821 | F13: =F12-F15-F16 -> 0.175 | G13: =G12-G15-G16 -> 0.184 | H13: =H12-H15-H16 -> 0.195 | I13: =I12-I15-I16 -> 0.202 | ... O13: =O12-O15-O16 -> 0.227
A14: Guided EBITDA: 16.5-17.5% FY26
A15: Employee Cost (% of Rev) | B15: 0.12 | C15: 0.11 | D15: 0.1386 | E15: 0.1387 | F15: 0.14 | G15: 0.138 | H15: 0.135 | I15: 0.133 | J15: 0.13 | K15: 0.128 | L15: 0.126 | M15: 0.125 | N15: 0.125 | O15: 0.125
A16: Other Expenses (% of Rev) | B16: 0.088 | C16: 0.092 | D16: 0.1032 | E16: 0.1142 | F16: 0.12 | G16: 0.118 | H16: 0.115 | I16: 0.113 | J16: 0.11 | K16: 0.108 | L16: 0.106 | M16: 0.105 | N16: 0.103 | O16: 0.103
A17: D&A (% of Revenue) | B17: 0.0554 | C17: 0.0336 | D17: 0.0333 | E17: 0.0362 | F17: 0.035 | G17: 0.038 | H17: 0.037 | I17: 0.036 | J17: 0.035 | K17: 0.034 | L17: 0.033 | M17: 0.032 | N17: 0.031 | O17: 0.03
A18: Effective Tax Rate (%) | B18: 0.26 | C18: 0.254 | D18: 0.2556 | E18: 0.2555 | F18: 0.255 | G18: 0.255 | H18: 0.255 | I18: 0.255 | J18: 0.255 | K18: 0.255 | L18: 0.255 | M18: 0.255 | N18: 0.255 | O18: 0.255
A20: BALANCE SHEET & WORKING CAPITAL
A21: Receivable Days | B21: 45 | C21: 42 | D21: 15 | E21: 26 | F21: 28 | G21: 30 | H21: 30 | I21: 30 | J21: 30 | K21: 30 | L21: 30 | M21: 30 | N21: 30 | O21: 30
A22: Inventory Days | B22: 90 | C22: 85 | D22: 53 | E22: 56 | F22: 56 | G22: 56 | H22: 55 | I22: 54 | J22: 53 | K22: 52 | L22: 51 | M22: 50 | N22: 49 | O22: 48
A23: Payable Days | B23: 81 | C23: 79 | D23: 36 | E23: 37 | F23: 38 | G23: 40 | H23: 42 | I23: 44 | J23: 46 | K23: 48 | L23: 50 | M23: 52 | N23: 54 | O23: 55
A25: CAPEX & INVESTMENT
A26: Capex (₹ Cr) | B26: 30 | C26: 50 | D26: 152.81 | E26: 210.02 | F26: 250 | G26: 240 | H26: 150 | I26: 130 | J26: 100 | K26: 100 | L26: 90 | M26: 90 | N26: 90 | O26: 90
A27: Capex as % of Revenue | B27: =IF(B5>0,B26/B5,0) -> 0.043719032 | C27: =IF(C5>0,C26/C5,0) -> 0.04125787 | D27: =IF(D5>0,D26/D5,0) -> 0.099411895 | E27: =IF(E5>0,E26/E5,0) -> 0.10980692 | F27: =IF(F5>0,F26/F5,0) -> 0.10626835 | G27: =IF(G5>0,G26/G5,0) -> 0.083620996 | H27: =IF(H5>0,H26/H5,0) -> 0.043371886 | I27: =IF(I5>0,I26/I5,0) -> 0.031455203 | ... O27: =IF(O5>0,O26/O5,0) -> 0.0089046568
A28: CFO Guided: ₹250 Cr FY26, ₹225-250 Cr FY27
A29: VALUATION ASSUMPTIONS
A30: WACC (%) | B30: 0.124
A31: Terminal Growth Rate (%) | B31: 0.065
A32: Risk-Free Rate (10Y GOI bond) | B32: 0.067
A33: Equity Risk Premium | B33: 0.07
A34: Levered Beta | B34: 0.85
A35: Cost of Equity (Ke) | B35: =B32+B34*B33 -> 0.1265
A36: Cost of Debt (pre-tax) | B36: 0.0875 | F36: 0.0875 | G36: 0.0875 | H36: 0.085 | I36: 0.085 | J36: 0.0825 | K36: 0.0825 | L36: 0.0825 | M36: 0.0825 | N36: 0.0825 | O36: 0.0825
A37: Debt / Total Capital | B37: 0.05
A38: Calculated WACC | B38: =B35*(1-B37)+B36*(1-Assumptions!B18)*B37 -> 0.1234125 | C38: =(((1+F38)*(1+G38)*(1+H38)*(1+I38)*(1+J38)*(1+K38)*(1+L38)*(1+M38)*(1+N38)*(1+O38))^(1/10))-1 -> 0.123283 | F38: =B35*(1-B37)+F36*(1-B18)*B37 -> 0.1234125 | G38: =B35*(1-B37)+G36*(1-B18)*B37 -> 0.1234125 | H38: =B35*(1-B37)+H36*(1-B18)*B37 -> 0.12332 | I38: =B35*(1-B37)+I36*(1-B18)*B37 -> 0.12332 | J38: =B35*(1-B37)+J36*(1-B18)*B37 -> 0.1232275 | K38: =B35*(1-B37)+K36*(1-B18)*B37 -> 0.1232275 | L38: =B35*(1-B37)+L36*(1-B18)*B37 -> 0.1232275 | M38: =B35*(1-B37)+M36*(1-B18)*B37 -> 0.1232275 | N38: =B35*(1-B37)+N36*(1-B18)*B37 -> 0.1232275 | O38: =B35*(1-B37)+O36*(1-B18)*B37 -> 0.1232275
A39: WACC Override (used in model) | B39: =B30 -> 0.124
A40: WACC JUSTIFICATION
A41: Ke = 6.7% + 0.85 x 7% = 12.65% | B41: Low beta: low cyclicality, essential school spend, branded moat
A42: Kd = 8.75%; D/TC = 5% | B42: Near debt-free; minimal leverage
A43: Terminal Growth = 6% | B43: India nominal GDP ~10%; stationery structural growth ~12%; 6% is conservative
A45: MANAGEMENT GUIDANCE vs ACTUAL DELIVERY
A46: Walk the Talk Analysis - Tracking Management Credibility
A48: Metric / Period | B48: Guidance | C48: Actual | D48: Verdict
A49: FY25 REVENUE GROWTH
A50: Annual Target | B50: 18-20% | C50: 0.244 | D50: BEAT
A51: Q1 FY25 | B51: Strong growth | C51: ~25% YoY | D51: DELIVERED
A52: Q2 FY25 | B52: Maintain trajectory | C52: ~24% YoY | D52: DELIVERED
A53: Q3 FY25 | B53: Upper end of range | C53: ~35% YoY | D53: BEAT (festive season)
A54: Q4 FY25 | B54: Seasonal normalization | C54: ~26% YoY | D54: BEAT
A56: FY25 EBITDA MARGIN
A57: Annual Target | B57: 16.5-17.5% | C57: 0.182 | D57: BEAT
A58: Commentary | B58: Input cost pressures | C58: Managed through backward integration | D58: BEAT
A60: FY26 REVENUE GROWTH (In Progress)
A61: Annual Target | B61: 18-20% (bias upper) | C61: 9M: 22.7% YoY | D61: TRACKING ABOVE
A62: Q1 FY26 | B62: Steady growth | C62: 26.4% YoY | D62: BEAT
A63: Q2 FY26 | B63: Maintain momentum | C63: 24.1% YoY | D63: BEAT
A64: Q3 FY26 | B64: Seasonal normalization | C64: 18.2% YoY | D64: AT UPPER END
A66: FY26 EBITDA MARGIN
A67: Annual Target | B67: 16.5-17.5% | C67: 9M: 17.5% | D67: AT UPPER END
A69: CAPACITY EXPANSION
A70: 44-Acre Facility Timeline | B70: Q3 FY26 possession | C70: Slight delay; Q4 FY26 now | D70: MINOR DELAY (monsoon)
A71: Commercial Production | B71: Q4 FY26 start | C71: Q1-Q2 FY27 expected | D71: ON TRACK (rolling)
A72: Distribution Target | B72: 145,000 outlets | C72: 145,000 achieved | D72: DELIVERED
A74: CAPEX GUIDANCE
A75: FY25 Capex | B75: ₹160-175 Cr | C75: ₹210-225 Cr | D75: EXCEEDED (accelerated)
A76: FY26 Capex | B76: ₹160-175 Cr (revised up) | C76: 9M: ₹230+ Cr | D76: EXCEEDED (good sign)
A78: HISTORICAL 5-YEAR TRACK RECORD
A79: Revenue CAGR FY20-FY25 | B79: N/A (no explicit) | C79: ~24% CAGR | D79: EXCELLENT
A80: PAT CAGR FY20-FY25 | B80: N/A | C80: ~41% CAGR | D80: EXCEPTIONAL
A81: Margin Trajectory | B81: Guided improvement | C81: 10.2% → 18.2% EBITDA | D81: OUTSTANDING
A83: VERDICT: STRONG 'WALK THE TALK' TRACK RECORD
A84: Pattern: Conservative guidance → Consistent outperformance
A85: Transparency: Proactively communicated facility delays
A86: Credibility Score (1-5): 4.6/5
A89: SHARES & DIVIDEND
A90: Shares Outstanding (Cr) | B90: 6.069
A91: Dividend Payout Ratio (%) | B91: 0.094
A92: Current Market Price (₹) | B92: 2350

Sheet Income Statement
A1: DOMS INDUSTRIES LTD — CONSOLIDATED INCOME STATEMENT
A2: (₹ Crores)
B3: FY22A | C3: FY23A | D3: FY24A | E3: FY25A | F3: FY26E | G3: FY27E | H3: FY28E | I3: FY29E | J3: FY30E | K3: FY31E | L3: FY32E | M3: FY33E | N3: FY34E | O3: FY35E
A4: Revenue from Operations | B4: 686.2 | C4: =Assumptions!C5 -> 1211.89 | D4: =Assumptions!D5 -> 1537.14 | E4: =Assumptions!E5 -> 1912.63 | F4: ='Revenue Build'!F14 -> 2352.5349 | G4: ='Revenue Build'!G14 -> 2870.0926 | H4: ='Revenue Build'!H14 -> 3458.4616 | I4: ='Revenue Build'!I14 -> 4132.8616 | J4: ='Revenue Build'!J14 -> 4897.4409 | K4: ='Revenue Build'!K14 -> 5754.4931 | L4: ='Revenue Build'!L14 -> 6703.9845 | M4: ='Revenue Build'!M14 -> 7743.1021 | ... O4: ='Revenue Build'!O14 -> 10107.071
A5: YoY Growth (%) | C5: =(C4-B4)/B4 -> 0.7660886 | D5: =(D4-C4)/C4 -> 0.26838244 | E5: =(E4-D4)/D4 -> 0.24427834 | F5: =(F4-E4)/E4 -> 0.23 | G5: =(G4-F4)/F4 -> 0.22 | H5: =(H4-G4)/G4 -> 0.205 | I5: =(I4-H4)/H4 -> 0.195 | J5: =(J4-I4)/I4 -> 0.185 | ... O5: =(O4-N4)/N4 -> 0.14
A7: Cost of Materials Consumed | B7: -473.48 | C7: -780.46 | D7: -892.75 | E7: -1080.6 | F7: =-F4*(1-Assumptions!F12) -> -1329.1822 | G7: =-G4*(1-Assumptions!G12) -> -1607.2518 | H7: =-H4*(1-Assumptions!H12) -> -1919.4462 | I7: =-I4*(1-Assumptions!I12) -> -2281.3396 | J7: =-J4*(1-Assumptions!J12) -> -2693.5925 | K7: =-K4*(1-Assumptions!K12) -> -3164.9712 | L7: =-L4*(1-Assumptions!L12) -> -3673.7835 | M7: =-M4*(1-Assumptions!M12) -> -4235.4768 | ... O7: =-O4*(1-Assumptions!O12) -> -5508.3538
A8: Gross Profit | B8: =B4+B7 -> 212.72 | C8: =C4+C7 -> 431.43 | D8: =D4+D7 -> 644.39 | E8: =E4+E7 -> 832.03 | F8: =F4+F7 -> 1023.3527 | G8: =G4+G7 -> 1262.8407 | H8: =H4+H7 -> 1539.0154 | I8: =I4+I7 -> 1851.522 | ... O8: =O4+O7 -> 4598.7174
A9: Gross Margin (%) | B9: =IF(B4>0,B8/B4,0) -> 0.30999709 | C9: =IF(C4>0,C8/C4,0) -> 0.35599766 | D9: =IF(D4>0,D8/D4,0) -> 0.4192136 | E9: =IF(E4>0,E8/E4,0) -> 0.4350188 | F9: =IF(F4>0,F8/F4,0) -> 0.435 | G9: =IF(G4>0,G8/G4,0) -> 0.44 | H9: =IF(H4>0,H8/H4,0) -> 0.445 | I9: =IF(I4>0,I8/I4,0) -> 0.448 | ... O9: =IF(O4>0,O8/O4,0) -> 0.455
A11: Employee Benefit Expenses | B11: -82.34 | C11: -133.31 | D11: -213.06 | E11: -265.24 | F11: =-F4*Assumptions!F15 -> -329.35489 | G11: =-G4*Assumptions!G15 -> -396.07278 | H11: =-H4*Assumptions!H15 -> -466.89231 | I11: =-I4*Assumptions!I15 -> -549.67059 | J11: =-J4*Assumptions!J15 -> -636.66732 | K11: =-K4*Assumptions!K15 -> -736.57512 | L11: =-L4*Assumptions!L15 -> -844.70204 | M11: =-M4*Assumptions!M15 -> -967.88776 | ... O11: =-O4*Assumptions!O15 -> -1263.3839
A12: Other Expenses | B12: -60.39 | C12: -111.49 | D12: -158.6 | E12: -218.34 | F12: =-F4*Assumptions!F16 -> -282.30419 | G12: =-G4*Assumptions!G16 -> -338.67092 | H12: =-H4*Assumptions!H16 -> -397.72308 | I12: =-I4*Assumptions!I16 -> -467.01336 | J12: =-J4*Assumptions!J16 -> -538.7185 | K12: =-K4*Assumptions!K16 -> -621.48526 | L12: =-L4*Assumptions!L16 -> -710.62235 | M12: =-M4*Assumptions!M16 -> -813.02572 | ... O12: =-O4*Assumptions!O16 -> -1041.0283
A14: EBITDA | B14: =B8+B11+B12 -> 69.99 | C14: =C8+C11+C12 -> 186.63 | D14: =D8+D11+D12 -> 272.73 | E14: =E8+E11+E12 -> 348.45 | F14: =F8+F11+F12 -> 411.69361 | G14: =G8+G11+G12 -> 528.09703 | H14: =H8+H11+H12 -> 674.4 | I14: =I8+I11+I12 -> 834.83804 | ... O14: =O8+O11+O12 -> 2294.3051
A15: EBITDA Margin (%) | B15: =IF(B4>0,B14/B4,0) -> 0.1019965 | C15: =IF(C4>0,C14/C4,0) -> 0.15399913 | D15: =IF(D4>0,D14/D4,0) -> 0.17742691 | E15: =IF(E4>0,E14/E4,0) -> 0.18218369 | F15: =IF(F4>0,F14/F4,0) -> 0.175 | G15: =IF(G4>0,G14/G4,0) -> 0.184 | H15: =IF(H4>0,H14/H4,0) -> 0.195 | I15: =IF(I4>0,I14/I4,0) -> 0.202 | ... O15: =IF(O4>0,O14/O4,0) -> 0.227
A17: Depreciation & Amortization | B17: -38.04 | C17: -40.67 | D17: -51.24 | E17: -69.18 | F17: =-F4*Assumptions!F17 -> -82.338722 | G17: =-G4*Assumptions!G17 -> -109.06352 | H17: =-H4*Assumptions!H17 -> -127.96308 | I17: =-I4*Assumptions!I17 -> -148.78302 | J17: =-J4*Assumptions!J17 -> -171.41043 | K17: =-K4*Assumptions!K17 -> -195.65277 | L17: =-L4*Assumptions!L17 -> -221.23149 | M17: =-M4*Assumptions!M17 -> -247.77927 | ... O17: =-O4*Assumptions!O17 -> -303.21213
A18: EBIT | B18: =B14+B17 -> 31.95 | C18: =C14+C17 -> 145.96 | D18: =D14+D17 -> 221.49 | E18: =E14+E17 -> 279.27 | F18: =F14+F17 -> 329.35489 | G18: =G14+G17 -> 419.03352 | H18: =H14+H17 -> 546.43693 | I18: =I14+I17 -> 686.05502 | ... O18: =O14+O17 -> 1991.093
A20: Other Income | B20: 2.62 | C20: 4.63 | D20: 10.13 | E20: 22.6 | F20: 12 | G20: 14 | H20: 16 | I20: 18 | J20: 20 | K20: 22 | L20: 24 | M20: 26 | N20: 28 | O20: 30
A21: Finance Costs | B21: -10.3 | C21: -11.88 | D21: -17.12 | E21: -15.04 | F21: -10 | G21: -10 | H21: -8 | I21: -7 | J21: -6 | K21: -5 | L21: -4 | M21: -4 | N21: -3 | O21: -3
A23: Profit Before Tax (PBT) | B23: =B18+B20+B21 -> 24.27 | C23: =C18+C20+C21 -> 138.71 | D23: =D18+D20+D21 -> 214.5 | E23: =E18+E20+E21 -> 286.83 | F23: =F18+F20+F21 -> 331.35489 | G23: =G18+G20+G21 -> 423.03352 | H23: =H18+H20+H21 -> 554.43693 | I23: =I18+I20+I21 -> 697.05502 | ... O23: =O18+O20+O21 -> 2018.093
A24: Tax Expense | B24: =-ABS(B23)*Assumptions!B18 -> -6.3102 | C24: =-ABS(C23)*Assumptions!C18 -> -35.23234 | D24: =-ABS(D23)*Assumptions!D18 -> -54.8262 | E24: =-ABS(E23)*Assumptions!E18 -> -73.285065 | F24: =-ABS(F23)*Assumptions!F18 -> -84.495496 | G24: =-ABS(G23)*Assumptions!G18 -> -107.87355 | H24: =-ABS(H23)*Assumptions!H18 -> -141.38142 | I24: =-ABS(I23)*Assumptions!I18 -> -177.74903 | ... O24: =-ABS(O23)*Assumptions!O18 -> -514.61372
A26: Profit After Tax (PAT) | B26: =B23+B24 -> 17.9598 | C26: =C23+C24 -> 103.47766 | D26: =D23+D24 -> 159.6738 | E26: =E23+E24 -> 213.54494 | F26: =F23+F24 -> 246.85939 | G26: =G23+G24 -> 315.15997 | H26: =H23+H24 -> 413.05551 | I26: =I23+I24 -> 519.30599 | ... O26: =O23+O24 -> 1503.4793
A27: PAT Margin (%) | B27: =IF(B4>0,B26/B4,0) -> 0.026172836 | C27: =IF(C4>0,C26/C4,0) -> 0.085385357 | D27: =IF(D4>0,D26/D4,0) -> 0.1038772 | E27: =IF(E4>0,E26/E4,0) -> 0.11164989 | F27: =IF(F4>0,F26/F4,0) -> 0.10493336 | G27: =IF(G4>0,G26/G4,0) -> 0.10980829 | H27: =IF(H4>0,H26/H4,0) -> 0.11943331 | I27: =IF(I4>0,I26/I4,0) -> 0.12565289 | ... O27: =IF(O4>0,O26/O4,0) -> 0.14875519
A29: EPS (₹) | B29: =B26/Assumptions!B90 -> 2.9592684 | C29: =C26/Assumptions!B90 -> 17.050199 | D29: =D26/Assumptions!B90 -> 26.309738 | E29: =E26/Assumptions!B90 -> 35.186181 | F29: =F26/Assumptions!B90 -> 40.675464 | G29: =G26/Assumptions!B90 -> 51.929473 | H29: =H26/Assumptions!B90 -> 68.059896 | I29: =I26/Assumptions!B90 -> 85.566978 | J29: =J26/Assumptions!B90 -> 106.926 | K29: =K26/Assumptions!$B$90 -> 129.23752 | L29: =L26/Assumptions!$B$90 -> 156.34628 | M29: =M26/Assumptions!$B$90 -> 184.24695 | N29: =N26/Assumptions!$B$90 -> 216.38107 | O29: =O26/Assumptions!$B$90 -> 247.73098
A30: Dividend per Share (₹) | B30: =B29*Assumptions!B91 -> 0.27817123 | C30: =C29*Assumptions!B91 -> 1.6027187 | D30: =D29*Assumptions!B91 -> 2.4731154 | E30: =E29*Assumptions!B91 -> 3.3075011 | F30: =F29*Assumptions!B91 -> 3.8234936 | G30: =G29*Assumptions!B91 -> 4.8813704 | H30: =H29*Assumptions!B91 -> 6.3976302 | I30: =I29*Assumptions!B91 -> 8.0432959 | J30: =J29*Assumptions!B91 -> 10.051044 | K30: =K29*Assumptions!$B$91 -> 12.148327 | L30: =L29*Assumptions!$B$91 -> 14.696551 | M30: =M29*Assumptions!$B$91 -> 17.319213 | N30: =N29*Assumptions!$B$91 -> 20.33982 | O30: =O29*Assumptions!$B$91 -> 23.286712

Sheet Balance Sheet
A1: DOMS INDUSTRIES LTD — CONSOLIDATED BALANCE SHEET
A2: (₹ Crores)
B3: FY22A | C3: FY23A | D3: FY24A | E3: FY25A | F3: FY26E | G3: FY27E | H3: FY28E | I3: FY29E | J3: FY30E | K3: FY31E | L3: FY32E | M3: FY33E | N3: FY34E | O3: FY35E
A4: ASSETS
A5: Non-Current Assets
A6: Property, Plant & Equipment (Net) | B6: 200 | C6: 230 | D6: 461.13 | E6: 635.19 | F6: =E6+Assumptions!F26+'Income Statement'!F17 -> 802.85128 | G6: =F6+Assumptions!G26+'Income Statement'!G17 -> 933.78776 | H6: =G6+Assumptions!H26+'Income Statement'!H17 -> 955.82468 | I6: =H6+Assumptions!I26+'Income Statement'!I17 -> 937.04167 | J6: =I6+Assumptions!J26+'Income Statement'!J17 -> 865.63123 | K6: =J6+Assumptions!K26+'Income Statement'!K17 -> 769.97847 | L6: =K6+Assumptions!L26+'Income Statement'!L17 -> 638.74698 | M6: =L6+Assumptions!M26+'Income Statement'!M17 -> 480.96771 | ... O6: =N6+Assumptions!O26+'Income Statement'!O17 -> 82.914171
A7: Goodwill & Intangibles | B7: 5 | C7: 5 | D7: 62.44 | E7: 115.5 | F7: 57 | G7: 54 | H7: 51 | I7: 48 | J7: 45 | K7: 42 | L7: 39 | M7: 36 | N7: 33 | O7: 30
A8: Other Non-Current Assets | B8: 20 | C8: 25 | D8: 49.93 | E8: 80.1 | F8: 48 | G8: 50 | H8: 53 | I8: 55 | J8: 58 | K8: 61 | L8: 64 | M8: 67 | N8: 70 | O8: 73
A9: Total Non-Current Assets | B9: =SUM(B6:B8) -> 225 | C9: =SUM(C6:C8) -> 260 | D9: =SUM(D6:D8) -> 573.5 | E9: =SUM(E6:E8) -> 830.79 | F9: =SUM(F6:F8) -> 907.85128 | G9: =SUM(G6:G8) -> 1037.7878 | H9: =SUM(H6:H8) -> 1059.8247 | I9: =SUM(I6:I8) -> 1040.0417 | ... O9: =SUM(O6:O8) -> 185.91417
A11: Current Assets
A12: Inventories | B12: 168 | C12: 282 | D12: 225.1 | E12: 294.04 | F12: ='Income Statement'!F4*Assumptions!F22/365 -> 360.93686 | G12: ='Income Statement'!G4*Assumptions!G22/365 -> 440.34297 | H12: ='Income Statement'!H4*Assumptions!H22/365 -> 521.13804 | I12: ='Income Statement'!I4*Assumptions!I22/365 -> 611.43705 | J12: ='Income Statement'!J4*Assumptions!J22/365 -> 711.13526 | K12: ='Income Statement'!K4*Assumptions!K22/365 -> 819.8182 | L12: ='Income Statement'!L4*Assumptions!L22/365 -> 936.72112 | M12: ='Income Statement'!M4*Assumptions!M22/365 -> 1060.6989 | ... O12: ='Income Statement'!O4*Assumptions!O22/365 -> 1329.1491
A13: Trade Receivables | B13: 84 | C13: 139 | D13: 64.65 | E13: 134.32 | F13: ='Income Statement'!F4*Assumptions!F21/365 -> 180.46843 | G13: ='Income Statement'!G4*Assumptions!G21/365 -> 235.89802 | H13: ='Income Statement'!H4*Assumptions!H21/365 -> 284.25711 | I13: ='Income Statement'!I4*Assumptions!I21/365 -> 339.68725 | J13: ='Income Statement'!J4*Assumptions!J21/365 -> 402.52939 | K13: ='Income Statement'!K4*Assumptions!K21/365 -> 472.97204 | L13: ='Income Statement'!L4*Assumptions!L21/365 -> 551.01242 | M13: ='Income Statement'!M4*Assumptions!M21/365 -> 636.41935 | ... O13: ='Income Statement'!O4*Assumptions!O21/365 -> 830.71818
A14: Cash & Cash Equivalents | B14: 15 | C14: 36 | D14: 305.9 | E14: 225.37 | F14: =MAX(0, F24+F29+F32+F34+'Debt Schedule'!F19 - F9-F12-F13-F15) -> 187.78865 | G14: =MAX(0, G24+G29+G32+G34+'Debt Schedule'!G19 - G9-G12-G13-G15) -> 226.30798 | H14: =MAX(0, H24+H29+H32+H34+'Debt Schedule'!H19 - H9-H12-H13-H15) -> 475.07577 | I14: =MAX(0, I24+I29+I32+I34+'Debt Schedule'!I19 - I9-I12-I13-I15) -> 854.76389 | J14: =MAX(0, J24+J29+J32+J34+'Debt Schedule'!J19 - J9-J12-J13-J15) -> 1397.0237 | K14: =MAX(0, K24+K29+K32+K34+'Debt Schedule'!K19 - K9-K12-K13-K15) -> 2089.9142 | L14: =MAX(0, L24+L29+L32+L34+'Debt Schedule'!L19 - L9-L12-L13-L15) -> 2962.9172 | M14: =MAX(0, M24+M29+M32+M34+'Debt Schedule'!M19 - M9-M12-M13-M15) -> 4019.5485 | ... O14: =MAX(0, O24+O29+O32+O34+'Debt Schedule'!O19 - O9-O12-O13-O15) -> 6723.3952
A15: Other Current Assets | B15: 30 | C15: 40 | D15: 20.84 | E15: 35.1 | F15: 75 | G15: 80 | H15: 85 | I15: 90 | J15: 95 | K15: 100 | L15: 105 | M15: 110 | N15: 115 | O15: 120
A16: Total Current Assets | B16: =SUM(B12:B15) -> 297 | C16: =SUM(C12:C15) -> 497 | D16: =SUM(D12:D15) -> 616.49 | E16: =SUM(E12:E15) -> 688.83 | F16: =SUM(F12:F15) -> 804.19394 | G16: =SUM(G12:G15) -> 982.54897 | H16: =SUM(H12:H15) -> 1365.4709 | I16: =SUM(I12:I15) -> 1895.8882 | ... O16: =SUM(O12:O15) -> 9003.2624
A18: TOTAL ASSETS | B18: =B9+B16 -> 522 | C18: =C9+C16 -> 757 | D18: =D9+D16 -> 1189.99 | E18: =E9+E16 -> 1519.62 | F18: =F9+F16 -> 1712.0452 | G18: =G9+G16 -> 2020.3367 | H18: =H9+H16 -> 2425.2956 | I18: =I9+I16 -> 2935.9299 | ... O18: =O9+O16 -> 9189.1766
A20: EQUITY & LIABILITIES
A21: Shareholders' Equity
A22: Share Capital | B22: 46 | C22: 46 | D22: 60.69 | E22: 60.69 | F22: 61 | G22: 61 | H22: 61 | I22: 61 | J22: 61 | K22: 61 | L22: 61 | M22: 61 | N22: 61 | O22: 61
A23: Reserves & Surplus | B23: 292.1 | C23: 443.8 | D23: 781.54 | E23: 1021.81 | F23: =E23+'Income Statement'!F26-'Income Statement'!F30*Assumptions!B90 -> 1245.4646 | G23: =F23+'Income Statement'!G26-'Income Statement'!G30*Assumptions!B90 -> 1530.9995 | H23: =G23+'Income Statement'!H26-'Income Statement'!H30*Assumptions!B90 -> 1905.2278 | I23: =H23+'Income Statement'!I26-'Income Statement'!I30*Assumptions!B90 -> 2375.7191 | J23: =I23+'Income Statement'!J26-'Income Statement'!J30*Assumptions!B90 -> 2963.6531 | K23: =J23+'Income Statement'!K26-'Income Statement'!K30*Assumptions!$B$90 -> 3674.2675 | L23: =K23+'Income Statement'!L26-'Income Statement'!L30*Assumptions!$B$90 -> 4533.9397 | M23: =L23+'Income Statement'!M26-'Income Statement'!M30*Assumptions!$B$90 -> 5547.0241 | N23: =M23+'Income Statement'!N26-'Income Statement'!N30*Assumptions!$B$90 -> 6736.7984 | O23: =N23+'Income Statement'!O26-'Income Statement'!O30*Assumptions!$B$90 -> 8098.9507
A24: Total Equity | B24: =B22+B23 -> 338.1 | C24: =C22+C23 -> 489.8 | D24: =D22+D23 -> 842.23 | E24: =E22+E23 -> 1082.5 | F24: =F22+F23 -> 1306.4646 | G24: =G22+G23 -> 1591.9995 | H24: =H22+H23 -> 1966.2278 | I24: =I22+I23 -> 2436.7191 | ... O24: =O22+O23 -> 8159.9507
A26: Non-Current Liabilities
A27: Long-term Borrowings | B27: 2.9 | C27: 15.2 | D27: 126.72 | E27: 148.73 | F27: ='Debt Schedule'!F9 -> 95.2 | G27: ='Debt Schedule'!G9 -> 80.2 | H27: ='Debt Schedule'!H9 -> 65.2 | I27: ='Debt Schedule'!I9 -> 50.2 | J27: ='Debt Schedule'!J9 -> 35.2 | K27: ='Debt Schedule'!K9 -> 25.2 | L27: ='Debt Schedule'!L9 -> 15.2 | M27: ='Debt Schedule'!M9 -> 10.2 | ... O27: ='Debt Schedule'!O9 -> 0.2
A28: Other Non-Current Liab. | B28: 15 | C28: 18 | D28: 13.24 | E28: 31.46 | F28: 32 | G28: 34 | H28: 36 | I28: 38 | J28: 40 | K28: 42 | L28: 44 | M28: 46 | N28: 48 | O28: 50
A29: Total Non-Current Liabilities | B29: =B27+B28 -> 17.9 | C29: =C27+C28 -> 33.2 | D29: =D27+D28 -> 139.96 | E29: =E27+E28 -> 180.19 | F29: =F27+F28 -> 127.2 | G29: =G27+G28 -> 114.2 | H29: =H27+H28 -> 101.2 | I29: =I27+I28 -> 88.2 | ... O29: =O27+O28 -> 50.2
A31: Current Liabilities
A32: Trade Payables | B32: 94 | C32: 159 | D32: 89.19 | E32: 109.11 | F32: =ABS('Income Statement'!F7)*Assumptions!F23/365 -> 138.38061 | G32: =ABS('Income Statement'!G7)*Assumptions!G23/365 -> 176.13719 | H32: =ABS('Income Statement'!H7)*Assumptions!H23/365 -> 220.86778 | I32: =ABS('Income Statement'!I7)*Assumptions!I23/365 -> 275.0108 | J32: =ABS('Income Statement'!J7)*Assumptions!J23/365 -> 339.46645 | K32: =ABS('Income Statement'!K7)*Assumptions!K23/365 -> 416.21539 | L32: =ABS('Income Statement'!L7)*Assumptions!L23/365 -> 503.25801 | M32: =ABS('Income Statement'!M7)*Assumptions!M23/365 -> 603.4104 | ... O32: =ABS('Income Statement'!O7)*Assumptions!O23/365 -> 830.02591
A33: Short-term Borrowings | B33: 30 | C33: 25 | D33: 45.18 | E33: 63.04 | F33: ='Debt Schedule'!F19 + MAX(0, F9+F12+F13+F15 - F24-F29-F32-F34-'Debt Schedule'!F19) -> 55 | G33: ='Debt Schedule'!G19 + MAX(0, G9+G12+G13+G15 - G24-G29-G32-G34-'Debt Schedule'!G19) -> 48 | H33: ='Debt Schedule'!H19 + MAX(0, H9+H12+H13+H15 - H24-H29-H32-H34-'Debt Schedule'!H19) -> 42 | I33: ='Debt Schedule'!I19 + MAX(0, I9+I12+I13+I15 - I24-I29-I32-I34-'Debt Schedule'!I19) -> 36 | J33: ='Debt Schedule'!J19 + MAX(0, J9+J12+J13+J15 - J24-J29-J32-J34-'Debt Schedule'!J19) -> 30 | K33: ='Debt Schedule'!K19 + MAX(0, K9+K12+K13+K15 - K24-K29-K32-K34-'Debt Schedule'!K19) -> 27 | L33: ='Debt Schedule'!L19 + MAX(0, L9+L12+L13+L15 - L24-L29-L32-L34-'Debt Schedule'!L19) -> 25 | M33: ='Debt Schedule'!M19 + MAX(0, M9+M12+M13+M15 - M24-M29-M32-M34-'Debt Schedule'!M19) -> 23 | ... O33: ='Debt Schedule'!O19 + MAX(0, O9+O12+O13+O15 - O24-O29-O32-O34-'Debt Schedule'!O19) -> 19
A34: Other Current Liabilities | B34: 42 | C34: 50 | D34: 73.43 | E34: 84.78 | F34: 85 | G34: 90 | H34: 95 | I34: 100 | J34: 105 | K34: 110 | L34: 115 | M34: 120 | N34: 125 | O34: 130
A35: Total Current Liabilities | B35: =SUM(B32:B34) -> 166 | C35: =SUM(C32:C34) -> 234 | D35: =SUM(D32:D34) -> 207.8 | E35: =SUM(E32:E34) -> 256.93 | F35: =SUM(F32:F34) -> 278.38061 | G35: =SUM(G32:G34) -> 314.13719 | H35: =SUM(H32:H34) -> 357.86778 | I35: =SUM(I32:I34) -> 411.0108 | ... O35: =SUM(O32:O34) -> 979.02591
A37: TOTAL EQUITY & LIABILITIES | B37: =B24+B29+B35 -> 522 | C37: =C24+C29+C35 -> 757 | D37: =D24+D29+D35 -> 1189.99 | E37: =E24+E29+E35 -> 1519.62 | F37: =F24+F29+F35 -> 1712.0452 | G37: =G24+G29+G35 -> 2020.3367 | H37: =H24+H29+H35 -> 2425.2956 | I37: =I24+I29+I35 -> 2935.9299 | ... O37: =O24+O29+O35 -> 9189.1766
A39: Balance Check (Assets - E&L) | B39: =B18-B37 -> 0 | C39: =C18-C37 -> 0 | D39: =D18-D37 -> 0 | E39: =E18-E37 -> 0 | F39: =F18-F37 -> 0 | G39: =G18-G37 -> 0 | H39: =H18-H37 -> 0 | I39: =I18-I37 -> 0 | ... O39: =O18-O37 -> 0
A41: KEY RATIOS
A42: Book Value per Share (₹) | B42: =B24/Assumptions!B90 -> 55.709343 | C42: =C24/Assumptions!B90 -> 80.705223 | D42: =D24/Assumptions!B90 -> 138.77575 | E42: =E24/Assumptions!B90 -> 178.36546 | F42: =F24/Assumptions!B90 -> 215.26851 | G42: =G24/Assumptions!B90 -> 262.31662 | H42: =H24/Assumptions!B90 -> 323.97888 | I42: =I24/Assumptions!B90 -> 401.50256 | J42: =J24/Assumptions!B90 -> 498.37751 | K42: =K24/Assumptions!$B$90 -> 615.46671 | L42: =L24/Assumptions!$B$90 -> 757.11644 | M42: =M24/Assumptions!$B$90 -> 924.04418 | N42: =N24/Assumptions!$B$90 -> 1120.0854 | O42: =O24/Assumptions!$B$90 -> 1344.5297
A43: ROE (%) | B43: =IF(B24>0,'Income Statement'!B26/B24,0) -> 0.053119787 | C43: =IF(C24>0,'Income Statement'!C26/C24,0) -> 0.21126513 | D43: =IF(D24>0,'Income Statement'!D26/D24,0) -> 0.18958456 | E43: =IF(E24>0,'Income Statement'!E26/E24,0) -> 0.19727015 | F43: =IF(F24>0,'Income Statement'!F26/F24,0) -> 0.18895222 | G43: =IF(G24>0,'Income Statement'!G26/G24,0) -> 0.19796486 | H43: =IF(H24>0,'Income Statement'!H26/H24,0) -> 0.2100751 | I43: =IF(I24>0,'Income Statement'!I26/I24,0) -> 0.21311689 | ... O43: =IF(O24>0,'Income Statement'!O26/O24,0) -> 0.18425103
A44: Net Debt (₹ Cr) | B44: =B27+B33-B14 -> 17.9 | C44: =C27+C33-C14 -> 4.2 | D44: =D27+D33-D14 -> -134 | E44: =E27+E33-E14 -> -13.6 | F44: =F27+F33-F14 -> -37.588651 | G44: =G27+G33-G14 -> -98.107977 | H44: =H27+H33-H14 -> -367.87577 | I44: =I27+I33-I14 -> -768.56389 | ... O44: =O27+O33-O14 -> -6704.1952

Sheet Cash Flow Statement
A1: DOMS INDUSTRIES LTD — CONSOLIDATED CASH FLOW STATEMENT
A2: (₹ Crores) | Indirect Method
B3: FY22A | C3: FY23A | D3: FY24A | E3: FY25A | F3: FY26E | G3: FY27E | H3: FY28E | I3: FY29E | J3: FY30E | K3: FY31E | L3: FY32E | M3: FY33E | N3: FY34E | O3: FY35E
A4: CASH FLOW FROM OPERATIONS
A5: PAT | B5: ='Income Statement'!B26 -> 17.9598 | C5: ='Income Statement'!C26 -> 103.47766 | D5: ='Income Statement'!D26 -> 159.6738 | E5: ='Income Statement'!E26 -> 213.54494 | F5: ='Income Statement'!F26 -> 246.85939 | G5: ='Income Statement'!G26 -> 315.15997 | H5: ='Income Statement'!H26 -> 413.05551 | I5: ='Income Statement'!I26 -> 519.30599 | ... O5: ='Income Statement'!O26 -> 1503.4793
A6: (+) Depreciation & Amortization | B6: =-'Income Statement'!B17 -> 38.04 | C6: =-'Income Statement'!C17 -> 40.67 | D6: =-'Income Statement'!D17 -> 51.24 | E6: =-'Income Statement'!E17 -> 69.18 | F6: =-'Income Statement'!F17 -> 82.338722 | G6: =-'Income Statement'!G17 -> 109.06352 | H6: =-'Income Statement'!H17 -> 127.96308 | I6: =-'Income Statement'!I17 -> 148.78302 | ... O6: =-'Income Statement'!O17 -> 303.21213
A7: (-) Change in Inventories | B7: -20 | C7: -60 | D7: 56.9 | E7: -68.94 | F7: =-('Balance Sheet'!F12-'Balance Sheet'!E12) -> -66.896861 | G7: =-('Balance Sheet'!G12-'Balance Sheet'!F12) -> -79.40611 | H7: =-('Balance Sheet'!H12-'Balance Sheet'!G12) -> -80.795072 | I7: =-('Balance Sheet'!I12-'Balance Sheet'!H12) -> -90.29901 | J7: =-('Balance Sheet'!J12-'Balance Sheet'!I12) -> -99.698208 | K7: =-('Balance Sheet'!K12-'Balance Sheet'!J12) -> -108.68294 | L7: =-('Balance Sheet'!L12-'Balance Sheet'!K12) -> -116.90292 | M7: =-('Balance Sheet'!M12-'Balance Sheet'!L12) -> -123.9778 | ... O7: =-('Balance Sheet'!O12-'Balance Sheet'!N12) -> -138.93883
A8: (-) Change in Receivables | B8: -8 | C8: -25 | D8: 74.35 | E8: -69.67 | F8: =-('Balance Sheet'!F13-'Balance Sheet'!E13) -> -46.148431 | G8: =-('Balance Sheet'!G13-'Balance Sheet'!F13) -> -55.429589 | H8: =-('Balance Sheet'!H13-'Balance Sheet'!G13) -> -48.359094 | I8: =-('Balance Sheet'!I13-'Balance Sheet'!H13) -> -55.430137 | J8: =-('Balance Sheet'!J13-'Balance Sheet'!I13) -> -62.842142 | K8: =-('Balance Sheet'!K13-'Balance Sheet'!J13) -> -70.442644 | L8: =-('Balance Sheet'!L13-'Balance Sheet'!K13) -> -78.040386 | M8: =-('Balance Sheet'!M13-'Balance Sheet'!L13) -> -85.406926 | ... O8: =-('Balance Sheet'!O13-'Balance Sheet'!N13) -> -102.01802
A9: (+) Change in Payables | B9: 18 | C9: 80 | D9: -69.81 | E9: 19.92 | F9: ='Balance Sheet'!F32-'Balance Sheet'!E32 -> 29.270615 | G9: ='Balance Sheet'!G32-'Balance Sheet'!F32 -> 37.756574 | H9: ='Balance Sheet'!H32-'Balance Sheet'!G32 -> 44.730589 | I9: ='Balance Sheet'!I32-'Balance Sheet'!H32 -> 54.143021 | J9: ='Balance Sheet'!J32-'Balance Sheet'!I32 -> 64.455656 | K9: ='Balance Sheet'!K32-'Balance Sheet'!J32 -> 76.748938 | L9: ='Balance Sheet'!L32-'Balance Sheet'!K32 -> 87.042621 | M9: ='Balance Sheet'!M32-'Balance Sheet'!L32 -> 100.15239 | ... O9: ='Balance Sheet'!O32-'Balance Sheet'!N32 -> 115.17106
A10: Other Operating Adjustments | B10: 4.9 | C10: 34.21 | D10: -89.86 | E10: 19.3 | F10: =('Balance Sheet'!F14-'Balance Sheet'!E14)-(F5+F6+F7+F8+F9+F17+F23) -> 66.77 | G10: =('Balance Sheet'!G14-'Balance Sheet'!F14)-(G5+G6+G7+G8+G9+G17+G23) -> 13 | H10: =('Balance Sheet'!H14-'Balance Sheet'!G14)-(H5+H6+H7+H8+H9+H17+H23) -> 12 | I10: =('Balance Sheet'!I14-'Balance Sheet'!H14)-(I5+I6+I7+I8+I9+I17+I23) -> 8 | J10: =('Balance Sheet'!J14-'Balance Sheet'!I14)-(J5+J6+J7+J8+J9+J17+J23) -> 7 | K10: =('Balance Sheet'!K14-'Balance Sheet'!J14)-(K5+K6+K7+K8+K9+K17+K23) -> 7 | L10: =('Balance Sheet'!L14-'Balance Sheet'!K14)-(L5+L6+L7+L8+L9+L17+L23) -> 7 | M10: =('Balance Sheet'!M14-'Balance Sheet'!L14)-(M5+M6+M7+M8+M9+M17+M23) -> 2 | ... O10: =('Balance Sheet'!O14-'Balance Sheet'!N14)-(O5+O6+O7+O8+O9+O17+O23) -> 2
A12: Cash from Operations (CFO) | B12: =SUM(B5:B10) -> 50.8998 | C12: =SUM(C5:C10) -> 173.35766 | D12: =SUM(D5:D10) -> 182.4938 | E12: =SUM(E5:E10) -> 183.33494 | F12: =SUM(F5:F10) -> 312.19343 | G12: =SUM(G5:G10) -> 340.14436 | H12: =SUM(H5:H10) -> 468.59501 | I12: =SUM(I5:I10) -> 584.50288 | ... O12: =SUM(O5:O10) -> 1682.9056
A14: CASH FLOW FROM INVESTING
A15: Capital Expenditure | B15: =-Assumptions!B26 -> -30 | C15: =-Assumptions!C26 -> -50 | D15: =-Assumptions!D26 -> -152.81 | E15: =-Assumptions!E26 -> -210.02 | F15: =-Assumptions!F26 -> -250 | G15: =-Assumptions!G26 -> -240 | H15: =-Assumptions!H26 -> -150 | I15: =-Assumptions!I26 -> -130 | ... O15: =-Assumptions!O26 -> -90
A16: Acquisitions / Investments | B16: -3.7 | C16: -85.9 | D16: -304.7 | E16: 70.45 | F16: -15 | G16: -10 | H16: -10 | I16: -5 | J16: -5 | K16: -5 | L16: -5 | M16: 0 | N16: 0 | O16: 0
A17: Cash from Investing (CFI) | B17: =B15+B16 -> -33.7 | C17: =C15+C16 -> -135.9 | D17: =D15+D16 -> -457.51 | E17: =E15+E16 -> -139.57 | F17: =F15+F16 -> -265 | G17: =G15+G16 -> -250 | H17: =H15+H16 -> -160 | I17: =I15+I16 -> -135 | ... O17: =O15+O16 -> -90
A19: CASH FLOW FROM FINANCING
A20: Net Borrowings | B20: -28.91 | C20: -2.68 | D20: -28.13 | E20: -24.58 | F20: =('Balance Sheet'!F27-'Balance Sheet'!E27)+('Balance Sheet'!F33-'Balance Sheet'!E33) -> -61.57 | G20: =('Balance Sheet'!G27-'Balance Sheet'!F27)+('Balance Sheet'!G33-'Balance Sheet'!F33) -> -22 | H20: =('Balance Sheet'!H27-'Balance Sheet'!G27)+('Balance Sheet'!H33-'Balance Sheet'!G33) -> -21 | I20: =('Balance Sheet'!I27-'Balance Sheet'!H27)+('Balance Sheet'!I33-'Balance Sheet'!H33) -> -21 | J20: =('Balance Sheet'!J27-'Balance Sheet'!I27)+('Balance Sheet'!J33-'Balance Sheet'!I33) -> -21 | K20: =('Balance Sheet'!K27-'Balance Sheet'!J27)+('Balance Sheet'!K33-'Balance Sheet'!J33) -> -13 | L20: =('Balance Sheet'!L27-'Balance Sheet'!K27)+('Balance Sheet'!L33-'Balance Sheet'!K33) -> -12 | M20: =('Balance Sheet'!M27-'Balance Sheet'!L27)+('Balance Sheet'!M33-'Balance Sheet'!L33) -> -7 | ... O20: =('Balance Sheet'!O27-'Balance Sheet'!N27)+('Balance Sheet'!O33-'Balance Sheet'!N33) -> -7
A21: IPO Proceeds | B21: 0 | C21: 0 | D21: 334.67 | E21: 0 | F21: 0 | G21: 0 | H21: 0 | I21: 0 | J21: 0 | K21: 0 | L21: 0 | M21: 0 | N21: 0 | O21: 0
A22: Dividends Paid | B22: =-'Income Statement'!B30*Assumptions!B90 -> -1.6882212 | C22: =-'Income Statement'!C30*Assumptions!B90 -> -9.7269 | D22: =-'Income Statement'!D30*Assumptions!B90 -> -15.009337 | E22: =-'Income Statement'!E30*Assumptions!B90 -> -20.073224 | F22: =-'Income Statement'!F30*Assumptions!B90 -> -23.204783 | G22: =-'Income Statement'!G30*Assumptions!B90 -> -29.625037 | H22: =-'Income Statement'!H30*Assumptions!B90 -> -38.827218 | I22: =-'Income Statement'!I30*Assumptions!B90 -> -48.814763 | J22: =-'Income Statement'!J30*Assumptions!B90 -> -60.999783 | K22: =-'Income Statement'!K30*Assumptions!$B$90 -> -73.728198 | L22: =-'Income Statement'!L30*Assumptions!$B$90 -> -89.193366 | M22: =-'Income Statement'!M30*Assumptions!$B$90 -> -105.1103 | N22: =-'Income Statement'!N30*Assumptions!$B$90 -> -123.44237 | O22: =-'Income Statement'!O30*Assumptions!$B$90 -> -141.32705
A23: Cash from Financing (CFF) | B23: =B20+B21+B22 -> -30.598221 | C23: =C20+C21+C22 -> -12.4069 | D23: =D20+D21+D22 -> 291.53066 | E23: =E20+E21+E22 -> -44.653224 | F23: =F20+F21+F22 -> -84.774783 | G23: =G20+G21+G22 -> -51.625037 | H23: =H20+H21+H22 -> -59.827218 | I23: =I20+I21+I22 -> -69.814763 | ... O23: =O20+O21+O22 -> -148.32705
A25: Net Change in Cash | B25: =B12+B17+B23 -> -13.398421 | C25: =C12+C17+C23 -> 25.05076 | D25: =D12+D17+D23 -> 16.514463 | E25: =E12+E17+E23 -> -0.88828889 | F25: =F12+F17+F23 -> -37.581349 | G25: =G12+G17+G23 -> 38.519325 | H25: =H12+H17+H23 -> 248.76779 | I25: =I12+I17+I23 -> 379.68812 | ... O25: =O12+O17+O23 -> 1444.5786
A27: FREE CASH FLOW CALCULATION
A28: FCFF = EBIT(1-t) + D&A - Capex - ΔWC
A29: EBIT × (1 - Tax Rate) | B29: ='Income Statement'!B18*(1-Assumptions!B18) -> 23.643 | C29: ='Income Statement'!C18*(1-Assumptions!C18) -> 108.88616 | D29: ='Income Statement'!D18*(1-Assumptions!D18) -> 164.87716 | E29: ='Income Statement'!E18*(1-Assumptions!E18) -> 207.91652 | F29: ='Income Statement'!F18*(1-Assumptions!F18) -> 245.36939 | G29: ='Income Statement'!G18*(1-Assumptions!G18) -> 312.17997 | H29: ='Income Statement'!H18*(1-Assumptions!H18) -> 407.09551 | I29: ='Income Statement'!I18*(1-Assumptions!I18) -> 511.11099 | ... O29: ='Income Statement'!O18*(1-Assumptions!O18) -> 1483.3643
A30: (+) D&A | B30: =B6 -> 38.04 | C30: =C6 -> 40.67 | D30: =D6 -> 51.24 | E30: =E6 -> 69.18 | F30: =F6 -> 82.338722 | G30: =G6 -> 109.06352 | H30: =H6 -> 127.96308 | I30: =I6 -> 148.78302 | ... O30: =O6 -> 303.21213
A31: (-) Capex | B31: =B15 -> -30 | C31: =C15 -> -50 | D31: =D15 -> -152.81 | E31: =E15 -> -210.02 | F31: =F15 -> -250 | G31: =G15 -> -240 | H31: =H15 -> -150 | I31: =I15 -> -130 | ... O31: =O15 -> -90
A32: (-) Change in Working Capital | B32: =B7+B8+B9 -> -10 | C32: =C7+C8+C9 -> -5 | D32: =D7+D8+D9 -> 61.44 | E32: =E7+E8+E9 -> -118.69 | F32: =F7+F8+F9 -> -83.774678 | G32: =G7+G8+G9 -> -97.079125 | H32: =H7+H8+H9 -> -84.423577 | I32: =I7+I8+I9 -> -91.586126 | ... O32: =O7+O8+O9 -> -125.78579
A34: Free Cash Flow to Firm (FCFF) | B34: =B29+B30+B31+B32 -> 21.683 | C34: =C29+C30+C31+C32 -> 94.55616 | D34: =D29+D30+D31+D32 -> 124.74716 | E34: =E29+E30+E31+E32 -> -51.613485 | F34: =F29+F30+F31+F32 -> -6.066566 | G34: =G29+G30+G31+G32 -> 84.164363 | H34: =H29+H30+H31+H32 -> 300.63501 | I34: =I29+I30+I31+I32 -> 438.30788 | ... O34: =O29+O30+O31+O32 -> 1570.7906

Sheet Working Capital
A1: DOMS INDUSTRIES LTD — WORKING CAPITAL SCHEDULE
A2: (₹ Crores)
B3: FY22A | C3: FY23A | D3: FY24A | E3: FY25A | F3: FY26E | G3: FY27E | H3: FY28E | I3: FY29E | J3: FY30E | K3: FY31E | L3: FY32E | M3: FY33E | N3: FY34E | O3: FY35E
A5: WORKING CAPITAL DAYS (ASSUMPTIONS)
A6: Days Sales Outstanding (DSO) | B6: =IF('Balance Sheet'!B13>0,'Balance Sheet'!B13/'Income Statement'!B4*365,0) -> 44.680851 | C6: =IF('Balance Sheet'!C13>0,'Balance Sheet'!C13/'Income Statement'!C4*365,0) -> 41.864361 | D6: =IF('Balance Sheet'!D13>0,'Balance Sheet'!D13/'Income Statement'!D4*365,0) -> 15.351399 | E6: =IF('Balance Sheet'!E13>0,'Balance Sheet'!E13/'Income Statement'!E4*365,0) -> 25.633186 | F6: =Assumptions!F21 -> 28 | G6: =Assumptions!G21 -> 30 | H6: =Assumptions!H21 -> 30 | I6: =Assumptions!I21 -> 30 | J6: =Assumptions!J21 -> 30 | K6: =Assumptions!K21 -> 30 | L6: =Assumptions!L21 -> 30 | M6: =Assumptions!M21 -> 30 | ... O6: =Assumptions!O21 -> 30
A7: Days Inventory Outstanding (on Revenue) | B7: =IF('Income Statement'!B4>0,'Balance Sheet'!B12/'Income Statement'!B4*365,0) -> 89.361702 | C7: =IF('Income Statement'!C4>0,'Balance Sheet'!C12/'Income Statement'!C4*365,0) -> 84.933451 | D7: =IF('Income Statement'!D4>0,'Balance Sheet'!D12/'Income Statement'!D4*365,0) -> 53.450889 | E7: =IF('Income Statement'!E4>0,'Balance Sheet'!E12/'Income Statement'!E4*365,0) -> 56.113624 | F7: =Assumptions!F22 -> 56 | G7: =Assumptions!G22 -> 56 | H7: =Assumptions!H22 -> 55 | I7: =Assumptions!I22 -> 54 | J7: =Assumptions!J22 -> 53 | K7: =Assumptions!K22 -> 52 | L7: =Assumptions!L22 -> 51 | M7: =Assumptions!M22 -> 50 | ... O7: =Assumptions!O22 -> 48
A8: Days Payable Outstanding (on COGS) | B8: =IF(ABS('Income Statement'!B7)>0,'Balance Sheet'!B32/ABS('Income Statement'!B7)*365,0) -> 72.463462 | C8: =IF(ABS('Income Statement'!C7)>0,'Balance Sheet'!C32/ABS('Income Statement'!C7)*365,0) -> 74.359993 | D8: =IF(ABS('Income Statement'!D7)>0,'Balance Sheet'!D32/ABS('Income Statement'!D7)*365,0) -> 36.465248 | E8: =IF(ABS('Income Statement'!E7)>0,'Balance Sheet'!E32/ABS('Income Statement'!E7)*365,0) -> 36.854664 | F8: =Assumptions!F23 -> 38 | G8: =Assumptions!G23 -> 40 | H8: =Assumptions!H23 -> 42 | I8: =Assumptions!I23 -> 44 | J8: =Assumptions!J23 -> 46 | K8: =Assumptions!K23 -> 48 | L8: =Assumptions!L23 -> 50 | M8: =Assumptions!M23 -> 52 | ... O8: =Assumptions!O23 -> 55
A10: Cash Conversion Cycle (Days) | B10: =B6+B7-B8 -> 61.579091 | C10: =C6+C7-C8 -> 52.437819 | D10: =D6+D7-D8 -> 32.337041 | E10: =E6+E7-E8 -> 44.892145 | F10: =F6+F7-F8 -> 46 | G10: =G6+G7-G8 -> 46 | H10: =H6+H7-H8 -> 43 | I10: =I6+I7-I8 -> 40 | ... O10: =O6+O7-O8 -> 23
A12: WORKING CAPITAL BALANCES (DERIVED)
A13: Trade Receivables | B13: ='Balance Sheet'!B13 -> 84 | C13: ='Balance Sheet'!C13 -> 139 | D13: ='Balance Sheet'!D13 -> 64.65 | E13: ='Balance Sheet'!E13 -> 134.32 | F13: =F6/365*'Income Statement'!F4 -> 180.46843 | G13: =G6/365*'Income Statement'!G4 -> 235.89802 | H13: =H6/365*'Income Statement'!H4 -> 284.25711 | I13: =I6/365*'Income Statement'!I4 -> 339.68725 | J13: =J6/365*'Income Statement'!J4 -> 402.52939 | K13: =K6/365*'Income Statement'!K4 -> 472.97204 | L13: =L6/365*'Income Statement'!L4 -> 551.01242 | M13: =M6/365*'Income Statement'!M4 -> 636.41935 | ... O13: =O6/365*'Income Statement'!O4 -> 830.71818
A14: Inventories | B14: ='Balance Sheet'!B12 -> 168 | C14: ='Balance Sheet'!C12 -> 282 | D14: ='Balance Sheet'!D12 -> 225.1 | E14: ='Balance Sheet'!E12 -> 294.04 | F14: =F7/365*'Income Statement'!F4 -> 360.93686 | G14: =G7/365*'Income Statement'!G4 -> 440.34297 | H14: =H7/365*'Income Statement'!H4 -> 521.13804 | I14: =I7/365*'Income Statement'!I4 -> 611.43705 | J14: =J7/365*'Income Statement'!J4 -> 711.13526 | K14: =K7/365*'Income Statement'!K4 -> 819.8182 | L14: =L7/365*'Income Statement'!L4 -> 936.72112 | M14: =M7/365*'Income Statement'!M4 -> 1060.6989 | ... O14: =O7/365*'Income Statement'!O4 -> 1329.1491
A15: Trade Payables | B15: ='Balance Sheet'!B32 -> 94 | C15: ='Balance Sheet'!C32 -> 159 | D15: ='Balance Sheet'!D32 -> 89.19 | E15: ='Balance Sheet'!E32 -> 109.11 | F15: =F8/365*ABS('Income Statement'!F7) -> 138.38061 | G15: =G8/365*ABS('Income Statement'!G7) -> 176.13719 | H15: =H8/365*ABS('Income Statement'!H7) -> 220.86778 | I15: =I8/365*ABS('Income Statement'!I7) -> 275.0108 | J15: =J8/365*ABS('Income Statement'!J7) -> 339.46645 | K15: =K8/365*ABS('Income Statement'!K7) -> 416.21539 | L15: =L8/365*ABS('Income Statement'!L7) -> 503.25801 | M15: =M8/365*ABS('Income Statement'!M7) -> 603.4104 | ... O15: =O8/365*ABS('Income Statement'!O7) -> 830.02591
A17: Net Working Capital (Rec + Inv - Pay) | B17: =B13+B14-B15 -> 158 | C17: =C13+C14-C15 -> 262 | D17: =D13+D14-D15 -> 200.56 | E17: =E13+E14-E15 -> 319.25 | F17: =F13+F14-F15 -> 403.02468 | G17: =G13+G14-G15 -> 500.1038 | H17: =H13+H14-H15 -> 584.52738 | I17: =I13+I14-I15 -> 676.11351 | ... O17: =O13+O14-O15 -> 1329.8413
A19: Change in Working Capital (ΔWC) | B19: 0 | C19: =C17-B17 -> 104 | D19: =D17-C17 -> -61.44 | E19: =E17-D17 -> 118.69 | F19: =F17-E17 -> 83.774678 | G19: =G17-F17 -> 97.079125 | H19: =H17-G17 -> 84.423577 | I19: =I17-H17 -> 91.586126 | J19: =J17-I17 -> 98.084694 | ... O19: =O17-N17 -> 125.78579
A21: WORKING CAPITAL AS % OF REVENUE
A22: Trade Receivables / Revenue | B22: =B13/'Income Statement'!B4 -> 0.12241329 | C22: =C13/'Income Statement'!C4 -> 0.11469688 | D22: =D13/'Income Statement'!D4 -> 0.042058628 | E22: =E13/'Income Statement'!E4 -> 0.070227906 | F22: =F13/'Income Statement'!F4 -> 0.076712329 | G22: =G13/'Income Statement'!G4 -> 0.082191781 | H22: =H13/'Income Statement'!H4 -> 0.082191781 | I22: =I13/'Income Statement'!I4 -> 0.082191781 | ... O22: =O13/'Income Statement'!O4 -> 0.082191781
A23: Inventories / Revenue | B23: =B14/'Income Statement'!B4 -> 0.24482658 | C23: =C14/'Income Statement'!C4 -> 0.23269439 | D23: =D14/'Income Statement'!D4 -> 0.14644079 | E23: =E14/'Income Statement'!E4 -> 0.15373596 | F23: =F14/'Income Statement'!F4 -> 0.15342466 | G23: =G14/'Income Statement'!G4 -> 0.15342466 | H23: =H14/'Income Statement'!H4 -> 0.15068493 | I23: =I14/'Income Statement'!I4 -> 0.14794521 | ... O23: =O14/'Income Statement'!O4 -> 0.13150685
A24: Trade Payables / Revenue | B24: =B15/'Income Statement'!B4 -> 0.1369863 | C24: =C15/'Income Statement'!C4 -> 0.13120003 | D24: =D15/'Income Statement'!D4 -> 0.058023342 | E24: =E15/'Income Statement'!E4 -> 0.057047103 | F24: =F15/'Income Statement'!F4 -> 0.058821918 | G24: =G15/'Income Statement'!G4 -> 0.061369863 | H24: =H15/'Income Statement'!H4 -> 0.063863014 | I24: =I15/'Income Statement'!I4 -> 0.066542466 | ... O24: =O15/'Income Statement'!O4 -> 0.082123288
A25: Net WC / Revenue | B25: =B17/'Income Statement'!B4 -> 0.23025357 | C25: =C17/'Income Statement'!C4 -> 0.21619124 | D25: =D17/'Income Statement'!D4 -> 0.13047608 | E25: =E17/'Income Statement'!E4 -> 0.16691676 | F25: =F17/'Income Statement'!F4 -> 0.17131507 | G25: =G17/'Income Statement'!G4 -> 0.17424658 | H25: =H17/'Income Statement'!H4 -> 0.1690137 | I25: =I17/'Income Statement'!I4 -> 0.16359452 | ... O25: =O17/'Income Statement'!O4 -> 0.13157534
A27: CROSS-CHECK vs BALANCE SHEET
A28: BS Receivables | B28: ='Balance Sheet'!B13 -> 84 | C28: ='Balance Sheet'!C13 -> 139 | D28: ='Balance Sheet'!D13 -> 64.65 | E28: ='Balance Sheet'!E13 -> 134.32 | F28: ='Balance Sheet'!F13 -> 180.46843 | G28: ='Balance Sheet'!G13 -> 235.89802 | H28: ='Balance Sheet'!H13 -> 284.25711 | I28: ='Balance Sheet'!I13 -> 339.68725 | ... O28: ='Balance Sheet'!O13 -> 830.71818
A29: BS Inventories | B29: ='Balance Sheet'!B12 -> 168 | C29: ='Balance Sheet'!C12 -> 282 | D29: ='Balance Sheet'!D12 -> 225.1 | E29: ='Balance Sheet'!E12 -> 294.04 | F29: ='Balance Sheet'!F12 -> 360.93686 | G29: ='Balance Sheet'!G12 -> 440.34297 | H29: ='Balance Sheet'!H12 -> 521.13804 | I29: ='Balance Sheet'!I12 -> 611.43705 | ... O29: ='Balance Sheet'!O12 -> 1329.1491
A30: BS Payables | B30: ='Balance Sheet'!B32 -> 94 | C30: ='Balance Sheet'!C32 -> 159 | D30: ='Balance Sheet'!D32 -> 89.19 | E30: ='Balance Sheet'!E32 -> 109.11 | F30: ='Balance Sheet'!F32 -> 138.38061 | G30: ='Balance Sheet'!G32 -> 176.13719 | H30: ='Balance Sheet'!H32 -> 220.86778 | I30: ='Balance Sheet'!I32 -> 275.0108 | ... O30: ='Balance Sheet'!O32 -> 830.02591
A31: Difference (WC model - BS) | B31: =B17-(B28+B29-B30) -> 0 | C31: =C17-(C28+C29-C30) -> 0 | D31: =D17-(D28+D29-D30) -> 0 | E31: =E17-(E28+E29-E30) -> 0 | F31: =F17-(F28+F29-F30) -> 0 | G31: =G17-(G28+G29-G30) -> 0 | H31: =H17-(H28+H29-H30) -> 0 | I31: =I17-(I28+I29-I30) -> 0 | ... O31: =O17-(O28+O29-O30) -> 0
A33: *Note: DIO calculated on Revenue (not COGS) to align with Balance Sheet methodology

Sheet Debt Schedule
A1: DOMS INDUSTRIES LTD — DEBT SCHEDULE
A2: (₹ Crores) | DOMS is a low-leverage company — debt is minimal relative to equity
B3: FY22A | C3: FY23A | D3: FY24A | E3: FY25A | F3: FY26E | G3: FY27E | H3: FY28E | I3: FY29E | J3: FY30E | K3: FY31E | L3: FY32E | M3: FY33E | N3: FY34E | O3: FY35E
A5: LONG-TERM BORROWINGS
A6: Opening Balance | B6: 2 | C6: =B9 -> 2.9 | D6: =C9 -> 15.2 | E6: =D9 -> 86.92 | F6: =E9 -> 108.93 | G6: =F9 -> 95.2 | H6: =G9 -> 80.2 | I6: =H9 -> 65.2 | J6: =I9 -> 50.2 | ... O6: =N9 -> 5.2
A7: (+) New Borrowings | B7: 2 | C7: 15 | D7: 86.72 | E7: 37.01 | F7: 0 | G7: 0 | H7: 0 | I7: 0 | J7: 0 | K7: 0 | L7: 0 | M7: 0 | N7: 0 | O7: 0
A8: (-) Repayments | B8: -1.1 | C8: -2.7 | D8: -15 | E8: -15 | F8: -13.73 | G8: -15 | H8: -15 | I8: -15 | J8: -15 | K8: -10 | L8: -10 | M8: -5 | N8: -5 | O8: -5
A9: Closing Balance | B9: =B6+B7+B8 -> 2.9 | C9: =C6+C7+C8 -> 15.2 | D9: =D6+D7+D8 -> 86.92 | E9: =E6+E7+E8 -> 108.93 | F9: =F6+F7+F8 -> 95.2 | G9: =G6+G7+G8 -> 80.2 | H9: =H6+H7+H8 -> 65.2 | I9: =I6+I7+I8 -> 50.2 | ... O9: =O6+O7+O8 -> 0.2
A11: Interest Rate (%) | B11: 0.085 | C11: 0.085 | D11: 0.065 | E11: 0.06 | F11: =Assumptions!F36 -> 0.0875 | G11: =Assumptions!G36 -> 0.0875 | H11: =Assumptions!H36 -> 0.085 | I11: =Assumptions!I36 -> 0.085 | J11: =Assumptions!J36 -> 0.0825 | K11: =Assumptions!K36 -> 0.0825 | L11: =Assumptions!L36 -> 0.0825 | M11: =Assumptions!M36 -> 0.0825 | ... O11: =Assumptions!O36 -> 0.0825
A12: Interest Expense — LT | B12: =-(B6+B9)/2*B11 -> -0.20825 | C12: =-(C6+C9)/2*C11 -> -0.76925 | D12: =-(D6+D9)/2*D11 -> -3.3189 | E12: =-(E6+E9)/2*E11 -> -5.8755 | F12: =-(F6+F9)/2*F11 -> -8.9306875 | G12: =-(G6+G9)/2*G11 -> -7.67375 | H12: =-(H6+H9)/2*H11 -> -6.1795 | I12: =-(I6+I9)/2*I11 -> -4.9045 | ... O12: =-(O6+O9)/2*O11 -> -0.22275
A13: Cross-check: BS LT Borrowings | B13: ='Balance Sheet'!B27 -> 2.9 | C13: ='Balance Sheet'!C27 -> 15.2 | D13: ='Balance Sheet'!D27 -> 126.72 | E13: ='Balance Sheet'!E27 -> 148.73 | F13: ='Balance Sheet'!F27 -> 95.2 | G13: ='Balance Sheet'!G27 -> 80.2 | H13: ='Balance Sheet'!H27 -> 65.2 | I13: ='Balance Sheet'!I27 -> 50.2 | ... O13: ='Balance Sheet'!O27 -> 0.2
A15: SHORT-TERM BORROWINGS
A16: Opening Balance | B16: 35 | C16: =B19 -> 30 | D16: =C19 -> 25 | E16: =D19 -> 45.18 | F16: =E19 -> 63.04 | G16: =F19 -> 55 | H16: =G19 -> 48 | I16: =H19 -> 42 | J16: =I19 -> 36 | ... O16: =N19 -> 21
A17: (+) New Drawings | B17: 10 | C17: 5 | D17: 30.18 | E17: 27.86 | F17: 0 | G17: 0 | H17: 0 | I17: 0 | J17: 0 | K17: 0 | L17: 0 | M17: 0 | N17: 0 | O17: 0
A18: (-) Repayments | B18: -15 | C18: -10 | D18: -10 | E18: -10 | F18: -8.04 | G18: -7 | H18: -6 | I18: -6 | J18: -6 | K18: -3 | L18: -2 | M18: -2 | N18: -2 | O18: -2
A19: Closing Balance | B19: =B16+B17+B18 -> 30 | C19: =C16+C17+C18 -> 25 | D19: =D16+D17+D18 -> 45.18 | E19: =E16+E17+E18 -> 63.04 | F19: =F16+F17+F18 -> 55 | G19: =G16+G17+G18 -> 48 | H19: =H16+H17+H18 -> 42 | I19: =I16+I17+I18 -> 36 | ... O19: =O16+O17+O18 -> 19
A21: Interest Rate (%) | B21: 0.095 | C21: 0.095 | D21: 0.075 | E21: 0.07 | F21: =Assumptions!F36+0.005 -> 0.0925 | G21: =Assumptions!G36+0.005 -> 0.0925 | H21: =Assumptions!H36+0.005 -> 0.09 | I21: =Assumptions!I36+0.005 -> 0.09 | J21: =Assumptions!J36+0.005 -> 0.0875 | K21: =Assumptions!K36+0.005 -> 0.0875 | L21: =Assumptions!L36+0.005 -> 0.0875 | M21: =Assumptions!M36+0.005 -> 0.0875 | ... O21: =Assumptions!O36+0.005 -> 0.0875
A22: Interest Expense — ST | B22: =-(B16+B19)/2*B21 -> -3.0875 | C22: =-(C16+C19)/2*C21 -> -2.6125 | D22: =-(D16+D19)/2*D21 -> -2.63175 | E22: =-(E16+E19)/2*E21 -> -3.7877 | F22: =-(F16+F19)/2*F21 -> -5.45935 | G22: =-(G16+G19)/2*G21 -> -4.76375 | H22: =-(H16+H19)/2*H21 -> -4.05 | I22: =-(I16+I19)/2*I21 -> -3.51 | ... O22: =-(O16+O19)/2*O21 -> -1.75
A23: Cross-check: BS ST Borrowings | B23: ='Balance Sheet'!B32 -> 94 | C23: ='Balance Sheet'!C32 -> 159 | D23: ='Balance Sheet'!D32 -> 89.19 | E23: ='Balance Sheet'!E32 -> 109.11 | F23: ='Balance Sheet'!F32 -> 138.38061 | G23: ='Balance Sheet'!G32 -> 176.13719 | H23: ='Balance Sheet'!H32 -> 220.86778 | I23: ='Balance Sheet'!I32 -> 275.0108 | ... O23: ='Balance Sheet'!O32 -> 830.02591
A25: TOTAL DEBT SUMMARY
A26: Total Debt (LT + ST) | B26: =B9+B19 -> 32.9 | C26: =C9+C19 -> 40.2 | D26: =D9+D19 -> 132.1 | E26: =E9+E19 -> 171.97 | F26: =F9+'Balance Sheet'!F33 -> 150.2 | G26: =G9+'Balance Sheet'!G33 -> 128.2 | H26: =H9+'Balance Sheet'!H33 -> 107.2 | I26: =I9+'Balance Sheet'!I33 -> 86.2 | J26: =J9+'Balance Sheet'!J33 -> 65.2 | K26: =K9+'Balance Sheet'!K33 -> 52.2 | L26: =L9+'Balance Sheet'!L33 -> 40.2 | M26: =M9+'Balance Sheet'!M33 -> 33.2 | ... O26: =O9+'Balance Sheet'!O33 -> 19.2
A27: (-) Cash & Equivalents | B27: ='Balance Sheet'!B14 -> 15 | C27: ='Balance Sheet'!C14 -> 36 | D27: ='Balance Sheet'!D14 -> 305.9 | E27: ='Balance Sheet'!E14 -> 225.37 | F27: ='Balance Sheet'!F14 -> 187.78865 | G27: ='Balance Sheet'!G14 -> 226.30798 | H27: ='Balance Sheet'!H14 -> 475.07577 | I27: ='Balance Sheet'!I14 -> 854.76389 | ... O27: ='Balance Sheet'!O14 -> 6723.3952
A28: Net Debt | B28: =B26-B27 -> 17.9 | C28: =C26-C27 -> 4.2 | D28: =D26-D27 -> -173.8 | E28: =E26-E27 -> -53.4 | F28: =F26-F27 -> -37.588651 | G28: =G26-G27 -> -98.107977 | H28: =H26-H27 -> -367.87577 | I28: =I26-I27 -> -768.56389 | ... O28: =O26-O27 -> -6704.1952
A30: Total Interest Expense | B30: =B12+B22 -> -3.29575 | C30: =C12+C22 -> -3.38175 | D30: =D12+D22 -> -5.95065 | E30: =E12+E22 -> -9.6632 | F30: =F12+F22 -> -14.390037 | G30: =G12+G22 -> -12.4375 | H30: =H12+H22 -> -10.2295 | I30: =I12+I22 -> -8.4145 | ... O30: =O12+O22 -> -1.97275
A31: Cross-check: IS Finance Costs | B31: ='Income Statement'!B21 -> -10.3 | C31: ='Income Statement'!C21 -> -11.88 | D31: ='Income Statement'!D21 -> -17.12 | E31: ='Income Statement'!E21 -> -15.04 | F31: ='Income Statement'!F21 -> -10 | G31: ='Income Statement'!G21 -> -10 | H31: ='Income Statement'!H21 -> -8 | I31: ='Income Statement'!I21 -> -7 | ... O31: ='Income Statement'!O21 -> -3
A33: Key Ratios
A34: Debt / Equity (x) | B34: =IF('Balance Sheet'!B24>0,B26/'Balance Sheet'!B24,0) -> 0.097308489 | C34: =IF('Balance Sheet'!C24>0,C26/'Balance Sheet'!C24,0) -> 0.082074316 | D34: =IF('Balance Sheet'!D24>0,D26/'Balance Sheet'!D24,0) -> 0.15684552 | E34: =IF('Balance Sheet'!E24>0,E26/'Balance Sheet'!E24,0) -> 0.15886374 | F34: =IF('Balance Sheet'!F24>0,F26/'Balance Sheet'!F24,0) -> 0.11496676 | G34: =IF('Balance Sheet'!G24>0,G26/'Balance Sheet'!G24,0) -> 0.080527661 | H34: =IF('Balance Sheet'!H24>0,H26/'Balance Sheet'!H24,0) -> 0.05452064 | I34: =IF('Balance Sheet'!I24>0,I26/'Balance Sheet'!I24,0) -> 0.035375436 | ... O34: =IF('Balance Sheet'!O24>0,O26/'Balance Sheet'!O24,0) -> 0.0023529554
A35: Net Debt / EBITDA (x) | B35: =IF('Income Statement'!B14>0,B28/'Income Statement'!B14,0) -> 0.25575082 | C35: =IF('Income Statement'!C14>0,C28/'Income Statement'!C14,0) -> 0.022504421 | D35: =IF('Income Statement'!D14>0,D28/'Income Statement'!D14,0) -> -0.63726029 | E35: =IF('Income Statement'!E14>0,E28/'Income Statement'!E14,0) -> -0.15325011 | F35: =IF('Income Statement'!F14>0,F28/'Income Statement'!F14,0) -> -0.09130249 | G35: =IF('Income Statement'!G14>0,G28/'Income Statement'!G14,0) -> -0.18577642 | H35: =IF('Income Statement'!H14>0,H28/'Income Statement'!H14,0) -> -0.54548601 | I35: =IF('Income Statement'!I14>0,I28/'Income Statement'!I14,0) -> -0.92061436 | ... O35: =IF('Income Statement'!O14>0,O28/'Income Statement'!O14,0) -> -2.9221026
A36: Interest Coverage (EBITDA / Int.) | B36: =IF(ABS(B30)>0,'Income Statement'!B14/ABS(B30),0) -> 21.236441 | C36: =IF(ABS(C30)>0,'Income Statement'!C14/ABS(C30),0) -> 55.187403 | D36: =IF(ABS(D30)>0,'Income Statement'!D14/ABS(D30),0) -> 45.831968 | E36: =IF(ABS(E30)>0,'Income Statement'!E14/ABS(E30),0) -> 36.059483 | F36: =IF(ABS(F30)>0,'Income Statement'!F14/ABS(F30),0) -> 28.609627 | G36: =IF(ABS(G30)>0,'Income Statement'!G14/ABS(G30),0) -> 42.460063 | H36: =IF(ABS(H30)>0,'Income Statement'!H14/ABS(H30),0) -> 65.926976 | I36: =IF(ABS(I30)>0,'Income Statement'!I14/ABS(I30),0) -> 99.214218 | ... O36: =IF(ABS(O30)>0,'Income Statement'!O14/ABS(O30),0) -> 1162.9984
A37: Debt / Total Capital (%) | B37: =IF((B26+'Balance Sheet'!B24)>0,B26/(B26+'Balance Sheet'!B24),0) -> 0.088679245 | C37: =IF((C26+'Balance Sheet'!C24)>0,C26/(C26+'Balance Sheet'!C24),0) -> 0.075849057 | D37: =IF((D26+'Balance Sheet'!D24)>0,D26/(D26+'Balance Sheet'!D24),0) -> 0.13558035 | E37: =IF((E26+'Balance Sheet'!E24)>0,E26/(E26+'Balance Sheet'!E24),0) -> 0.13708578 | F37: =IF((F26+'Balance Sheet'!F24)>0,F26/(F26+'Balance Sheet'!F24),0) -> 0.10311227 | G37: =IF((G26+'Balance Sheet'!G24)>0,G26/(G26+'Balance Sheet'!G24),0) -> 0.074526238 | H37: =IF((H26+'Balance Sheet'!H24)>0,H26/(H26+'Balance Sheet'!H24),0) -> 0.051701824 | I37: =IF((I26+'Balance Sheet'!I24)>0,I26/(I26+'Balance Sheet'!I24),0) -> 0.034166772 | ... O37: =IF((O26+'Balance Sheet'!O24)>0,O26/(O26+'Balance Sheet'!O24),0) -> 0.002347432
A38: Net Debt / Total Capital (%) | B38: =IF((B28+'Balance Sheet'!B24)>0,B28/(B28+'Balance Sheet'!B24),0) -> 0.050280899 | C38: =IF((C28+'Balance Sheet'!C24)>0,C28/(C28+'Balance Sheet'!C24),0) -> 0.0085020243 | D38: =IF((D28+'Balance Sheet'!D24)>0,D28/(D28+'Balance Sheet'!D24),0) -> -0.26001227 | E38: =IF((E28+'Balance Sheet'!E24)>0,E28/(E28+'Balance Sheet'!E24),0) -> -0.051890001 | F38: =IF((F28+'Balance Sheet'!F24)>0,F28/(F28+'Balance Sheet'!F24),0) -> -0.029623582 | G38: =IF((G28+'Balance Sheet'!G24)>0,G28/(G28+'Balance Sheet'!G24),0) -> -0.065672756 | H38: =IF((H28+'Balance Sheet'!H24)>0,H28/(H28+'Balance Sheet'!H24),0) -> -0.23015941 | I38: =IF((I28+'Balance Sheet'!I24)>0,I28/(I28+'Balance Sheet'!I24),0) -> -0.46072685 | ... O38: =IF((O28+'Balance Sheet'!O24)>0,O28/(O28+'Balance Sheet'!O24),0) -> -4.6053029

Sheet DCF Valuation
A1: DOMS INDUSTRIES LTD — DCF VALUATION
A2: FCFF-based | WACC: 12.4% | Terminal Growth: 6.5% | 10-Year Explicit Period
A4: KEY DCF INPUTS
A5: WACC | B5: =Assumptions!B30 -> 0.124
A6: Terminal Growth Rate | B6: =Assumptions!B31 -> 0.065
A7: Shares Outstanding (Cr) | B7: =Assumptions!B90 -> 6.069
A8: Net Debt (FY25A, ₹ Cr) | B8: ='Balance Sheet'!E44 -> -13.6
A10: FCFF PROJECTIONS
B11: FY26E | C11: FY27E | D11: FY28E | E11: FY29E | F11: FY30E | G11: FY31E | H11: FY32E | I11: FY33E | J11: FY34E | K11: FY35E
A12: FCFF (₹ Cr) | B12: ='Cash Flow Statement'!F34 -> -6.066566 | C12: ='Cash Flow Statement'!G34 -> 84.164363 | D12: ='Cash Flow Statement'!H34 -> 300.63501 | E12: ='Cash Flow Statement'!I34 -> 438.30788 | F12: ='Cash Flow Statement'!J34 -> 611.8296 | G12: ='Cash Flow Statement'!K34 -> 764.95365 | H12: ='Cash Flow Statement'!L34 -> 957.2964 | I12: ='Cash Flow Statement'!M34 -> 1150.3516 | ... K12: ='Cash Flow Statement'!O34 -> 1570.7906
A13: Year Number | B13: 1 | C13: 2 | D13: 3 | E13: 4 | F13: 5 | G13: 6 | H13: 7 | I13: 8 | J13: 9 | K13: 10
A14: Discount Factor | B14: =1/(1+$B$5)^B13 -> 0.88967972 | C14: =1/(1+$B$5)^C13 -> 0.79153 | D14: =1/(1+$B$5)^D13 -> 0.70420818 | E14: =1/(1+$B$5)^E13 -> 0.62651973 | F14: =1/(1+$B$5)^F13 -> 0.5574019 | G14: =1/(1+$B$5)^G13 -> 0.49590916 | H14: =1/(1+$B$5)^H13 -> 0.44120032 | I14: =1/(1+$B$5)^I13 -> 0.39252698 | ... K14: =1/(1+$B$5)^K13 -> 0.31069688
A15: PV of FCFF | B15: =B12*B14 -> -5.3973007 | C15: =C12*C14 -> 66.618618 | D15: =D12*D14 -> 211.70963 | E15: =E12*E14 -> 274.60854 | F15: =F12*F14 -> 341.03498 | G15: =G12*G14 -> 379.34752 | H15: =H12*H14 -> 422.35948 | I15: =I12*I14 -> 451.54405 | ... K15: =K12*K14 -> 488.03975
A17: TERMINAL VALUE
A18: Terminal Year FCFF (FY35E) | B18: =K12 -> 1570.7906
A19: Terminal Value = FCFF × (1+g) / (WACC - g) | B19: =B18*(1+B6)/(B5-B6) -> 28354.102
A20: PV of Terminal Value | B20: =B19*K14 -> 8809.531
A22: DCF SUMMARY
A23: PV of Explicit FCFF | B23: =SUM(B15:K15) -> 3107.9818
A24: PV of Terminal Value | B24: =B20 -> 8809.531
A25: Enterprise Value (EV) | B25: =B23+B24 -> 11917.513
A26: (-) Net Debt | B26: =-B8 -> 13.6
A27: Equity Value | B27: =B25+B26 -> 11931.113
A28: Implied Share Price (₹) | B28: =B27/B7 -> 1965.9108
A30: CMP (₹) | B30: =Assumptions!B92 -> 2350
A31: Upside / (Downside) | B31: =B28/B30-1 -> -0.1634422
A33: Terminal Value as % of EV | B33: =B24/B25 -> 0.73920886
A35: SENSITIVITY: IMPLIED SHARE PRICE (₹) | D35: Terminal Growth Rate -->
A36: =B28 -> 1965.9108 | B36: 0.04 | C36: 0.045 | D36: 0.05 | E36: 0.055 | F36: 0.06 | G36: 0.065 | H36: 0.07
A37: 0.11 | B37: 1915.4435 | C37: 2026.6302 | D37: 2156.3481 | E37: 2309.651 | F37: 2493.6145 | G37: 2718.4588 | H37: 2999.5141
A38: 0.113 | B38: 1814.7385 | C38: 1914.2064 | D38: 2029.4628 | E38: 2164.591 | F38: 2325.2152 | G38: 2519.3027 | H38: 2758.5268
A39: 0.116 | B39: 1722.371 | C39: 1811.6854 | D39: 1914.5323 | E39: 2034.2393 | F39: 2175.3226 | G39: 2344.0693 | H39: 2549.5
A40: 0.12 | B40: 1610.5482 | C40: 1688.3263 | D40: 1777.2157 | E40: 1879.7803 | F40: 1999.439 | G40: 2140.8539 | H40: 2310.5517
A41: 0.124 | B41: 1509.9652 | C41: 1578.0684 | D41: 1655.3749 | E41: 1743.8851 | F41: 1846.2251 | G41: 1965.9108 | H41: 2107.7606
A42: 0.128 | B42: 1419.0723 | C42: 1479.0001 | D42: 1546.611 | E42: 1623.4837 | F42: 1711.6611 | G42: 1813.835 | H42: 1933.625
A43: 0.134 | B43: 1298.1626 | C43: 1348.0437 | D43: 1403.863 | E43: 1466.7481 | F43: 1538.1311 | G43: 1619.8594 | H43: 1714.3579

Sheet Trading Comps
A1: DOMS INDUSTRIES LTD — TRADING COMPARABLES
A2: As of February 2026 | Sources: NSE, BSE, Company filings
A4: Company | B4: Mkt Cap (₹ Cr) | C4: Revenue (₹ Cr) | D4: EBITDA (₹ Cr) | E4: PAT (₹ Cr) | F4: P/E (x) | G4: EV/EBITDA (x) | H4: EV/Sales (x)
A5: PURE-PLAY STATIONERY PEERS | E5: Exc. Exceptional items from other income
A6: DOMS Industries | B6: 14269 | C6: 2231 | D6: 390 | E6: 233 | F6: =B6/E6 -> 61.240343 | G6: 35 | H6: 6.4
A7: Flair Writing Industries | B7: 3288 | C7: 1225 | D7: 214 | E7: 136 | F7: =B7/E7 -> 24.176471 | G7: 14 | H7: 2.7
A8: Navneet Education | B8: 3285 | C8: 1725 | D8: 299 | E8: 215 | F8: =B8/E8 -> 15.27907 | G8: 9.5 | H8: 1.65
A9: Kokuyo Camlin | B9: 854 | C9: 760 | D9: 19 | E9: -1 | F9: N/M | G9: 45.1 | H9: 1.1
A10: Linc Ltd | B10: 639 | C10: 546 | D10: 59 | E10: 38 | F10: =B10/E10 -> 16.815789 | G10: 10.2 | H10: 1.3
A12: FMCG / CONSUMER BRAND LATERAL COMPS
A13: Pidilite Industries | B13: 154238 | C13: 14159 | D13: 3313 | E13: 2314 | F13: =B13/E13 -> 66.654278 | G13: 43 | H13: 11
A14: Asian Paints | B14: 230000 | C14: 34696 | D14: 6346 | E14: 5412 | F14: =B14/E14 -> 42.498152 | G14: 34 | H14: 6.7
A15: Colgate-Palmolive India | B15: 62428 | C15: 5902 | D15: 1858 | E15: 1327 | F15: =B15/E15 -> 47.044461 | G15: 32 | H15: 10.5
A17: VALUATION SUMMARY
A18: Stationery Peer Median | B18: =MEDIAN(B7:B10) -> 2069.5 | C18: =MEDIAN(C7:C10) -> 992.5 | D18: =MEDIAN(D7:D10) -> 136.5 | E18: =MEDIAN(E7:E10) -> 87 | F18: =MEDIAN(F7,F10) -> 20.49613 | G18: =MEDIAN(G7:G10) -> 12.1 | H18: =MEDIAN(H7:H10) -> 1.475
A19: FMCG Lateral Median | B19: =MEDIAN(B13:B15) -> 154238 | C19: =MEDIAN(C13:C15) -> 14159 | D19: =MEDIAN(D13:D15) -> 3313 | E19: =MEDIAN(E13:E15) -> 2314 | F19: =MEDIAN(F13:F15) -> 47.044461 | G19: =MEDIAN(G13:G15) -> 34 | H19: =MEDIAN(H13:H15) -> 10.5
A21: IMPLIED DOMS VALUATION (₹ per share)
A22: Method | B22: Multiple Used | C22: Implied EV (₹ Cr) | D22: Implied Price (₹)
A23: Stationery EV/EBITDA | B23: =G18 -> 12.1 | C23: =B23*$D$6 -> 4719 | D23: =(C23-'Balance Sheet'!F44)/Assumptions!B90 -> 783.75163
A24: FMCG EV/EBITDA | B24: =G19 -> 34 | C24: =B24*$D$6 -> 13260 | D24: =(C24-'Balance Sheet'!F44)/Assumptions!B90 -> 2191.0675
A25: Stationery P/E | B25: =F18 -> 20.49613 | C25: N/A | D25: =B25*'Income Statement'!E29 -> 721.18055
A26: FMCG P/E | B26: =F19 -> 47.044461 | C26: N/A | D26: =B26*'Income Statement'!E29 -> 1655.3149
A29: BLENDED COMPS VALUATION
A30: Method | B30: Implied Price (₹) | C30: Weight | D30: Weighted Price (₹)
A31: Stationery EV/EBITDA | B31: =D23 -> 783.75163 | C31: 0.1 | D31: =B31*C31 -> 78.375163
A32: FMCG EV/EBITDA | B32: =D24 -> 2191.0675 | C32: 0.4 | D32: =B32*C32 -> 876.427
A33: Stationery P/E | B33: =D25 -> 721.18055 | C33: 0.15 | D33: =B33*C33 -> 108.17708
A34: FMCG P/E | B34: =D26 -> 1655.3149 | C34: 0.35 | D34: =B34*C34 -> 579.36023
A35: Total Weight Check | C35: =SUM(C31:C34) -> 1
A36: Blended Implied Price (₹) | D36: =SUM(D31:D34) -> 1642.3395
A38: Current Market Price (₹) | D38: =Assumptions!B92 -> 2350
A39: Premium / (Discount) to CMP | D39: =D36/D38-1 -> -0.30113214
A41: NOTES:
A42: DOMS trades at premium to stationery peers but at a slight discount to FMCG names.
A43: This is justified given: (1) higher growth (20%+ CAGR), (2) pester power moat,
A44: (3) FILA partnership for global exports, (4) diversification into hygiene/bags.

Sheet Precedent Transactions
A1: DOMS INDUSTRIES LTD — PRECEDENT TRANSACTION ANALYSIS
A2: Indian Stationery & Lateral Consumer M&A
A4: Transaction | B4: Year | C4: Acquirer | D4: Target | E4: Stake (%) | F4: Deal Value | G4: Target Rev (at deal) | H4: Implied EV/Sales | I4: Key Insight
A5: PURE-PLAY STATIONERY M&A
A6: FILA → DOMS (Minority) | B6: 2012 | C6: F.I.L.A. S.p.A | D6: DOMS (Writefine) | E6: 0.185 | F6: €5.4M (~₹36 Cr) | G6: ~€10M (~₹67 Cr) | H6: ~3.0x | I6: Entry at early stage; DOMS was sub-scale
A7: FILA → DOMS (Control) | B7: 2015 | C7: F.I.L.A. S.p.A | D7: DOMS Industries | E7: 51% (total) | F7: €36M (~₹291 Cr) | G7: ~€7M (~₹47 Cr) | H7: ~8.0x | I7: Control premium; DOMS scaled post-partnership
A8: Kokuyo → Camlin | B8: 2011 | C8: Kokuyo Co. (Japan) | D8: Camlin Ltd | E8: 0.5074 | F8: ~₹60 Cr (@₹85/sh) | G8: ~₹440 Cr | H8: ~2.0x | I8: 2x sales for alpha-kids brand & retail reach
A11: LATERAL CONSUMER / DISTRIBUTION COMPS
A12: Mitsubishi → Linc JV | B12: 2024-25 | C12: Mitsubishi Pencil (Japan) | D12: Linc Ltd (JV) | E12: 51% JV | F12: ₹200M (~₹20 Cr) | G12: JV entity (new) | H12: N/A (JV) | I12: Premiumization play; ₹20 price-point products
A13: FILA stake sale (ABB) | B13: 45627 | C13: Market (ABB) | D13: DOMS Industries | E13: 4.57% sold | F13: ₹799 Cr | G13: Rev ~₹1,913 Cr (FY25) | H13: ~9.1x | I13: Implied ~₹17,500 Cr mkt cap (~9.1x EV/Sales on FY25 rev)
A14: DOMS → Uniclan | B14: 45536 | C14: DOMS Industries | D14: Uniclan Healthcare | E14: 0.5177 | F14: ₹54.9 Cr | G14: ~₹80 Cr (est) | H14: ~1.3x | I14: Baby hygiene entry; leverages DOMS distribution
A16: PTA VALUATION BENCHMARKS | F16: CONTROL PREMIUM DERIVATION
A17: Metric | B17: Low | C17: Median | D17: High | F17: FILA Minority (2012) | G17: FILA Control (2015) | H17: Raw Step-Up | I17: Adj. Control Premium
A18: EV/Sales (Stationery) | B18: 2.0x | C18: 4.0x | D18: 8.0x | F18: 3.0x EV/Sales | G18: 8.0x EV/Sales | H18: =8/3-1 -> 1.6666667 | I18: ~33-60%
A19: Control Premium Observed | B19: 0.15 | C19: 0.25 | D19: 0.4 | F19: 18.5% stake | G19: 51% stake (control) | H19: (3 yrs apart) | I19: (adj. for biz improvement)
A21: IMPLIED DOMS VALUATION FROM PTA
B22: Bear (2.0x Sales) | C22: Base (4.0x Sales) | D22: Bull (8.0x Sales)
A23: FY26E Revenue (₹ Cr) | B23: ='Income Statement'!F4 -> 2352.5349 | C23: ='Income Statement'!F4 -> 2352.5349 | D23: ='Income Statement'!F4 -> 2352.5349
A24: Implied EV (₹ Cr) | B24: =B23*2 -> 4705.0698 | C24: =C23*4 -> 9410.1396 | D24: =D23*8 -> 18820.279
A25: Implied Share Price (₹) | B25: =(B24-'Balance Sheet'!F44)/Assumptions!B90 -> 781.45633 | C25: =(C24-'Balance Sheet'!F44)/Assumptions!B90 -> 1556.7191 | D25: =(D24-'Balance Sheet'!F44)/Assumptions!B90 -> 3107.2447
A27: BLENDED PTA VALUATION
A28: Scenario | B28: Implied Price (₹) | C28: Weight | D28: Weighted Price (₹)
A29: Bear (2.0x Sales) | B29: =B25 -> 781.45633 | C29: 0.25 | D29: =B29*C29 -> 195.36408
A30: Base (4.0x Sales) | B30: =C25 -> 1556.7191 | C30: 0.5 | D30: =B30*C30 -> 778.35955
A31: Bull (8.0x Sales) | B31: =D25 -> 3107.2447 | C31: 0.25 | D31: =B31*C31 -> 776.81117
A32: Blended PTA Price (₹) | D32: =SUM(D29:D31) -> 1750.5348
A33: Premium / (Discount) to CMP | D33: =D32/Assumptions!B92-1 -> -0.25509157
A34: KEY INSIGHT: | B34: The FILA → DOMS deal evolution (3x → 8x sales) shows a massive re-rating as DOMS scaled.
B35: The 2024 FILA stake sale at market implied ~9.1x EV/Sales (FY25 rev), confirming the 'Consumer Brand' re-rating.
B36: Kokuyo-Camlin at 2x sales sets the floor for established stationery brands in India.

Sheet Returns Analysis
A1: DOMS INDUSTRIES LTD - RETURNS ANALYSIS
A2: 10-Year Hold: FY26 Entry → FY36 Exit | Equity Investor Perspective
A4: ENTRY VALUATION (FY26)
A5: Entry Price (₹/share) | B5: =Assumptions!B92 -> 2350
A6: Shares Outstanding (Cr) | B6: =Assumptions!B90 -> 6.069
A7: Entry Equity Value (₹ Cr) | B7: =B5*B6 -> 14262.15
A8: (+) Net Debt FY25 (₹ Cr) | B8: ='Balance Sheet'!E44 -> -13.6
A9: Entry EV (₹ Cr) | B9: =B7+B8 -> 14248.55
A11: Entry P/E (FY26E EPS) | B11: =B5/'Income Statement'!F29 -> 57.774387 | D11: =B11 -> 57.774387
A12: Entry EV/EBITDA (FY26E) | B12: =B9/'Income Statement'!F14 -> 34.609597
A13: Entry EV/Sales (FY26E) | B13: =B9/'Income Statement'!F4 -> 6.0566795
A15: EXIT SCENARIO ANALYSIS (FY36 = Year 10)
A16: FY35E Revenue (₹ Cr) | B16: ='Income Statement'!O4 -> 10107.071
A17: FY35E EBITDA (₹ Cr) | B17: ='Income Statement'!O14 -> 2294.3051
A18: FY35E PAT (₹ Cr) | B18: ='Income Statement'!O26 -> 1503.4793
A19: FY35E EPS (₹) | B19: ='Income Statement'!O29 -> 247.73098
A20: Cumulative Dividends / Share (₹) | B20: =SUM('Income Statement'!F30:O30) -> 120.98746
B22: Bear Case | C22: Base Case | D22: Bull Case | E22: Ultra Bull
A23: Exit P/E Multiple | B23: 35 | C23: 50 | D23: 60 | E23: 70
A24: Exit Share Price (₹) | B24: =B23*$B$19 -> 8670.5842 | C24: =C23*$B$19 -> 12386.549 | D24: =D23*$B$19 -> 14863.859 | E24: =E23*$B$19 -> 17341.168
A25: Total Return / Share (₹) | B25: =B24+$B$20-$B$5 -> 6441.5716 | C25: =C24+$B$20-$B$5 -> 10157.536 | D25: =D24+$B$20-$B$5 -> 12634.846 | E25: =E24+$B$20-$B$5 -> 15112.156
A26: MOIC (x) | B26: =(B24+$B$20)/$B$5 -> 3.7410943 | C26: =(C24+$B$20)/$B$5 -> 5.3223559 | D26: =(D24+$B$20)/$B$5 -> 6.3765302 | E26: =(E24+$B$20)/$B$5 -> 7.4307046
A27: IRR (%) | B27: =((B23*$B$19+$B$20)/($B$5))^(1/10)-1 -> 0.14103736 | C27: =((C23*$B$19+$B$20)/($B$5))^(1/10)-1 -> 0.18198072 | D27: =((D23*$B$19+$B$20)/($B$5))^(1/10)-1 -> 0.20353422 | E27: =((E23*$B$19+$B$20)/($B$5))^(1/10)-1 -> 0.22208946
A29: IRR SENSITIVITY: Entry P/E vs Exit P/E | D29: EXIT PE ----->
A30: =((C23*$B$19+$B$20)/(D11*'Income Statement'!F29))^(1/10)-1 -> 0.18198072 | B30: 35 | C30: 40 | D30: 50 | E30: 55 | F30: 60 | G30: 65 | H30: 70
A31: 54 | B31: 0.14877248 | C31: 0.16401465 | D31: 0.18999339 | E31: 0.20128377 | F31: 0.21169301 | G31: 0.22135476 | H31: 0.23037404
A32: 57 | B32: 0.14257815 | C32: 0.15773813 | D32: 0.18357679 | E32: 0.19480629 | F32: 0.2051594 | G32: 0.21476906 | H32: 0.2237397
A33: 60 | B33: 0.1367325 | C33: 0.15181491 | D33: 0.17752138 | E33: 0.18869343 | F33: 0.19899356 | G33: 0.20855406 | H33: 0.21747881
A34: 63 | B34: 0.13119987 | C34: 0.14620888 | D34: 0.17179022 | E34: 0.1829079 | F34: 0.1931579 | G34: 0.20267187 | H34: 0.21155317
A35: 66 | B35: 0.12594975 | C35: 0.1408891 | D35: 0.16635171 | E35: 0.17741779 | F35: 0.18762022 | G35: 0.19709003 | H35: 0.20593012
A36: 69 | B36: 0.12095581 | C36: 0.1358289 | D36: 0.16117858 | E36: 0.17219557 | F36: 0.18235276 | G36: 0.19178056 | H36: 0.20058144
A37: 72 | B37: 0.1161952 | C37: 0.13100513 | D37: 0.15624715 | E37: 0.16721736 | F37: 0.1773314 | G37: 0.18671917 | H37: 0.19548267
A39: INVESTMENT THESIS
A40: 1. Market Leader in Structural Growth Segment | B40: India's 2nd largest branded stationery player (~12% market share by value). Indian stationery market growing at 12-15% CAGR driven by 350M+ children under 14, rising education spend (>3.4% of GDP), and organized sector share gains from unorganized players.
A41: 2. FMCG-Like Distribution Moat | B41: 145K+ retail outlets, 5,800+ distributors, 130+ super-stockists across 28 states. Replicating this network takes 10+ years. General trade contributes >70% of sales - classic kirana moat similar to Pidilite/Colgate.
A42: 3. 'Pester Power' Brand | B42: Children choose DOMS by name - the brand has 29% pencil market share, 30% math-box share. Brand recall is driven by in-school marketing (DOMS Art League) and school-level competitions. Switching cost is emotional, not rational.
A43: 4. FILA Partnership = Global Export Platform | B43: Strategic partnership with F.I.L.A. (Italy) since 2012 gives access to 150+ countries. FILA uses DOMS as its global manufacturing hub for cost-effective production. Export revenue growing; FILA partnership expected to drive 15-20% of revenue long-term.
A44: 5. Capacity Doubling in FY27 | B44: 44-acre Umbergaon facility to double manufacturing capacity. Commercial production from Q2 FY27. This is the key growth unlock - capex-heavy phase (₹250 Cr FY26, ₹240 Cr FY27) transitions to harvesting from FY28.
A45: 6. Smart Diversification | B45: Uniclan (baby diapers/wipes) acquired Sep 2024 - leverages same school/kirana distribution. Seven S.p.A JV for premium backpacks. ClapJoy (toys, 30% stake). Each adjacent category shares the 'child ecosystem' distribution.
A46: 7. Management Credibility | B46: Walk-the-Talk score: 4.6/5. Revenue growth consistently delivered at upper end of guidance. EBITDA margins maintained within/above guided range. Founder-led business (Raveshia-Rajani families) with FILA's operational rigor.
A47: 8. GST Tailwind | B47: GST 2.0 rate reductions (Sep 2025) benefit organized brands like DOMS - accelerates shift from unorganized to organized sector. Short-term disruption already absorbed in Q2 FY26.
A48: 9. Premiumization | B48: Product mix shifting toward higher-value categories: office supplies, hobby & craft, kits & combos growing faster than base pencils. Average realization per SKU improving.
A50: KEY RISKS & MITIGATING FACTORS
A51: Risk | B51: Severity | C51: Mitigant
A52: Wooden pencil concentration (~32% of sales) | B52: MEDIUM | C52: Declining share of mix as pens, office supplies, hobby grow. Pencil capacity expansion ensures volume hold while mix shifts.
A53: Commodity price inflation (polymers, waxes, wood) | B53: MEDIUM | C53: Vertically integrated manufacturing absorbs cost. Pricing power via branded product. Margins guided at 16.5-17.5% floor.
A54: US tariff headwinds on exports | B54: LOW-MED | C54: US is <5% of total revenue. FILA partnership diversifies exports across 150+ countries. Domestic market (89%) is the core driver.
A55: Uniclan Healthcare integration risk | B55: MEDIUM | C55: Uniclan already contributing revenue; EBITDA margins stabilizing at 7.5-8% per management. Leverages existing distribution.
A56: FILA promoter stake dilution (now ~26%) | B56: LOW | C56: FILA committed to long-term strategic partnership. 90-day lock-up post Dec 2024 sale. Still single largest shareholder.
A57: Premium valuation risk (65x P/E) | B57: HIGH | C57: Key risk. Any growth miss could cause de-rating. Mitigated by earnings CAGR (~20-25%) reducing forward P/E rapidly.
A58: Execution risk on 44-acre facility | B58: MEDIUM | C58: Minor delays from monsoons already absorbed. First buildings completing Q1 FY27. Management has track record of on-time delivery.
A59: Competition from Kokuyo Camlin, Flair, Linc-Mitsubishi JV | B59: LOW-MED | C59: DOMS is the fastest growing. Kokuyo Camlin struggling (negative profits). Flair is a pen-focused player. Linc-Mitsubishi JV is early stage.
A61: DUE DILIGENCE FOCUS AREAS
A62: Area | B62: Priority | C62: Key Questions
A63: FILA Relationship & Export Strategy (FILA relationship DD) | B63: CRITICAL | C63: What is FILA's long-term commitment post-26% stake? Will they sell further? What are the export revenue guarantees under the FILA distribution agreement? What happens if FILA divests entirely?
A64: Umbergaon Facility Progress (Capacity DD) | B64: HIGH | C64: Physical verification of construction progress. What % of capacity is contracted to customers? What is the ramp-up timeline (Q2 FY27 start → full capacity by when)?
A65: Uniclan Integration & Hygiene Margins (Adjacency DD) | B65: HIGH | C65: Verify EBITDA trajectory (7.5-8% guided). Diaper market competitive intensity (Pampers, Huggies). What is DOMS Wowper's brand positioning - premium or mass?
A66: Distribution Network Depth (Commercial DD) | B66: HIGH | C66: Verify the 145K outlet claim independently. What is throughput per outlet? What is the overlap with Uniclan distribution? How many are exclusive vs. multi-brand?
A67: Raw Material Sourcing & Cost Structure (Technology DD) | B67: MEDIUM | C67: Verify backward integration claims. Manufacturing automation levels. What % of raw materials are in-house vs. sourced? Wood supply chain for pencils - sustainability of Jammu facility?
A68: Working Capital Efficiency (Financial DD) | B68: MEDIUM | C68: Inventory days have been declining (90 → 75). Is this sustainable? Verify receivable quality - any channel stuffing? Payable terms with key suppliers?
A69: FILA-DOMS Transfer Pricing | B69: HIGH | C69: What is the transfer pricing mechanism for FILA exports? Are margins fair? Is DOMS getting full economic benefit or is value being extracted to FILA?
A70: Management Depth & Key-Person Risk (Management DD) | B70: MEDIUM | C70: Post-founder era - how deep is the management bench? CFO Rahul Shah is articulate and credible. What is succession planning for MD Santosh Raveshia?
A72: VALUATION FOOTBALL FIELD (₹ per share)
A73: Methodology | B73: Low | C73: Base | D73: High
A74: DCF (WACC 10.5-14.5%) | B74: ='DCF Valuation'!H43 -> 1714.3579 | C74: ='DCF Valuation'!B28 -> 1965.9108 | D74: ='DCF Valuation'!B37 -> 1915.4435
A75: Trading Comps (EV/EBITDA) | B75: ='Trading Comps'!D23 -> 783.75163 | C75: =AVERAGE('Trading Comps'!D23,'Trading Comps'!D24) -> 1487.4096 | D75: ='Trading Comps'!D24 -> 2191.0675
A76: Precedent Transactions (EV/Sales) | B76: ='Precedent Transactions'!B25 -> 781.45633 | C76: ='Precedent Transactions'!C25 -> 1556.7191 | D76: ='Precedent Transactions'!D25 -> 3107.2447
A77: P/E Based (FY26E) | B77: =35*'Income Statement'!F29 -> 1423.6412 | C77: =50*'Income Statement'!F29 -> 2033.7732 | D77: =70*'Income Statement'!F29 -> 2847.2825
A79: Current Market Price | B79: =Assumptions!B92 -> 2350
A81: MASTER BLENDED VALUATION
A82: Equal-weighted across DCF, Trading Comps & Precedent Transactions
A83: Methodology | B83: Blended Price (₹) | C83: Weight | D83: Weighted Price (₹) | E83: Source
A84: DCF Valuation (FCFF) | B84: ='DCF Valuation'!B28 -> 1965.9108 | C84: 0.4 | D84: =B84*C84 -> 786.36433 | E84: DCF Valuation!B28
A85: Trading Comps (Blended) | B85: ='Trading Comps'!D36 -> 1642.3395 | C85: 0.3 | D85: =B85*C85 -> 492.70184 | E85: Trading Comps!D36
A86: Precedent Transactions (Blended) | B86: ='Precedent Transactions'!D32 -> 1750.5348 | C86: 0.3 | D86: =B86*C86 -> 525.16044 | E86: Precedent Transactions!D32
A87: Total Weight Check | C87: =SUM(C84:C86) -> 1
A88: BLENDED FAIR VALUE PER SHARE (₹) | D88: =SUM(D84:D86) -> 1804.2266
A90: Current Market Price (₹) | D90: =Assumptions!B92 -> 2350
A91: Premium / (Discount) to CMP | D91: =D88/D90-1 -> -0.232244
A92: Implied Fair Value P/E (FY26E) | D92: =D88/'Income Statement'!F29 -> 44.356633
A93: VERDICT
A94: At CMP of ~₹2,350, DOMS trades at ~63x FY26E P/E - optically expensive but compressing rapidly on a forward basis.
A95: On FY27E earnings (post-capacity ramp), the forward P/E compresses to ~46x, which is in line with premium consumer franchises growing 20%+ (Pidilite, Asian Paints in their growth phases).
A96: Base case IRR of ~18-19% over a 5-year hold (5.44x MOIC) makes this a BUY at or below ₹2,400 for patient equity investors. See note below for PE-lens justification.
A98: WHY 18-19% IRR JUSTIFIES A BUY (PE LENS)
A100: 1. Fund-Level 20% ≠ Deal-Level 20%
A101: PE funds target ~20% net IRR at the fund level, but this is a blended return across the portfolio. Funds expect 2-3 deals to return 3-5x (carrying the fund), while several deliver 1.5-2.5x. A 2.3x MOIC over a period of 5 years and 5.4x MOIC over the 10-year period/ ~18% IRR on a low-risk, high-visibility consumer compounder is a solid 'base hit' that anchors portfolio downside. Not every deal needs to be a home run.
A103: 2. Risk-Adjusted Return is Superior
A104: A 18% IRR in DOMS is not the same as a 18% IRR in an early-stage or turnaround bet. DOMS offers: (a) market leadership with structural tailwinds, (b) 20%+ earnings CAGR with high visibility, (c) asset-light, cash-generative model post FY28, (d) zero leverage risk (net cash by FY28E). The probability of achieving base case is significantly higher than a typical PE deal — the risk-adjusted IRR is closer to 20%+ on an expected-value basis. Basically low beta stable cash flows from a consumer staple business.
A106: 3. Multiple Compression Already Baked In
A107: Entry at ~58x FY26E P/E, exit at 50x FY30E P/E implies ~14% multiple de-rating over 5 years. The entire return comes from earnings growth (~2.5x EPS growth from ₹39.69 to ₹99.34), not multiple expansion. This is the safest form of PE return — you're underwriting the business, not the market mood.
A109: 4. Asymmetric Upside from Sensitivity Table
... A113: For a PE fund focused on Indian consumer, a company like DOMS offers: portfolio 'quality anchor' (de-risks the fund narrative to LPs), potential platform for bolt-on acquisitions (Uniclan playbook), and exposure to the $8B Indian stationery market before it fully consolidates. The strategic optionality is not captured in a simple 5-year IRR calculation.
