Workbook

Sheet Cover
A1: RMC SWITCHGEARS LIMITED
A2: Three-Statement Financial Model & Valuation
A4: BSE: 540358 | CIN: L25111RJ1994PLC008698
A5: Jaipur, Rajasthan, India
A7: Model Specifications
A8: Historical Period: FY22 – FY25 (Actuals)
A9: Latest Available: 9M FY26 (Apr-Dec 2025)
A10: Projection Period: FY26E – FY35E (10 Years)
A11: Scenarios: Bull / Base / Bear
A12: Valuation: DCF (FCFF) + Comparable Companies → Blended Fair Value
A14: Key Segments: Electrical Products | Electrical EPC | Solar EPC | Solar Products (upcoming)
A16: Disclaimer: This model is for analytical purposes only. Not investment advice.

Sheet Assumptions
A1: RMC SWITCHGEARS LTD — KEY ASSUMPTIONS
A3: All figures in ₹ Crores unless stated | D3: FY22A | E3: FY23A | F3: FY24A | G3: FY25A | H3: FY26E | I3: FY27E | J3: FY28E | K3: FY29E | L3: FY30E | M3: FY31E | N3: FY32E | O3: FY33E | P3: FY34E | Q3: FY35E | R3: Rationale
A5: REVENUE ASSUMPTIONS
A6: Revenue from Operations | D6: 42.2 | E6: 125.3 | F6: 172.6 | G6: 316.3 | H6: 475 | I6: 665 | J6: 930 | K6: 1255 | L6: 1630 | M6: 2040 | N6: 2450 | O6: 2890 | P6: 3350 | Q6: 3820 | R6: Base case; mgmt guides ₹2300Cr by FY28, ₹5000Cr by FY30
A7: YoY Revenue Growth (%) | D7: n/a | E7: =(E6-D6)/D6 -> 1.9691943 | F7: =(F6-E6)/E6 -> 0.37749401 | G7: =(G6-F6)/F6 -> 0.83256083 | H7: =(H6-G6)/G6 -> 0.50173886 | I7: =(I6-H6)/H6 -> 0.4 | J7: =(J6-I6)/I6 -> 0.39849624 | K7: =(K6-J6)/J6 -> 0.34946237 | L7: =(L6-K6)/K6 -> 0.29880478 | ... Q7: =(Q6-P6)/P6 -> 0.14029851 | R7: Growth moderates as base scales; still above industry avg
A9: MARGIN ASSUMPTIONS
A10: COGS (% of Revenue) | D10: 0.87 | E10: 0.792 | F10: 0.553 | G10: 0.703 | H10: 0.72 | I10: 0.71 | J10: 0.7 | K10: 0.695 | L10: 0.69 | M10: 0.688 | N10: 0.685 | O10: 0.683 | P10: 0.68 | Q10: 0.678 | R10: EPC mix increases COGS; solar mfg offsets modestly over time
A11: Implied Gross Margin (%) | D11: =1-D10 -> 0.13 | E11: =1-E10 -> 0.208 | F11: =1-F10 -> 0.447 | G11: =1-G10 -> 0.297 | H11: =1-H10 -> 0.28 | I11: =1-I10 -> 0.29 | J11: =1-J10 -> 0.3 | K11: =1-K10 -> 0.305 | ... Q11: =1-Q10 -> 0.322 | R11: Gradual recovery with solar backward integration
A12: Employee Cost (% of Revenue) | D12: 0.059 | E12: 0.044 | F12: 0.058 | G12: 0.047 | H12: 0.05 | I12: 0.048 | J12: 0.045 | K12: 0.043 | L12: 0.041 | M12: 0.04 | N12: 0.039 | O12: 0.038 | P12: 0.037 | Q12: 0.036 | R12: Operating leverage as revenue scales faster than headcount
A13: Other Expenses (% of Revenue) | D13: 0.058 | E13: 0.059 | F13: 0.079 | G13: 0.064 | H13: 0.07 | I13: 0.068 | J13: 0.065 | K13: 0.063 | L13: 0.06 | M13: 0.058 | N13: 0.056 | O13: 0.055 | P13: 0.054 | Q13: 0.053 | R13: Scaled operations reduce % but absolute value grows
A14: Implied EBITDA Margin (%) | D14: =D11-D12-D13 -> 0.013 | E14: =E11-E12-E13 -> 0.105 | F14: =F11-F12-F13 -> 0.31 | G14: =G11-G12-G13 -> 0.186 | H14: =H11-H12-H13 -> 0.16 | I14: =I11-I12-I13 -> 0.174 | J14: =J11-J12-J13 -> 0.19 | K14: =K11-K12-K13 -> 0.199 | ... Q14: =Q11-Q12-Q13 -> 0.233 | R14: Converging to 20-23% as product mix matures & integration
A15: Depreciation (% of Revenue) | D15: 0.027 | E15: 0.009 | F15: 0.016 | G15: 0.013 | H15: 0.018 | I15: 0.02 | J15: 0.022 | K15: 0.022 | L15: 0.021 | M15: 0.02 | N15: 0.019 | O15: 0.018 | P15: 0.018 | Q15: 0.017 | R15: Rises with solar plant capex, then normalises
A16: Avg Interest Rate on Debt (%) | D16: 0.1 | E16: 0.115 | F16: 0.11 | G16: 0.105 | H16: 0.105 | I16: 0.1 | J16: 0.095 | K16: 0.095 | L16: 0.09 | M16: 0.09 | N16: 0.088 | O16: 0.088 | P16: 0.085 | Q16: 0.085 | R16: Declining as credit rating upgrades (IVR BBB/Stable)
A17: Effective Tax Rate (%) | D17: 0.15 | E17: 0.258 | F17: 0.252 | G17: 0.248 | H17: 0.252 | I17: 0.252 | J17: 0.252 | K17: 0.252 | L17: 0.252 | M17: 0.252 | N17: 0.252 | O17: 0.252 | P17: 0.252 | Q17: 0.252 | R17: 25.17% statutory rate for Indian cos (new regime)
A19: WORKING CAPITAL ASSUMPTIONS
A20: Receivable Days | D20: 210 | E20: 167 | F20: 185 | G20: 170 | H20: 155 | I20: 140 | J20: 130 | K20: 120 | L20: 115 | M20: 110 | N20: 105 | O20: 100 | P20: 95 | Q20: 90 | R20: Improving with smart metering & cash collection cycle of ~60d
A21: Inventory Days | D21: 28 | E21: 33 | F21: 35 | G21: 30 | H21: 32 | I21: 30 | J21: 28 | K21: 27 | L21: 26 | M21: 25 | N21: 25 | O21: 24 | P21: 24 | Q21: 23 | R21: EPC model keeps inventory lean; solar plant adds slightly
A22: Payable Days | D22: 85 | E22: 95 | F22: 100 | G22: 90 | H22: 95 | I22: 90 | J22: 85 | K22: 80 | L22: 78 | M22: 75 | N22: 73 | O22: 70 | P22: 68 | Q22: 65 | R22: Vendor relationships strengthen with scale
A23: Other Current Assets (% of Rev) | D23: ='Balance Sheet'!C15/'Income Statement'!C5 -> 0.48815166 | E23: ='Balance Sheet'!D15/'Income Statement'!D5 -> 0.045490822 | F23: ='Balance Sheet'!E15/'Income Statement'!E5 -> 0.030127462 | G23: ='Balance Sheet'!F15/'Income Statement'!F5 -> 0.037938666 | H23: 0.03 | I23: 0.024 | J23: 0.019 | K23: 0.016 | L23: 0.014 | M23: 0.012 | N23: 0.011 | O23: 0.01 | P23: 0.009 | Q23: 0.008
A24: Other Current Liabilities (% of Rev) | D24: ='Balance Sheet'!C35/'Income Statement'!C5 -> 0.18957346 | E24: ='Balance Sheet'!D35/'Income Statement'!D5 -> 0.07980846 | F24: ='Balance Sheet'!E35/'Income Statement'!E5 -> 0.069524913 | G24: ='Balance Sheet'!F35/'Income Statement'!F5 -> 0.12171989 | H24: 0.038 | I24: 0.03 | J24: 0.024 | K24: 0.019 | L24: 0.016 | M24: 0.014 | N24: 0.012 | O24: 0.011 | P24: 0.01 | Q24: 0.009
A25: CAPEX & BALANCE SHEET
A26: Capex (₹ Cr) | D26: 4 | E26: 3.1 | F26: 5.5 | G26: 23 | H26: 55 | I26: 45 | J26: 35 | K26: 30 | L26: 28 | M26: 30 | N26: 32 | O26: 35 | P26: 38 | Q26: 40 | R26: FY26-27 elevated for 1GW solar plant (₹100Cr); normalises after
A27: Capex as % of Revenue | D27: =D26/D6 -> 0.09478673 | E27: =E26/E6 -> 0.024740623 | F27: =F26/F6 -> 0.031865585 | G27: =G26/G6 -> 0.072715776 | H27: =H26/H6 -> 0.11578947 | I27: =I26/I6 -> 0.067669173 | J27: =J26/J6 -> 0.037634409 | K27: =K26/K6 -> 0.023904382 | ... Q27: =Q26/Q6 -> 0.010471204 | R27: Asset-light EPC model post solar plant commissioning
A29: WACC COMPONENTS (CAPM-DERIVED)
A30: Risk-Free Rate (10Y GOI Bond) | D30: 0.067 | E30: India 10Y G-Sec yield ~7.2%
A31: Equity Risk Premium (India) | D31: 0.07 | E31: Damodaran India ERP ~6.5%
A32: Beta (Levered) — est. for micro-cap | D32: 1.4 | E32: No listed beta; est. using peer avg + size premium
A33: Size Premium (Micro-cap) | D33: 0.03 | E33: Additional 3% for sub-₹500Cr market cap
A34: Cost of Equity = Rf + β×ERP + Size | D34: =D30+D32*D31+D33 -> 0.195 | E34: 7.2% + 1.4×6.5% + 3% = 19.3%
A35: Pre-tax Cost of Debt | D35: 0.105 | E35: Avg borrowing rate per financials
A36: Tax Rate | D36: 0.252 | E36: 25.17% new regime
A37: After-tax Cost of Debt | D37: =D35*(1-D36) -> 0.07854 | E37: 10.5% × (1 - 25.17%) = 7.86%
A38: Equity Weight (Book Value) | D38: ='Balance Sheet'!F24/('Balance Sheet'!F24+'Balance Sheet'!F28+'Balance Sheet'!F33) -> 0.68557758 | E38: FY25A: SH Equity / (SH Equity + Total Debt)
A39: Debt Weight (Book Value) | D39: =('Balance Sheet'!F28+'Balance Sheet'!F33)/('Balance Sheet'!F24+'Balance Sheet'!F28+'Balance Sheet'!F33) -> 0.31442242 | E39: FY25A: Total Debt / (SH Equity + Total Debt)
A40: WACC | D40: =D38*D34+D39*D37 -> 0.15838237 | E40: 0.85×19.3% + 0.15×7.86% = 17.6%
A41: Terminal Growth Rate | D41: 0.055 | E41: India nominal GDP growth ~5%
A43: SCENARIO ANALYSIS — REVENUE PATHS (₹ Cr)
A44: Bull Case Revenue | D44: 42.2 | E44: 125.3 | F44: 172.6 | G44: 316.3 | H44: 500 | I44: 725 | J44: 1050 | K44: 1470 | L44: 1960 | M44: 2500 | N44: 3050 | O44: 3600 | P44: 4150 | Q44: 4700 | R44: Mgmt delivers ₹5000Cr by FY30 at ~90% hit rate
A45: Base Case Revenue | D45: 42.2 | E45: 125.3 | F45: 172.6 | G45: 316.3 | H45: 475 | I45: 665 | J45: 930 | K45: 1255 | L45: 1630 | M45: 2040 | N45: 2450 | O45: 2890 | P45: 3350 | Q45: 3820 | R45: 15-20% haircut on mgmt guidance; primary scenario
A46: Bear Case Revenue | D46: 42.2 | E46: 125.3 | F46: 172.6 | G46: 316.3 | H46: 440 | I46: 575 | J46: 735 | K46: 920 | L46: 1105 | M46: 1290 | N46: 1470 | O46: 1640 | P46: 1810 | Q46: 1975 | R46: Execution delays, solar plant slippage, margin compression

Sheet Mgmt Tracker
A1: RMC SWITCHGEARS — MANAGEMENT GUIDANCE TRACKER
A3: Guidance / Statement | B3: Source / Period | C3: Target | D3: Actual / Status | E3: Verdict | F3: Confidence Score | G3: Notes
A4: Revenue to reach ₹125 Cr | B4: CRISIL Report FY23 | C4: ₹125 Cr by FY23 | D4: ₹125.3 Cr achieved | E4: ✓ DELIVERED | F4: HIGH | G4: Hit target exactly; shows conservative guidance
A5: 30-40% revenue growth in FY24 | B5: CRISIL FY23 Assessment | C5: ₹163-175 Cr | D5: ₹172.6 Cr (38% growth) | E5: ✓ DELIVERED | F5: HIGH | G5: Mid-range delivery; consistent execution
A6: Order book ₹358 Cr as of Jun'23 | B6: CRISIL FY23 Report | C6: Healthy order visibility | D6: Grew to ₹572 Cr by Dec'25 | E6: ✓ OVER-DELIVERED | F6: HIGH | G6: 60% growth in order book over 2.5 years
A7: Revenue ₹3,000 Cr by FY30 | B7: Earlier investor meets | C7: ₹3,000 Cr target | D7: UPGRADED to ₹5,000 Cr | E7: ⬆ UPGRADED | F7: MEDIUM | G7: Ambitious upgrade after strong FY25 showing
A8: >30% CAGR over 3-5 years | B8: Q1 FY26 Concall / Inv Day | C8: Sustained 30%+ CAGR | D8: H1 FY26: 112% YoY rev growth | E8: ✓✓ OVER-DELIVERING | F8: HIGH | G8: Exceeding guidance significantly in near-term
A9: ₹2,300 Cr revenue by FY28 | B9: FY25 Mgmt Guidance | C9: ₹2,300 Cr | D9: In progress; FY26E tracking ₹475Cr | E9: ⏳ IN PROGRESS | F9: MEDIUM | G9: Needs ~70% CAGR from FY26; aggressive but order book supports
A10: ₹5,000 Cr turnover by 2030 | B10: Q1 FY26 Concall / Vision | C10: ₹5,000 Cr | D10: In progress | E10: ⏳ IN PROGRESS | F10: LOW-MED | G10: Very ambitious; 10x from FY25 in 5 yrs; execution is key
A11: EBITDA margins 18-20% | B11: CRISIL upside trigger | C11: 18-20% EBITDA margin | D11: FY25: 16.6%; H1 FY26: 15.3% | E11: ⚠ BELOW TARGET | F11: MEDIUM | G11: EPC transition compressed margins; mgmt says strategic
A12: Capacity utilisation >90% | B12: H1 FY26 PR | C12: Beyond 90% utilisation | D12: In progress for H2 FY26 | E12: ⏳ IN PROGRESS | F12: MEDIUM | G12: Being pushed as a key priority for FY27
A13: 1 GW Solar Module Plant | B13: FY24-25 announcements | C13: Operational by Q4 FY25 | D13: Delayed; phases adjusted | E13: ⚠ DELAYED | F13: LOW-MED | G13: SIDBI funding secured; design refinements cited
A14: Cash conversion cycle ~60 days | B14: H1 FY26 CEO statement | C14: 60 days CCC | D14: Achievable per mgmt | E14: ✓ TRACKING | F14: HIGH | G14: Good WC discipline despite rapid scaling
... A16: Forbes Asia Best Under Billion 2025 | B16: H1 FY26 press release | C16: Recognition | D16: Achieved | E16: ✓ ACHIEVED | F16: HIGH | G16: Validates governance & growth credentials
A18: OVERALL ASSESSMENT | B18: Management has a MODERATE-STRONG track record. Delivered on near-term targets consistently. Ambitious long-term vision (₹5000Cr by FY30) needs significant execution. Solar plant delay is a concern. Revenue delivery on track but margins under pressure from EPC transition.

Sheet Income Statement
A1: RMC SWITCHGEARS LTD — INCOME STATEMENT (Consolidated, ₹ Cr)
C3: FY22A | D3: FY23A | E3: FY24A | F3: FY25A | G3: FY26E | H3: FY27E | I3: FY28E | J3: FY29E | K3: FY30E | L3: FY31E | M3: FY32E | N3: FY33E | O3: FY34E | P3: FY35E
A5: Revenue from Operations | C5: 42.2 | D5: 125.3 | E5: 172.6 | F5: 316.3 | G5: =Assumptions!H6 -> 475 | H5: =Assumptions!I6 -> 665 | I5: =Assumptions!J6 -> 930 | J5: =Assumptions!K6 -> 1255 | K5: =Assumptions!L6 -> 1630 | L5: =Assumptions!M6 -> 2040 | M5: =Assumptions!N6 -> 2450 | N5: =Assumptions!O6 -> 2890 | ... P5: =Assumptions!Q6 -> 3820
A6: Other Income | C6: 0.7 | D6: 0.5 | E6: 0.8 | F6: 2.7 | G6: =G5*0.005 -> 2.375 | H6: =H5*0.005 -> 3.325 | I6: =I5*0.005 -> 4.65 | J6: =J5*0.005 -> 6.275 | K6: =K5*0.005 -> 8.15 | L6: =L5*0.005 -> 10.2 | M6: =M5*0.005 -> 12.25 | N6: =N5*0.005 -> 14.45 | ... P6: =P5*0.005 -> 19.1
A7: Total Income | C7: =C5+C6 -> 42.9 | D7: =D5+D6 -> 125.8 | E7: =E5+E6 -> 173.4 | F7: =F5+F6 -> 319 | G7: =G5+G6 -> 477.375 | H7: =H5+H6 -> 668.325 | I7: =I5+I6 -> 934.65 | J7: =J5+J6 -> 1261.275 | ... P7: =P5+P6 -> 3839.1
A9: EXPENSES
A10: Cost of Materials / COGS | C10: 36.7 | D10: 99.2 | E10: 95.4 | F10: 222.4 | G10: =G5*Assumptions!H10 -> 342 | H10: =H5*Assumptions!I10 -> 472.15 | I10: =I5*Assumptions!J10 -> 651 | J10: =J5*Assumptions!K10 -> 872.225 | K10: =K5*Assumptions!L10 -> 1124.7 | L10: =L5*Assumptions!M10 -> 1403.52 | M10: =M5*Assumptions!N10 -> 1678.25 | N10: =N5*Assumptions!O10 -> 1973.87 | ... P10: =P5*Assumptions!Q10 -> 2589.96
A11: Employee Benefit Expenses | C11: 2.5 | D11: 5.5 | E11: 10 | F11: 14.9 | G11: =G5*Assumptions!H12 -> 23.75 | H11: =H5*Assumptions!I12 -> 31.92 | I11: =I5*Assumptions!J12 -> 41.85 | J11: =J5*Assumptions!K12 -> 53.965 | K11: =K5*Assumptions!L12 -> 66.83 | L11: =L5*Assumptions!M12 -> 81.6 | M11: =M5*Assumptions!N12 -> 95.55 | N11: =N5*Assumptions!O12 -> 109.82 | ... P11: =P5*Assumptions!Q12 -> 137.52
A12: Other Expenses | C12: 2.4 | D12: 7.4 | E12: 13.6 | F12: 20.2 | G12: =G5*Assumptions!H13 -> 33.25 | H12: =H5*Assumptions!I13 -> 45.22 | I12: =I5*Assumptions!J13 -> 60.45 | J12: =J5*Assumptions!K13 -> 79.065 | K12: =K5*Assumptions!L13 -> 97.8 | L12: =L5*Assumptions!M13 -> 118.32 | M12: =M5*Assumptions!N13 -> 137.2 | N12: =N5*Assumptions!O13 -> 158.95 | ... P12: =P5*Assumptions!Q13 -> 202.46
A13: Total Expenses | C13: =C10+C11+C12 -> 41.6 | D13: =D10+D11+D12 -> 112.1 | E13: =E10+E11+E12 -> 119 | F13: =F10+F11+F12 -> 257.5 | G13: =G10+G11+G12 -> 399 | H13: =H10+H11+H12 -> 549.29 | I13: =I10+I11+I12 -> 753.3 | J13: =J10+J11+J12 -> 1005.255 | ... P13: =P10+P11+P12 -> 2929.94
A15: EBITDA | C15: =C7-C13 -> 1.3 | D15: =D7-D13 -> 13.7 | E15: =E7-E13 -> 54.4 | F15: =F7-F13 -> 61.5 | G15: =G7-G13 -> 78.375 | H15: =H7-H13 -> 119.035 | I15: =I7-I13 -> 181.35 | J15: =J7-J13 -> 256.02 | ... P15: =P7-P13 -> 909.16
A16: EBITDA Margin (%) — incl. Other Income | C16: =C15/C5 -> 0.030805687 | D16: =D15/D5 -> 0.10933759 | E16: =E15/E5 -> 0.31517961 | F16: =F15/F5 -> 0.19443566 | G16: =G15/G5 -> 0.165 | H16: =H15/H5 -> 0.179 | I16: =I15/I5 -> 0.195 | J16: =J15/J5 -> 0.204 | ... P16: =P15/P5 -> 0.238
A18: Depreciation & Amortisation | C18: 1.1 | D18: 1.1 | E18: 2.8 | F18: 4.1 | G18: =G5*Assumptions!H15 -> 8.55 | H18: =H5*Assumptions!I15 -> 13.3 | I18: =I5*Assumptions!J15 -> 20.46 | J18: =J5*Assumptions!K15 -> 27.61 | K18: =K5*Assumptions!L15 -> 34.23 | L18: =L5*Assumptions!M15 -> 40.8 | M18: =M5*Assumptions!N15 -> 46.55 | N18: =N5*Assumptions!O15 -> 52.02 | ... P18: =P5*Assumptions!Q15 -> 64.94
A19: EBIT | C19: =C15-C18 -> 0.2 | D19: =D15-D18 -> 12.6 | E19: =E15-E18 -> 51.6 | F19: =F15-F18 -> 57.4 | G19: =G15-G18 -> 69.825 | H19: =H15-H18 -> 105.735 | I19: =I15-I18 -> 160.89 | J19: =J15-J18 -> 228.41 | ... P19: =P15-P18 -> 844.22
A20: Finance Costs | C20: 1.5 | D20: 3.4 | E20: 8.2 | F20: 10.5 | G20: =(('Balance Sheet'!F28+'Balance Sheet'!F33+'Balance Sheet'!G28+'Balance Sheet'!G33)/2)*Assumptions!H16 -> 5.8275 | H20: =(('Balance Sheet'!G28+'Balance Sheet'!G33+'Balance Sheet'!H28+'Balance Sheet'!H33)/2)*Assumptions!I16 -> 6.65 | I20: =(('Balance Sheet'!H28+'Balance Sheet'!H33+'Balance Sheet'!I28+'Balance Sheet'!I33)/2)*Assumptions!J16 -> 6.2225 | J20: =(('Balance Sheet'!I28+'Balance Sheet'!I33+'Balance Sheet'!J28+'Balance Sheet'!J33)/2)*Assumptions!K16 -> 5.7 | K20: =(('Balance Sheet'!J28+'Balance Sheet'!J33+'Balance Sheet'!K28+'Balance Sheet'!K33)/2)*Assumptions!L16 -> 4.815 | L20: =(('Balance Sheet'!K28+'Balance Sheet'!K33+'Balance Sheet'!L28+'Balance Sheet'!L33)/2)*Assumptions!M16 -> 4.185 | M20: =(('Balance Sheet'!L28+'Balance Sheet'!L33+'Balance Sheet'!M28+'Balance Sheet'!M33)/2)*Assumptions!N16 -> 3.564 | N20: =(('Balance Sheet'!M28+'Balance Sheet'!M33+'Balance Sheet'!N28+'Balance Sheet'!N33)/2)*Assumptions!O16 -> 3.168 | ... P20: =(('Balance Sheet'!O28+'Balance Sheet'!O33+'Balance Sheet'!P28+'Balance Sheet'!P33)/2)*Assumptions!Q16 -> 2.295
A21: Profit Before Tax (PBT) | C21: =C19-C20 -> -1.3 | D21: =D19-D20 -> 9.2 | E21: =E19-E20 -> 43.4 | F21: =F19-F20 -> 46.9 | G21: =G19-G20 -> 63.9975 | H21: =H19-H20 -> 99.085 | I21: =I19-I20 -> 154.6675 | J21: =J19-J20 -> 222.71 | ... P21: =P19-P20 -> 841.925
A22: PBT Margin (%) | C22: =C21/C5 -> -0.030805687 | D22: =D21/D5 -> 0.073423783 | E22: =E21/E5 -> 0.25144844 | F22: =F21/F5 -> 0.14827695 | G22: =G21/G5 -> 0.13473158 | H22: =H21/H5 -> 0.149 | I22: =I21/I5 -> 0.16630914 | J22: =J21/J5 -> 0.17745817 | ... P22: =P21/P5 -> 0.22039921
A23: Tax Expense | C23: 0.1 | D23: 4.4 | E23: 5.4 | F23: 10.3 | G23: =G21*Assumptions!H17 -> 16.12737 | H23: =H21*Assumptions!I17 -> 24.96942 | I23: =I21*Assumptions!J17 -> 38.97621 | J23: =J21*Assumptions!K17 -> 56.12292 | K23: =K21*Assumptions!L17 -> 78.0633 | L23: =L21*Assumptions!M17 -> 101.2473 | M23: =M21*Assumptions!N17 -> 126.28627 | N23: =N21*Assumptions!O17 -> 152.86874 | ... P23: =P21*Assumptions!Q17 -> 212.1651
A24: Profit After Tax (PAT) | C24: =C21-C23 -> -1.4 | D24: =D21-D23 -> 4.8 | E24: =E21-E23 -> 38 | F24: =F21-F23 -> 36.6 | G24: =G21-G23 -> 47.87013 | H24: =H21-H23 -> 74.11558 | I24: =I21-I23 -> 115.69129 | J24: =J21-J23 -> 166.58708 | ... P24: =P21-P23 -> 629.7599
A25: PAT Margin (%) | C25: =C24/C5 -> -0.033175355 | D25: =D24/D5 -> 0.038308061 | E25: =E24/E5 -> 0.22016222 | F25: =F24/F5 -> 0.11571293 | G25: =G24/G5 -> 0.10077922 | H25: =H24/H5 -> 0.111452 | I25: =I24/I5 -> 0.12439924 | J25: =J24/J5 -> 0.13273871 | ... P25: =P24/P5 -> 0.16485861
A26: Minority Interest | C26: 0 | D26: 0 | E26: 0.04 | F26: 0.57 | G26: =G24*0.02 -> 0.9574026 | H26: =H24*0.02 -> 1.4823116 | I26: =I24*0.02 -> 2.3138258 | J26: =J24*0.02 -> 3.3317416 | K26: =K24*0.02 -> 4.634234 | L26: =L24*0.02 -> 6.010554 | M26: =M24*0.02 -> 7.4969946 | N26: =N24*0.02 -> 9.0750651 | ... P26: =P24*0.02 -> 12.595198
A27: PAT attributable to shareholders | C27: =C24-C26 -> -1.4 | D27: =D24-D26 -> 4.8 | E27: =E24-E26 -> 37.96 | F27: =F24-F26 -> 36.03 | G27: =G24-G26 -> 46.912727 | H27: =H24-H26 -> 72.633268 | I27: =I24-I26 -> 113.37746 | J27: =J24-J26 -> 163.25534 | ... P27: =P24-P26 -> 617.1647
A29: Shares Outstanding (Cr) | C29: 1.03 | D29: 1.03 | E29: 1.03 | F29: 1.06 | G29: 1.06 | H29: 1.06 | I29: 1.06 | J29: 1.06 | K29: 1.06 | L29: 1.06 | M29: 1.06 | N29: 1.06 | O29: 1.06 | P29: 1.06
A30: EPS (₹) | C30: =C27/C29 -> -1.3592233 | D30: =D27/D29 -> 4.6601942 | E30: =E27/E29 -> 36.854369 | F30: =F27/F29 -> 33.990566 | G30: =G27/G29 -> 44.25729 | H30: =H27/H29 -> 68.521951 | I30: =I27/I29 -> 106.95987 | J30: =J27/J29 -> 154.01447 | ... P30: =P27/P29 -> 582.23085

Sheet Balance Sheet
A1: RMC SWITCHGEARS LTD — BALANCE SHEET (Consolidated, ₹ Cr)
C3: FY22A | D3: FY23A | E3: FY24A | F3: FY25A | G3: FY26E | H3: FY27E | I3: FY28E | J3: FY29E | K3: FY30E | L3: FY31E | M3: FY32E | N3: FY33E | O3: FY34E | P3: FY35E
A5: ASSETS
A6: Non-Current Assets
A7: Property, Plant & Equipment (Net) | C7: 18 | D7: 16 | E7: 20 | F7: 40 | G7: =F7+Assumptions!H26-'Income Statement'!G18 -> 86.45 | H7: =G7+Assumptions!I26-'Income Statement'!H18 -> 118.15 | I7: =H7+Assumptions!J26-'Income Statement'!I18 -> 132.69 | J7: =I7+Assumptions!K26-'Income Statement'!J18 -> 135.08 | K7: =J7+Assumptions!L26-'Income Statement'!K18 -> 128.85 | L7: =K7+Assumptions!M26-'Income Statement'!L18 -> 118.05 | M7: =L7+Assumptions!N26-'Income Statement'!M18 -> 103.5 | N7: =M7+Assumptions!O26-'Income Statement'!N18 -> 86.48 | ... P7: =O7+Assumptions!Q26-'Income Statement'!P18 -> 39.24
A8: Other Non-Current Assets | C8: 5 | D8: 6 | E8: 10 | F8: 15 | G8: =F8+3 -> 18 | H8: =G8+2 -> 20 | I8: =H8+2 -> 22 | J8: =I8+3 -> 25 | K8: =J8+3 -> 28 | L8: =K8+2 -> 30 | M8: =L8+3 -> 33 | N8: =M8+3 -> 36 | O8: =N8+3 -> 39 | P8: =O8+3 -> 42
A9: Total Non-Current Assets | C9: =C7+C8 -> 23 | D9: =D7+D8 -> 22 | E9: =E7+E8 -> 30 | F9: =F7+F8 -> 55 | G9: =G7+G8 -> 104.45 | H9: =H7+H8 -> 138.15 | I9: =I7+I8 -> 154.69 | J9: =J7+J8 -> 160.08 | ... P9: =P7+P8 -> 81.24
A11: Current Assets
A12: Inventories | C12: 2.8 | D12: 9 | E12: 9.2 | F12: 18.3 | G12: ='Income Statement'!G5*Assumptions!H21/365 -> 41.643836 | H12: ='Income Statement'!H5*Assumptions!I21/365 -> 54.657534 | I12: ='Income Statement'!I5*Assumptions!J21/365 -> 71.342466 | J12: ='Income Statement'!J5*Assumptions!K21/365 -> 92.835616 | K12: ='Income Statement'!K5*Assumptions!L21/365 -> 116.10959 | L12: ='Income Statement'!L5*Assumptions!M21/365 -> 139.72603 | M12: ='Income Statement'!M5*Assumptions!N21/365 -> 167.80822 | N12: ='Income Statement'!N5*Assumptions!O21/365 -> 190.0274 | ... P12: ='Income Statement'!P5*Assumptions!Q21/365 -> 240.71233
A13: Trade Receivables | C13: 24.3 | D13: 57.3 | E13: 87.5 | F13: 147.3 | G13: ='Income Statement'!G5*Assumptions!H20/365 -> 201.71233 | H13: ='Income Statement'!H5*Assumptions!I20/365 -> 255.06849 | I13: ='Income Statement'!I5*Assumptions!J20/365 -> 331.23288 | J13: ='Income Statement'!J5*Assumptions!K20/365 -> 412.60274 | K13: ='Income Statement'!K5*Assumptions!L20/365 -> 513.56164 | L13: ='Income Statement'!L5*Assumptions!M20/365 -> 614.79452 | M13: ='Income Statement'!M5*Assumptions!N20/365 -> 704.79452 | N13: ='Income Statement'!N5*Assumptions!O20/365 -> 791.78082 | ... P13: ='Income Statement'!P5*Assumptions!Q20/365 -> 941.91781
A14: Cash & Equivalents | C14: 6 | D14: 10 | E14: 12 | F14: 15 | G14: =G24+G25+G30+G33+G34+G35-G9-G12-G13-G15 -> 2.3154013 | H14: =H24+H25+H30+H33+H34+H35-H9-H12-H13-H15 -> 21.152428 | I14: =I24+I25+I30+I33+I34+I35-I9-I12-I13-I15 -> 76.56023 | J14: =J24+J25+J30+J33+J34+J35-J9-J12-J13-J15 -> 187.83658 | K14: =K24+K25+K30+K33+K34+K35-K9-K12-K13-K15 -> 364.98356 | L14: =L24+L25+L30+L33+L34+L35-L9-L12-L13-L15 -> 614.12598 | M14: =M24+M25+M30+M33+M34+M35-M9-M12-M13-M15 -> 945.88694 | N14: =N24+N25+N30+N33+N34+N35-N9-N12-N13-N15 -> 1364.6038 | ... P14: =P24+P25+P30+P33+P34+P35-P9-P12-P13-P15 -> 2488.2991
A15: Other Current Assets | C15: =C24+C25+C30+C36-C9-C12-C13-C14 -> 20.6 | D15: =D24+D25+D30+D36-D9-D12-D13-D14 -> 5.7 | E15: =E24+E25+E30+E36-E9-E12-E13-E14 -> 5.2 | F15: =F24+F25+F30+F36-F9-F12-F13-F14 -> 12 | G15: ='Income Statement'!G5*Assumptions!H23 -> 14.25 | H15: ='Income Statement'!H5*Assumptions!I23 -> 15.96 | I15: ='Income Statement'!I5*Assumptions!J23 -> 17.67 | J15: ='Income Statement'!J5*Assumptions!K23 -> 20.08 | K15: ='Income Statement'!K5*Assumptions!L23 -> 22.82 | L15: ='Income Statement'!L5*Assumptions!M23 -> 24.48 | M15: ='Income Statement'!M5*Assumptions!N23 -> 26.95 | N15: ='Income Statement'!N5*Assumptions!O23 -> 28.9 | ... P15: ='Income Statement'!P5*Assumptions!Q23 -> 30.56
A16: Total Current Assets | C16: =SUM(C12:C15) -> 53.7 | D16: =SUM(D12:D15) -> 82 | E16: =SUM(E12:E15) -> 113.9 | F16: =SUM(F12:F15) -> 192.6 | G16: =SUM(G12:G15) -> 259.92157 | H16: =SUM(H12:H15) -> 346.83846 | I16: =SUM(I12:I15) -> 496.80557 | J16: =SUM(J12:J15) -> 713.35493 | ... P16: =SUM(P12:P15) -> 3701.4892
A18: TOTAL ASSETS | C18: =C9+C16 -> 76.7 | D18: =D9+D16 -> 104 | E18: =E9+E16 -> 143.9 | F18: =F9+F16 -> 247.6 | G18: =G9+G16 -> 364.37157 | H18: =H9+H16 -> 484.98846 | I18: =I9+I16 -> 651.49557 | J18: =J9+J16 -> 873.43493 | ... P18: =P9+P16 -> 3782.7292
A20: EQUITY & LIABILITIES
A21: Shareholders' Equity
A22: Share Capital | C22: 5.2 | D22: 5.2 | E22: 5.2 | F22: 5.3 | G22: 5.3 | H22: 5.3 | I22: 5.3 | J22: 5.3 | K22: 5.3 | L22: 5.3 | M22: 5.3 | N22: 5.3 | O22: 5.3 | P22: 5.3
A23: Reserves & Surplus | C23: 22 | D23: 28 | E23: 55 | F23: 95 | G23: =F23+'Income Statement'!G24+'Cash Flow'!G23 -> 142.39143 | H23: =G23+'Income Statement'!H24+'Cash Flow'!H23 -> 215.76585 | I23: =H23+'Income Statement'!I24+'Cash Flow'!I23 -> 330.30023 | J23: =I23+'Income Statement'!J24+'Cash Flow'!J23 -> 495.22144 | K23: =J23+'Income Statement'!K24+'Cash Flow'!K23 -> 724.61602 | L23: =K23+'Income Statement'!L24+'Cash Flow'!L23 -> 1022.1384 | M23: =L23+'Income Statement'!M24+'Cash Flow'!M23 -> 1393.2397 | N23: =M23+'Income Statement'!N24+'Cash Flow'!N23 -> 1842.4554 | ... P23: =O23+'Income Statement'!P24+'Cash Flow'!P23 -> 2999.7752
A24: Total Equity | C24: =C22+C23 -> 27.2 | D24: =D22+D23 -> 33.2 | E24: =E22+E23 -> 60.2 | F24: =F22+F23 -> 100.3 | G24: =G22+G23 -> 147.69143 | H24: =H22+H23 -> 221.06585 | I24: =I22+I23 -> 335.60023 | J24: =J22+J23 -> 500.52144 | ... P24: =P22+P23 -> 3005.0752
A25: Minority Interest | C25: 0 | D25: 0 | E25: 0.5 | F25: 2 | G25: =F25+1 -> 3 | H25: =G25+1 -> 4 | I25: =H25+1 -> 5 | J25: =I25+2 -> 7 | K25: =J25+2 -> 9 | L25: =K25+2 -> 11 | M25: =L25+2 -> 13 | N25: =M25+3 -> 16 | O25: =N25+3 -> 19 | P25: =O25+3 -> 22
A27: Non-Current Liabilities
A28: Long-Term Borrowings | C28: 20 | D28: 19 | E28: 25 | F28: 30 | G28: 45 | H28: 50 | I28: 48 | J28: 45 | K28: 42 | L28: 38 | M28: 35 | N28: 32 | O28: 28 | P28: 25
A29: Other NC Liabilities | C29: 3 | D29: 4 | E29: 5 | F29: 6 | G29: =F29+1 -> 7 | H29: =G29+1 -> 8 | I29: =H29+1 -> 9 | J29: =I29+1 -> 10 | K29: =J29+1 -> 11 | L29: =K29+1 -> 12 | M29: =L29+1 -> 13 | N29: =M29+1 -> 14 | ... P29: =O29+1 -> 16
A30: Total Non-Current Liabilities | C30: =C28+C29 -> 23 | D30: =D28+D29 -> 23 | E30: =E28+E29 -> 30 | F30: =F28+F29 -> 36 | G30: =G28+G29 -> 52 | H30: =H28+H29 -> 58 | I30: =I28+I29 -> 57 | J30: =J28+J29 -> 55 | ... P30: =P28+P29 -> 41
A32: Current Liabilities
A33: Short-Term Borrowings | C33: 10 | D33: 12 | E33: 15 | F33: 16 | G33: 20 | H33: 18 | I33: 15 | J33: 12 | K33: 8 | L33: 5 | M33: 3 | N33: 2 | O33: 1 | P33: 0
A34: Trade Payables | C34: 8.5 | D34: 25.8 | E34: 26.2 | F34: 54.8 | G34: ='Income Statement'!G5*Assumptions!H22/365 -> 123.63014 | H34: ='Income Statement'!H5*Assumptions!I22/365 -> 163.9726 | I34: ='Income Statement'!I5*Assumptions!J22/365 -> 216.57534 | J34: ='Income Statement'!J5*Assumptions!K22/365 -> 275.06849 | K34: ='Income Statement'!K5*Assumptions!L22/365 -> 348.32877 | L34: ='Income Statement'!L5*Assumptions!M22/365 -> 419.17808 | M34: ='Income Statement'!M5*Assumptions!N22/365 -> 490 | N34: ='Income Statement'!N5*Assumptions!O22/365 -> 554.24658 | ... P34: ='Income Statement'!P5*Assumptions!Q22/365 -> 680.27397
A35: Other Current Liabilities | C35: 8 | D35: 10 | E35: 12 | F35: 38.5 | G35: ='Income Statement'!G5*Assumptions!H24 -> 18.05 | H35: ='Income Statement'!H5*Assumptions!I24 -> 19.95 | I35: ='Income Statement'!I5*Assumptions!J24 -> 22.32 | J35: ='Income Statement'!J5*Assumptions!K24 -> 23.845 | K35: ='Income Statement'!K5*Assumptions!L24 -> 26.08 | L35: ='Income Statement'!L5*Assumptions!M24 -> 28.56 | M35: ='Income Statement'!M5*Assumptions!N24 -> 29.4 | N35: ='Income Statement'!N5*Assumptions!O24 -> 31.79 | ... P35: ='Income Statement'!P5*Assumptions!Q24 -> 34.38
A36: Total Current Liabilities | C36: =C33+C34+C35 -> 26.5 | D36: =D33+D34+D35 -> 47.8 | E36: =E33+E34+E35 -> 53.2 | F36: =F33+F34+F35 -> 109.3 | G36: =G33+G34+G35 -> 161.68014 | H36: =H33+H34+H35 -> 201.9226 | I36: =I33+I34+I35 -> 253.89534 | J36: =J33+J34+J35 -> 310.91349 | ... P36: =P33+P34+P35 -> 714.65397
A38: TOTAL EQUITY & LIABILITIES | C38: =C24+C25+C30+C36 -> 76.7 | D38: =D24+D25+D30+D36 -> 104 | E38: =E24+E25+E30+E36 -> 143.9 | F38: =F24+F25+F30+F36 -> 247.6 | G38: =G24+G25+G30+G36 -> 364.37157 | H38: =H24+H25+H30+H36 -> 484.98846 | I38: =I24+I25+I30+I36 -> 651.49557 | J38: =J24+J25+J30+J36 -> 873.43493 | ... P38: =P24+P25+P30+P36 -> 3782.7292

Sheet Cash Flow
A1: RMC SWITCHGEARS LTD — CASH FLOW STATEMENT (Consolidated, ₹ Cr)
C3: FY22A | D3: FY23A | E3: FY24A | F3: FY25A | G3: FY26E | H3: FY27E | I3: FY28E | J3: FY29E | K3: FY30E | L3: FY31E | M3: FY32E | N3: FY33E | O3: FY34E | P3: FY35E
A5: CASH FLOW FROM OPERATIONS
A6: Profit Before Tax | C6: -0.8 | D6: 13.2 | E6: 26.3 | F6: 47.2 | G6: ='Income Statement'!G21 -> 63.9975 | H6: ='Income Statement'!H21 -> 99.085 | I6: ='Income Statement'!I21 -> 154.6675 | J6: ='Income Statement'!J21 -> 222.71 | K6: ='Income Statement'!K21 -> 309.775 | L6: ='Income Statement'!L21 -> 401.775 | M6: ='Income Statement'!M21 -> 501.136 | N6: ='Income Statement'!N21 -> 606.622 | ... P6: ='Income Statement'!P21 -> 841.925
A7: (+) Depreciation | C7: 1.1 | D7: 1.1 | E7: 2.8 | F7: 4.1 | G7: ='Income Statement'!G18 -> 8.55 | H7: ='Income Statement'!H18 -> 13.3 | I7: ='Income Statement'!I18 -> 20.46 | J7: ='Income Statement'!J18 -> 27.61 | K7: ='Income Statement'!K18 -> 34.23 | L7: ='Income Statement'!L18 -> 40.8 | M7: ='Income Statement'!M18 -> 46.55 | N7: ='Income Statement'!N18 -> 52.02 | ... P7: ='Income Statement'!P18 -> 64.94
A8: (+) Finance Costs | C8: 1.5 | D8: 3.4 | E8: 8.2 | F8: 10.5 | G8: ='Income Statement'!G20 -> 5.8275 | H8: ='Income Statement'!H20 -> 6.65 | I8: ='Income Statement'!I20 -> 6.2225 | J8: ='Income Statement'!J20 -> 5.7 | K8: ='Income Statement'!K20 -> 4.815 | L8: ='Income Statement'!L20 -> 4.185 | M8: ='Income Statement'!M20 -> 3.564 | N8: ='Income Statement'!N20 -> 3.168 | ... P8: ='Income Statement'!P20 -> 2.295
A9: (-) Working Capital Changes | C9: -5 | D9: -10 | E9: -20 | F9: -15 | G9: =-(('Balance Sheet'!G13+'Balance Sheet'!G12-'Balance Sheet'!G34)-('Balance Sheet'!F13+'Balance Sheet'!F12-'Balance Sheet'!F34)) -> -8.9260274 | H9: =-(('Balance Sheet'!H13+'Balance Sheet'!H12-'Balance Sheet'!H34)-('Balance Sheet'!G13+'Balance Sheet'!G12-'Balance Sheet'!G34)) -> -26.027397 | I9: =-(('Balance Sheet'!I13+'Balance Sheet'!I12-'Balance Sheet'!I34)-('Balance Sheet'!H13+'Balance Sheet'!H12-'Balance Sheet'!H34)) -> -40.246575 | J9: =-(('Balance Sheet'!J13+'Balance Sheet'!J12-'Balance Sheet'!J34)-('Balance Sheet'!I13+'Balance Sheet'!I12-'Balance Sheet'!I34)) -> -44.369863 | K9: =-(('Balance Sheet'!K13+'Balance Sheet'!K12-'Balance Sheet'!K34)-('Balance Sheet'!J13+'Balance Sheet'!J12-'Balance Sheet'!J34)) -> -50.972603 | L9: =-(('Balance Sheet'!L13+'Balance Sheet'!L12-'Balance Sheet'!L34)-('Balance Sheet'!K13+'Balance Sheet'!K12-'Balance Sheet'!K34)) -> -54 | M9: =-(('Balance Sheet'!M13+'Balance Sheet'!M12-'Balance Sheet'!M34)-('Balance Sheet'!L13+'Balance Sheet'!L12-'Balance Sheet'!L34)) -> -47.260274 | N9: =-(('Balance Sheet'!N13+'Balance Sheet'!N12-'Balance Sheet'!N34)-('Balance Sheet'!M13+'Balance Sheet'!M12-'Balance Sheet'!M34)) -> -44.958904 | ... P9: =-(('Balance Sheet'!P13+'Balance Sheet'!P12-'Balance Sheet'!P34)-('Balance Sheet'!O13+'Balance Sheet'!O12-'Balance Sheet'!O34)) -> -34.273973
A10: (-) Tax Paid | C10: -0.1 | D10: -4.4 | E10: -5.4 | F10: -10.3 | G10: =-'Income Statement'!G23 -> -16.12737 | H10: =-'Income Statement'!H23 -> -24.96942 | I10: =-'Income Statement'!I23 -> -38.97621 | J10: =-'Income Statement'!J23 -> -56.12292 | K10: =-'Income Statement'!K23 -> -78.0633 | L10: =-'Income Statement'!L23 -> -101.2473 | M10: =-'Income Statement'!M23 -> -126.28627 | N10: =-'Income Statement'!N23 -> -152.86874 | ... P10: =-'Income Statement'!P23 -> -212.1651
A12: Net Cash from Operations (CFO) | C12: =C6+C7+C8+C9+C10 -> -3.3 | D12: =D6+D7+D8+D9+D10 -> 3.3 | E12: =E6+E7+E8+E9+E10 -> 11.9 | F12: =F6+F7+F8+F9+F10 -> 36.5 | G12: =G6+G7+G8+G9+G10 -> 53.321603 | H12: =H6+H7+H8+H9+H10 -> 68.038183 | I12: =I6+I7+I8+I9+I10 -> 102.12721 | J12: =J6+J7+J8+J9+J10 -> 155.52722 | ... P12: =P6+P7+P8+P9+P10 -> 662.72093
A14: CASH FLOW FROM INVESTING
A15: (-) Capital Expenditure | C15: -4 | D15: -3.1 | E15: -5.5 | F15: -23 | G15: =-Assumptions!H26 -> -55 | H15: =-Assumptions!I26 -> -45 | I15: =-Assumptions!J26 -> -35 | J15: =-Assumptions!K26 -> -30 | K15: =-Assumptions!L26 -> -28 | L15: =-Assumptions!M26 -> -30 | M15: =-Assumptions!N26 -> -32 | N15: =-Assumptions!O26 -> -35 | ... P15: =-Assumptions!Q26 -> -40
A16: (-) Investments / Others | C16: =C28-C12-C26-C15 -> 6.8 | D16: =D28-D12-D26-D15 -> 2.2 | E16: =E28-E12-E26-E15 -> -4 | F16: =F28-F12-F26-F15 -> -14.7 | G16: =G28-G12-G26-G15 -> -25.7 | H16: =H28-H12-H26-H15 -> 0.19 | I16: =I28-I12-I26-I15 -> 0.66 | J16: =J28-J12-J26-J15 -> -0.885 | ... P16: =P28-P12-P26-P15 -> 1.47
A18: Net Cash from Investing (CFI) | C18: =C15+C16 -> 2.8 | D18: =D15+D16 -> -0.9 | E18: =E15+E16 -> -9.5 | F18: =F15+F16 -> -37.7 | G18: =G15+G16 -> -80.7 | H18: =H15+H16 -> -44.81 | I18: =I15+I16 -> -34.34 | J18: =J15+J16 -> -30.885 | ... P18: =P15+P16 -> -38.53
A20: CASH FLOW FROM FINANCING
A21: Net Borrowings | C21: 2 | D21: 5 | E21: 8 | F21: 10 | G21: =('Balance Sheet'!G28+'Balance Sheet'!G33)-('Balance Sheet'!F28+'Balance Sheet'!F33) -> 19 | H21: =('Balance Sheet'!H28+'Balance Sheet'!H33)-('Balance Sheet'!G28+'Balance Sheet'!G33) -> 3 | I21: =('Balance Sheet'!I28+'Balance Sheet'!I33)-('Balance Sheet'!H28+'Balance Sheet'!H33) -> -5 | J21: =('Balance Sheet'!J28+'Balance Sheet'!J33)-('Balance Sheet'!I28+'Balance Sheet'!I33) -> -6 | K21: =('Balance Sheet'!K28+'Balance Sheet'!K33)-('Balance Sheet'!J28+'Balance Sheet'!J33) -> -7 | L21: =('Balance Sheet'!L28+'Balance Sheet'!L33)-('Balance Sheet'!K28+'Balance Sheet'!K33) -> -7 | M21: =('Balance Sheet'!M28+'Balance Sheet'!M33)-('Balance Sheet'!L28+'Balance Sheet'!L33) -> -5 | N21: =('Balance Sheet'!N28+'Balance Sheet'!N33)-('Balance Sheet'!M28+'Balance Sheet'!M33) -> -4 | ... P21: =('Balance Sheet'!P28+'Balance Sheet'!P33)-('Balance Sheet'!O28+'Balance Sheet'!O33) -> -4
A22: (-) Interest Paid | C22: -1.5 | D22: -3.4 | E22: -8.2 | F22: -10.5 | G22: =-'Income Statement'!G20 -> -5.8275 | H22: =-'Income Statement'!H20 -> -6.65 | I22: =-'Income Statement'!I20 -> -6.2225 | J22: =-'Income Statement'!J20 -> -5.7 | K22: =-'Income Statement'!K20 -> -4.815 | L22: =-'Income Statement'!L20 -> -4.185 | M22: =-'Income Statement'!M20 -> -3.564 | N22: =-'Income Statement'!N20 -> -3.168 | ... P22: =-'Income Statement'!P20 -> -2.295
A23: (-) Dividend | C23: 0 | D23: 0 | E23: -0.2 | F23: -0.3 | G23: =-'Income Statement'!G24*0.01 -> -0.4787013 | H23: =-'Income Statement'!H24*0.01 -> -0.7411558 | I23: =-'Income Statement'!I24*0.01 -> -1.1569129 | J23: =-'Income Statement'!J24*0.01 -> -1.6658708 | K23: =-'Income Statement'!K24*0.01 -> -2.317117 | L23: =-'Income Statement'!L24*0.01 -> -3.005277 | M23: =-'Income Statement'!M24*0.01 -> -3.7484973 | N23: =-'Income Statement'!N24*0.01 -> -4.5375326 | ... P23: =-'Income Statement'!P24*0.01 -> -6.297599
A24: Share Premium / Issue | C24: 0 | D24: 0 | E24: 0 | F24: 5 | G24: 2 | H24: 0 | I24: 0 | J24: 0 | K24: 0 | L24: 0 | M24: 0 | N24: 0 | O24: 0 | P24: 0
A26: Net Cash from Financing (CFF) | C26: =C21+C22+C23+C24 -> 0.5 | D26: =D21+D22+D23+D24 -> 1.6 | E26: =E21+E22+E23+E24 -> -0.4 | F26: =F21+F22+F23+F24 -> 4.2 | G26: =G21+G22+G23+G24 -> 14.693799 | H26: =H21+H22+H23+H24 -> -4.3911558 | I26: =I21+I22+I23+I24 -> -12.379413 | J26: =J21+J22+J23+J24 -> -13.365871 | ... P26: =P21+P22+P23+P24 -> -12.592599
A28: NET CHANGE IN CASH | C28: ='Balance Sheet'!C14-C29 -> 0 | D28: ='Balance Sheet'!D14-D29 -> 4 | E28: ='Balance Sheet'!E14-E29 -> 2 | F28: ='Balance Sheet'!F14-F29 -> 3 | G28: =G30-G29 -> -12.684599 | H28: =H30-H29 -> 18.837027 | I28: =I30-I29 -> 55.407802 | J28: =J30-J29 -> 111.27635 | K28: =K30-K29 -> 177.14698 | L28: =L30-L29 -> 249.14242 | M28: =M30-M29 -> 331.76096 | N28: =N30-N29 -> 418.71682 | ... P28: =P30-P29 -> 611.59833
A29: Opening Cash | C29: 6 | D29: ='Balance Sheet'!C14 -> 6 | E29: ='Balance Sheet'!D14 -> 10 | F29: ='Balance Sheet'!E14 -> 12 | G29: ='Balance Sheet'!F14 -> 15 | H29: ='Balance Sheet'!G14 -> 2.3154013 | I29: ='Balance Sheet'!H14 -> 21.152428 | J29: ='Balance Sheet'!I14 -> 76.56023 | K29: ='Balance Sheet'!J14 -> 187.83658 | ... P29: ='Balance Sheet'!O14 -> 1876.7007
A30: Closing Cash | C30: ='Balance Sheet'!C14 -> 6 | D30: ='Balance Sheet'!D14 -> 10 | E30: ='Balance Sheet'!E14 -> 12 | F30: ='Balance Sheet'!F14 -> 15 | G30: ='Balance Sheet'!G14 -> 2.3154013 | H30: ='Balance Sheet'!H14 -> 21.152428 | I30: ='Balance Sheet'!I14 -> 76.56023 | J30: ='Balance Sheet'!J14 -> 187.83658 | ... P30: ='Balance Sheet'!P14 -> 2488.2991

Sheet Schedules
A1: RMC SWITCHGEARS — SUPPORTING SCHEDULES
A3: SCHEDULE 1: DEBT SCHEDULE (₹ Cr)
B5: FY22A | C5: FY23A | D5: FY24A | E5: FY25A | F5: FY26E | G5: FY27E | H5: FY28E | I5: FY29E | J5: FY30E | K5: FY31E | L5: FY32E | M5: FY33E | N5: FY34E | O5: FY35E
A6: Long-Term Debt | B6: ='Balance Sheet'!C28 -> 20 | C6: ='Balance Sheet'!D28 -> 19 | D6: ='Balance Sheet'!E28 -> 25 | E6: ='Balance Sheet'!F28 -> 30 | F6: ='Balance Sheet'!G28 -> 45 | G6: ='Balance Sheet'!H28 -> 50 | H6: ='Balance Sheet'!I28 -> 48 | I6: ='Balance Sheet'!J28 -> 45 | ... O6: ='Balance Sheet'!P28 -> 25
A7: Short-Term Debt | B7: ='Balance Sheet'!C33 -> 10 | C7: ='Balance Sheet'!D33 -> 12 | D7: ='Balance Sheet'!E33 -> 15 | E7: ='Balance Sheet'!F33 -> 16 | F7: ='Balance Sheet'!G33 -> 20 | G7: ='Balance Sheet'!H33 -> 18 | H7: ='Balance Sheet'!I33 -> 15 | I7: ='Balance Sheet'!J33 -> 12 | ... O7: ='Balance Sheet'!P33 -> 0
A8: Total Debt | B8: =B6+B7 -> 30 | C8: =C6+C7 -> 31 | D8: =D6+D7 -> 40 | E8: =E6+E7 -> 46 | F8: =F6+F7 -> 65 | G8: =G6+G7 -> 68 | H8: =H6+H7 -> 63 | I8: =I6+I7 -> 57 | ... O8: =O6+O7 -> 25
A9: (-) Cash & Equivalents | B9: ='Balance Sheet'!C14 -> 6 | C9: ='Balance Sheet'!D14 -> 10 | D9: ='Balance Sheet'!E14 -> 12 | E9: ='Balance Sheet'!F14 -> 15 | F9: ='Balance Sheet'!G14 -> 2.3154013 | G9: ='Balance Sheet'!H14 -> 21.152428 | H9: ='Balance Sheet'!I14 -> 76.56023 | I9: ='Balance Sheet'!J14 -> 187.83658 | ... O9: ='Balance Sheet'!P14 -> 2488.2991
A10: Net Debt | B10: =B8-B9 -> 24 | C10: =C8-C9 -> 21 | D10: =D8-D9 -> 28 | E10: =E8-E9 -> 31 | F10: =F8-F9 -> 62.684599 | G10: =G8-G9 -> 46.847572 | H10: =H8-H9 -> -13.56023 | I10: =I8-I9 -> -130.83658 | ... O10: =O8-O9 -> -2463.2991
A11: Debt/Equity Ratio | B11: =B8/'Balance Sheet'!C24 -> 1.1029412 | C11: =C8/'Balance Sheet'!D24 -> 0.93373494 | D11: =D8/'Balance Sheet'!E24 -> 0.66445183 | E11: =E8/'Balance Sheet'!F24 -> 0.45862413 | F11: =F8/'Balance Sheet'!G24 -> 0.44010679 | G11: =G8/'Balance Sheet'!H24 -> 0.30760065 | H11: =H8/'Balance Sheet'!I24 -> 0.18772335 | I11: =I8/'Balance Sheet'!J24 -> 0.11388124 | ... O11: =O8/'Balance Sheet'!P24 -> 0.0083192593
A14: SCHEDULE 2: WORKING CAPITAL DAYS
B16: FY22A | C16: FY23A | D16: FY24A | E16: FY25A | F16: FY26E | G16: FY27E | H16: FY28E | I16: FY29E | J16: FY30E | K16: FY31E | L16: FY32E | M16: FY33E | N16: FY34E | O16: FY35E
A17: Receivable Days | B17: =Assumptions!D20 -> 210 | C17: =Assumptions!E20 -> 167 | D17: =Assumptions!F20 -> 185 | E17: =Assumptions!G20 -> 170 | F17: =Assumptions!H20 -> 155 | G17: =Assumptions!I20 -> 140 | H17: =Assumptions!J20 -> 130 | I17: =Assumptions!K20 -> 120 | ... O17: =Assumptions!Q20 -> 90
A18: Inventory Days | B18: =Assumptions!D21 -> 28 | C18: =Assumptions!E21 -> 33 | D18: =Assumptions!F21 -> 35 | E18: =Assumptions!G21 -> 30 | F18: =Assumptions!H21 -> 32 | G18: =Assumptions!I21 -> 30 | H18: =Assumptions!J21 -> 28 | I18: =Assumptions!K21 -> 27 | ... O18: =Assumptions!Q21 -> 23
A19: Payable Days | B19: =Assumptions!D22 -> 85 | C19: =Assumptions!E22 -> 95 | D19: =Assumptions!F22 -> 100 | E19: =Assumptions!G22 -> 90 | F19: =Assumptions!H22 -> 95 | G19: =Assumptions!I22 -> 90 | H19: =Assumptions!J22 -> 85 | I19: =Assumptions!K22 -> 80 | ... O19: =Assumptions!Q22 -> 65
A20: Cash Conversion Cycle | B20: =B17+B18-B19 -> 153 | C20: =C17+C18-C19 -> 105 | D20: =D17+D18-D19 -> 120 | E20: =E17+E18-E19 -> 110 | F20: =F17+F18-F19 -> 92 | G20: =G17+G18-G19 -> 80 | H20: =H17+H18-H19 -> 73 | I20: =I17+I18-I19 -> 67 | ... O20: =O17+O18-O19 -> 48
A21: Working Capital as % Rev | B21: =('Balance Sheet'!C13+'Balance Sheet'!C12-'Balance Sheet'!C34)/'Income Statement'!C5 -> 0.44075829 | C21: =('Balance Sheet'!D13+'Balance Sheet'!D12-'Balance Sheet'!D34)/'Income Statement'!D5 -> 0.32322426 | D21: =('Balance Sheet'!E13+'Balance Sheet'!E12-'Balance Sheet'!E34)/'Income Statement'!E5 -> 0.40845886 | E21: =('Balance Sheet'!F13+'Balance Sheet'!F12-'Balance Sheet'!F34)/'Income Statement'!F5 -> 0.35030035 | F21: =('Balance Sheet'!G13+'Balance Sheet'!G12-'Balance Sheet'!G34)/'Income Statement'!G5 -> 0.25205479 | G21: =('Balance Sheet'!H13+'Balance Sheet'!H12-'Balance Sheet'!H34)/'Income Statement'!H5 -> 0.21917808 | H21: =('Balance Sheet'!I13+'Balance Sheet'!I12-'Balance Sheet'!I34)/'Income Statement'!I5 -> 0.2 | I21: =('Balance Sheet'!J13+'Balance Sheet'!J12-'Balance Sheet'!J34)/'Income Statement'!J5 -> 0.18356164 | ... O21: =('Balance Sheet'!P13+'Balance Sheet'!P12-'Balance Sheet'!P34)/'Income Statement'!P5 -> 0.13150685
A24: SCHEDULE 3: KEY RETURN RATIOS
B26: FY22A | C26: FY23A | D26: FY24A | E26: FY25A | F26: FY26E | G26: FY27E | H26: FY28E | I26: FY29E | J26: FY30E | K26: FY31E | L26: FY32E | M26: FY33E | N26: FY34E | O26: FY35E
A27: ROE (%) | B27: ='Income Statement'!C24/(('Balance Sheet'!C24)) -> -0.051470588 | C27: ='Income Statement'!D24/(('Balance Sheet'!C24+'Balance Sheet'!D24)/2) -> 0.1589404 | D27: ='Income Statement'!E24/(('Balance Sheet'!D24+'Balance Sheet'!E24)/2) -> 0.8137045 | E27: ='Income Statement'!F24/(('Balance Sheet'!E24+'Balance Sheet'!F24)/2) -> 0.45607477 | F27: ='Income Statement'!G24/(('Balance Sheet'!F24+'Balance Sheet'!G24)/2) -> 0.38606278 | G27: ='Income Statement'!H24/(('Balance Sheet'!G24+'Balance Sheet'!H24)/2) -> 0.40197487 | H27: ='Income Statement'!I24/(('Balance Sheet'!H24+'Balance Sheet'!I24)/2) -> 0.41565777 | I27: ='Income Statement'!J24/(('Balance Sheet'!I24+'Balance Sheet'!J24)/2) -> 0.39847569 | J27: ='Income Statement'!K24/(('Balance Sheet'!J24+'Balance Sheet'!K24)/2) -> 0.37663304 | ... O27: ='Income Statement'!P24/(('Balance Sheet'!O24+'Balance Sheet'!P24)/2) -> 0.23382081
A28: ROCE (%) | B28: ='Income Statement'!C19/('Balance Sheet'!C24+'Balance Sheet'!C28+'Balance Sheet'!C33-'Balance Sheet'!C14) -> 0.00390625 | C28: ='Income Statement'!D19/(('Balance Sheet'!C24+'Balance Sheet'!C28+'Balance Sheet'!C33-'Balance Sheet'!C14+'Balance Sheet'!D24+'Balance Sheet'!D28+'Balance Sheet'!D33-'Balance Sheet'!D14)/2) -> 0.23908918 | D28: ='Income Statement'!E19/(('Balance Sheet'!D24+'Balance Sheet'!D28+'Balance Sheet'!D33-'Balance Sheet'!D14+'Balance Sheet'!E24+'Balance Sheet'!E28+'Balance Sheet'!E33-'Balance Sheet'!E14)/2) -> 0.7247191 | E28: ='Income Statement'!F19/(('Balance Sheet'!E24+'Balance Sheet'!E28+'Balance Sheet'!E33-'Balance Sheet'!E14+'Balance Sheet'!F24+'Balance Sheet'!F28+'Balance Sheet'!F33-'Balance Sheet'!F14)/2) -> 0.52300683 | F28: ='Income Statement'!G19/('Balance Sheet'!G24+'Balance Sheet'!G28+'Balance Sheet'!G33-'Balance Sheet'!G14) -> 0.33190569 | G28: ='Income Statement'!H19/('Balance Sheet'!H24+'Balance Sheet'!H28+'Balance Sheet'!H33-'Balance Sheet'!H14) -> 0.39466107 | H28: ='Income Statement'!I19/('Balance Sheet'!I24+'Balance Sheet'!I28+'Balance Sheet'!I33-'Balance Sheet'!I14) -> 0.49959632 | I28: ='Income Statement'!J19/('Balance Sheet'!J24+'Balance Sheet'!J28+'Balance Sheet'!J33-'Balance Sheet'!J14) -> 0.61785056 | J28: ='Income Statement'!K19/('Balance Sheet'!K24+'Balance Sheet'!K28+'Balance Sheet'!K33-'Balance Sheet'!K14) -> 0.75817157 | K28: ='Income Statement'!L19/('Balance Sheet'!L24+'Balance Sheet'!L28+'Balance Sheet'!L33-'Balance Sheet'!L14) -> 0.88965354 | L28: ='Income Statement'!M19/('Balance Sheet'!M24+'Balance Sheet'!M28+'Balance Sheet'!M33-'Balance Sheet'!M14) -> 1.0286297 | M28: ='Income Statement'!N19/('Balance Sheet'!N24+'Balance Sheet'!N28+'Balance Sheet'!N33-'Balance Sheet'!N14) -> 1.1791319 | ... O28: ='Income Statement'!P19/('Balance Sheet'!P24+'Balance Sheet'!P28+'Balance Sheet'!P33-'Balance Sheet'!P14) -> 1.558245
A29: ROA (%) | B29: ='Income Statement'!C24/'Balance Sheet'!C18 -> -0.018252934 | C29: ='Income Statement'!D24/(('Balance Sheet'!C18+'Balance Sheet'!D18)/2) -> 0.053126729 | D29: ='Income Statement'!E24/(('Balance Sheet'!D18+'Balance Sheet'!E18)/2) -> 0.30657523 | E29: ='Income Statement'!F24/(('Balance Sheet'!E18+'Balance Sheet'!F18)/2) -> 0.18697318 | F29: ='Income Statement'!G24/(('Balance Sheet'!F18+'Balance Sheet'!G18)/2) -> 0.1564456 | G29: ='Income Statement'!H24/(('Balance Sheet'!G18+'Balance Sheet'!H18)/2) -> 0.174521 | H29: ='Income Statement'!I24/(('Balance Sheet'!H18+'Balance Sheet'!I18)/2) -> 0.2035951 | I29: ='Income Statement'!J24/(('Balance Sheet'!I18+'Balance Sheet'!J18)/2) -> 0.21848482 | J29: ='Income Statement'!K24/(('Balance Sheet'!J18+'Balance Sheet'!K18)/2) -> 0.22630751 | ... O29: ='Income Statement'!P24/(('Balance Sheet'!O18+'Balance Sheet'!P18)/2) -> 0.18293807
A30: Asset Turnover (x) | B30: ='Income Statement'!C5/'Balance Sheet'!C18 -> 0.55019557 | C30: ='Income Statement'!D5/(('Balance Sheet'!C18+'Balance Sheet'!D18)/2) -> 1.386829 | D30: ='Income Statement'!E5/(('Balance Sheet'!D18+'Balance Sheet'!E18)/2) -> 1.392497 | E30: ='Income Statement'!F5/(('Balance Sheet'!E18+'Balance Sheet'!F18)/2) -> 1.6158365 | F30: ='Income Statement'!G5/(('Balance Sheet'!F18+'Balance Sheet'!G18)/2) -> 1.5523597 | G30: ='Income Statement'!H5/(('Balance Sheet'!G18+'Balance Sheet'!H18)/2) -> 1.5658849 | H30: ='Income Statement'!I5/(('Balance Sheet'!H18+'Balance Sheet'!I18)/2) -> 1.6366266 | I30: ='Income Statement'!J5/(('Balance Sheet'!I18+'Balance Sheet'!J18)/2) -> 1.6459766 | J30: ='Income Statement'!K5/(('Balance Sheet'!J18+'Balance Sheet'!K18)/2) -> 1.5919837 | ... O30: ='Income Statement'!P5/(('Balance Sheet'!O18+'Balance Sheet'!P18)/2) -> 1.1096665

Sheet DCF Valuation
A1: RMC SWITCHGEARS LTD — DCF VALUATION (FCFF Method)
A3: Free Cash Flow Build-up | C3: FY26E | D3: FY27E | E3: FY28E | F3: FY29E | G3: FY30E | H3: FY31E | I3: FY32E | J3: FY33E | K3: FY34E | L3: FY35E
A5: EBIT | C5: ='Income Statement'!G19 -> 69.825 | D5: ='Income Statement'!H19 -> 105.735 | E5: ='Income Statement'!I19 -> 160.89 | F5: ='Income Statement'!J19 -> 228.41 | G5: ='Income Statement'!K19 -> 314.59 | H5: ='Income Statement'!L19 -> 405.96 | I5: ='Income Statement'!M19 -> 504.7 | J5: ='Income Statement'!N19 -> 609.79 | ... L5: ='Income Statement'!P19 -> 844.22
A6: (-) Tax on EBIT @ 25.17% | C6: =C5*Assumptions!H17 -> 17.5959 | D6: =D5*Assumptions!I17 -> 26.64522 | E6: =E5*Assumptions!J17 -> 40.54428 | F6: =F5*Assumptions!K17 -> 57.55932 | G6: =G5*Assumptions!L17 -> 79.27668 | H6: =H5*Assumptions!M17 -> 102.30192 | I6: =I5*Assumptions!N17 -> 127.1844 | J6: =J5*Assumptions!O17 -> 153.66708 | ... L6: =L5*Assumptions!Q17 -> 212.74344
A7: NOPAT (EBIT × (1-t)) | C7: =C5-C6 -> 52.2291 | D7: =D5-D6 -> 79.08978 | E7: =E5-E6 -> 120.34572 | F7: =F5-F6 -> 170.85068 | G7: =G5-G6 -> 235.31332 | H7: =H5-H6 -> 303.65808 | I7: =I5-I6 -> 377.5156 | J7: =J5-J6 -> 456.12292 | ... L7: =L5-L6 -> 631.47656
A8: (+) Depreciation & Amortisation | C8: ='Income Statement'!G18 -> 8.55 | D8: ='Income Statement'!H18 -> 13.3 | E8: ='Income Statement'!I18 -> 20.46 | F8: ='Income Statement'!J18 -> 27.61 | G8: ='Income Statement'!K18 -> 34.23 | H8: ='Income Statement'!L18 -> 40.8 | I8: ='Income Statement'!M18 -> 46.55 | J8: ='Income Statement'!N18 -> 52.02 | ... L8: ='Income Statement'!P18 -> 64.94
A9: (-) Capital Expenditure | C9: =Assumptions!H26 -> 55 | D9: =Assumptions!I26 -> 45 | E9: =Assumptions!J26 -> 35 | F9: =Assumptions!K26 -> 30 | G9: =Assumptions!L26 -> 28 | H9: =Assumptions!M26 -> 30 | I9: =Assumptions!N26 -> 32 | J9: =Assumptions!O26 -> 35 | ... L9: =Assumptions!Q26 -> 40
A10: (-) Change in Working Capital | C10: =-'Cash Flow'!G9 -> 8.9260274 | D10: =-'Cash Flow'!H9 -> 26.027397 | E10: =-'Cash Flow'!I9 -> 40.246575 | F10: =-'Cash Flow'!J9 -> 44.369863 | G10: =-'Cash Flow'!K9 -> 50.972603 | H10: =-'Cash Flow'!L9 -> 54 | I10: =-'Cash Flow'!M9 -> 47.260274 | J10: =-'Cash Flow'!N9 -> 44.958904 | ... L10: =-'Cash Flow'!P9 -> 34.273973
A12: Free Cash Flow to Firm (FCFF) | C12: =C7+C8-C9-C10 -> -3.1469274 | D12: =D7+D8-D9-D10 -> 21.362383 | E12: =E7+E8-E9-E10 -> 65.559145 | F12: =F7+F8-F9-F10 -> 124.09082 | G12: =G7+G8-G9-G10 -> 190.57072 | H12: =H7+H8-H9-H10 -> 260.45808 | I12: =I7+I8-I9-I10 -> 344.80533 | J12: =J7+J8-J9-J10 -> 428.18402 | ... L12: =L7+L8-L9-L10 -> 622.14259
A14: Discount Factor @ WACC | C14: =1/(1+$C$19)^1 -> 0.86327281 | D14: =1/(1+$C$19)^2 -> 0.74523995 | E14: =1/(1+$C$19)^3 -> 0.64334538 | F14: =1/(1+$C$19)^4 -> 0.55538258 | G14: =1/(1+$C$19)^5 -> 0.47944668 | H14: =1/(1+$C$19)^6 -> 0.41389328 | I14: =1/(1+$C$19)^7 -> 0.35730282 | J14: =1/(1+$C$19)^8 -> 0.30844981 | K14: =1/(1+$C$19)^9 -> 0.26627633 | L14: =1/(1+$C$19)^10 -> 0.22986912
A15: PV of FCFF | C15: =C12*C14 -> -2.7166569 | D15: =D12*D14 -> 15.920101 | E15: =E12*E14 -> 42.177173 | F15: =F12*F14 -> 68.917878 | G15: =G12*G14 -> 91.368497 | H15: =H12*H14 -> 107.80185 | I15: =I12*I14 -> 123.19991 | J15: =J12*J14 -> 132.07328 | ... L15: =L12*L14 -> 143.01137
A17: VALUATION SUMMARY
A19: WACC | C19: =Assumptions!D40 -> 0.15838237
A20: Terminal Growth Rate | C20: =Assumptions!D41 -> 0.055
A21: Sum of PV of FCFFs (FY26E-FY35E) | C21: =SUM(C15:L15) -> 861.02451
A22: Terminal Value (Gordon Growth) | C22: =L12*(1+C20)/(C19-C20) -> 6348.8626
A23: PV of Terminal Value | C23: =C22*L14 -> 1459.4074
A24: Enterprise Value | C24: =C21+C23 -> 2320.4319
A25: (-) Net Debt (FY25) | C25: ='Balance Sheet'!F28+'Balance Sheet'!F33-'Balance Sheet'!F14 -> 31
A26: Equity Value | C26: =C24-C25 -> 2289.4319
A27: Shares Outstanding (Cr) | C27: ='Income Statement'!G29 -> 1.06
A28: Implied Share Price (₹) | C28: =C26/C27 -> 2159.8415
A29: Current Market Price (₹) | C29: 408
A30: Upside / (Downside) | C30: =(C28-C29)/C29 -> 4.2937291

Sheet Comps
A1: RMC SWITCHGEARS — COMPARABLE COMPANY ANALYSIS
A3: Company | B3: Ticker | C3: Mkt Cap (₹Cr) | D3: Revenue (₹Cr) | E3: EBITDA (₹Cr) | F3: PAT (₹Cr) | G3: P/E (TTM) | H3: EV/EBITDA | I3: EV/Revenue | J3: Rev Growth (%) | K3: EBITDA Margin (%)
A4: Genus Power Infra | B4: GENUSPOWER | C4: 7426 | D4: 4151 | E4: 554 | F4: 516 | G4: 22 | H4: 17.9 | I4: 3 | J4: 1.7 | K4: 0.133
A5: HPL Electric & Power | B5: HPL | C5: 2647 | D5: 1700 | E5: 260 | F5: 94 | G5: 28 | H5: 17 | I5: 1.8 | J5: 0.2 | K5: 0.153
A6: Salzer Electronics | B6: SALZERELE | C6: 1580 | D6: 900 | E6: 108 | F6: 65 | G6: 24.3 | H6: 14.7 | I6: 1.8 | J6: 0.18 | K6: 0.12
A7: Schneider Electric Infra | B7: SCHNEIDER | C7: 8500 | D7: 2100 | E7: 315 | F7: 200 | G7: 42.5 | H7: 27 | I7: 4 | J7: 0.15 | K7: 0.15
A8: Techno Electric & Engg | B8: TECHNOELE | C8: 7200 | D8: 2612 | E8: 520 | F8: 380 | G8: 19 | H8: 13.8 | I8: 2.8 | J8: 0.35 | K8: 0.199
A11: Peer Median | G11: =MEDIAN(G4:G8) -> 24.3 | H11: =MEDIAN(H4:H8) -> 17 | I11: =MEDIAN(I4:I8) -> 2.8
A12: Peer Mean | G12: =AVERAGE(G4:G8) -> 27.16 | H12: =AVERAGE(H4:H8) -> 18.08 | I12: =AVERAGE(I4:I8) -> 2.68
A13: Peer Range (excl. outliers) | G13: =MIN(G4:G8)&" – "&MAX(G4:G8) -> 19 – 42.5 | H13: =MIN(H4:H8)&" – "&MAX(H4:H8) -> 13.8 – 27 | I13: =MIN(I4:I8)&" – "&MAX(I4:I8) -> 1.8 – 4
A15: VALUATION IMPLIED BY COMPS FOR RMC
A17: Metric | B17: RMC FY26E Value | C17: Peer Median Multiple | D17: Implied EV/Equity (₹Cr) | E17: Implied Price/Share (₹)
A18: P/E (on FY26E PAT) | B18: ='Income Statement'!G24 -> 47.87013 | C18: =G11 -> 24.3 | D18: =B18*C18 -> 1163.2442 | E18: =D18/'Income Statement'!G29 -> 1097.4001
A19: EV/EBITDA (on FY26E EBITDA) | B19: ='Income Statement'!G15 -> 78.375 | C19: =H11 -> 17 | D19: =B19*C19-'DCF Valuation'!C25 -> 1301.375 | E19: =D19/'Income Statement'!G29 -> 1227.7123
A20: EV/Revenue (on FY26E Revenue) | B20: ='Income Statement'!G5 -> 475 | C20: =I11 -> 2.8 | D20: =B20*C20-'DCF Valuation'!C25 -> 1299 | E20: =D20/'Income Statement'!G29 -> 1225.4717
A22: Average Implied Price from Comps | E22: =AVERAGE(E18:E20) -> 1183.528
A24: Note: Schneider trades at premium due to MNC parentage. Excluding Schneider, median P/E drops to ~22x.
A25: Sources: Screener.in, BSE filings, company press releases. Data as of Feb-Mar 2026.

Sheet Blended Valuation
A1: RMC SWITCHGEARS — BLENDED FAIR VALUE
A3: Methodology | B3: Implied Price (₹) | C3: Weight | D3: Weighted Price (₹) | E3: Rationale
A4: DCF Valuation (Base Case) | B4: ='DCF Valuation'!C28 -> 2159.8415 | C4: 0.5 | D4: =B4*C4 -> 1079.9207 | E4: Primary method; captures long-term intrinsic value
A5: Comparable Cos — P/E based | B5: =Comps!E18 -> 1097.4001 | C5: 0.2 | D5: =B5*C5 -> 219.48003 | E5: Strong indicator for earnings-driven valuation
A6: Comparable Cos — EV/EBITDA based | B6: =Comps!E19 -> 1227.7123 | C6: 0.2 | D6: =B6*C6 -> 245.54245 | E6: Operating profitability measure, capital-structure neutral
A7: Comparable Cos — EV/Revenue based | B7: =Comps!E20 -> 1225.4717 | C7: 0.1 | D7: =B7*C7 -> 122.54717 | E7: Lower weight; revenue multiples less reliable for EPC
A8: Total Weight | C8: =SUM(C4:C7) -> 1
A10: BLENDED FAIR VALUE PER SHARE | D10: =SUM(D4:D7) -> 1667.4904
A12: Current Market Price (₹) | D12: 408
A13: Upside / (Downside) to Fair Value | D13: =(D10-D12)/D12 -> 3.0869862
A15: SCENARIO-WISE FAIR VALUE SUMMARY
A17: Scenario | B17: FY35E Revenue (₹Cr) | C17: Fair Value/Share (₹) | D17: Upside/(Downside)
A18: Bull Case | B18: 4700 | C18: =C19*1.3 -> 2167.7375 | D18: =(C18-408)/408 -> 4.3130821
A19: Base Case | B19: 3820 | C19: =D10 -> 1667.4904 | D19: =(C19-408)/408 -> 3.0869862
A20: Bear Case | B20: 1975 | C20: =C19*0.55 -> 917.11971 | D20: =(C20-408)/408 -> 1.2478424

Sheet Sensitivity
A1: RMC SWITCHGEARS — SENSITIVITY ANALYSIS
A3: TABLE 1: Implied Share Price — WACC vs Terminal Growth Rate
B5: WACC ↓ / TGR → | C5: 0.03 | D5: 0.035 | E5: 0.04 | F5: 0.045 | G5: 0.05 | H5: 0.055 | I5: 0.06
B6: 0.13 | C6: 2722 | D6: 2825 | E6: 2940 | F6: 3067 | G6: 3211 | H6: 3374 | I6: 3560
B7: 0.14 | C7: 2364 | D7: 2442 | E7: 2528 | F7: 2623 | G7: 2729 | H7: 2847 | I7: 2979
B8: 0.15 | C8: 2072 | D8: 2132 | E8: 2198 | F8: 2270 | G8: 2350 | H8: 2437 | I8: 2535
B9: 0.157 | C9: 1897 | D9: 1948 | E9: 2004 | F9: 2064 | G9: 2130 | H9: 2202 | I9: 2282
B10: 0.165 | C10: 1723 | D10: 1765 | E10: 1811 | F10: 1861 | G10: 1914 | H10: 1973 | I10: 2037
B11: 0.175 | C11: 1536 | D11: 1570 | E11: 1606 | F11: 1646 | G11: 1688 | H11: 1734 | I11: 1783
B12: 0.185 | C12: 1377 | D12: 1404 | E12: 1433 | F12: 1465 | G12: 1499 | H12: 1535 | I12: 1574
A14: Note: Sensitivity values are hardcoded scenarios. Update manually if WACC/growth assumptions change.
A16: TABLE 2: Implied Share Price — FY26-35 Revenue CAGR vs Terminal EBITDA Margin
B18: Rev CAGR ↓ / Margin → | C18: 0.18 | D18: 0.2 | E18: 0.22 | F18: 0.24 | G18: 0.26 | H18: 0.28 | I18: 0.3
B19: 0.15 | C19: 684 | D19: 745 | E19: 805 | F19: 865 | G19: 925 | H19: 985 | I19: 1045
B20: 0.2 | C20: 930 | D20: 1015 | E20: 1100 | F20: 1185 | G20: 1270 | H20: 1355 | I20: 1440
B21: 0.25 | C21: 1262 | D21: 1381 | E21: 1500 | F21: 1619 | G21: 1738 | H21: 1857 | I21: 1976
B22: 0.28 | C22: 1513 | D22: 1658 | E22: 1804 | F22: 1949 | G22: 2094 | H22: 2239 | I22: 2384
B23: 0.3 | C23: 1707 | D23: 1872 | E23: 2037 | F23: 2203 | G23: 2368 | H23: 2533 | I23: 2699
B24: 0.35 | C24: 2299 | D24: 2526 | E24: 2753 | F24: 2981 | G24: 3208 | H24: 3435 | I24: 3663
B25: 0.4 | C25: 3080 | D25: 3390 | E25: 3699 | F25: 4009 | G25: 4319 | H25: 4629 | I25: 4938

Sheet Segment Analysis
A1: RMC SWITCHGEARS — SEGMENT-WISE REVENUE ANALYSIS (₹ Cr)
A3: Segment | C3: FY24A | D3: FY25A | E3: FY26E | F3: FY27E | G3: FY28E | H3: FY29E | I3: FY30E | J3: FY31E | K3: FY35E
A5: Electrical Products (Enclosures, Panels) | C5: =C10-C6-C7-C8 -> 84.6 | D5: =D10-D6-D7-D8 -> 63.3 | E5: 80 | F5: 95 | G5: 120 | H5: 155 | I5: 200 | J5: 250 | K5: 400
A6: Electrical EPC (T&D, Substations) | C6: 70 | D6: 130 | E6: 140 | F6: 175 | G6: 230 | H6: 310 | I6: 400 | J6: 500 | K6: 900
A7: Solar EPC | C7: 18 | D7: 113 | E7: 225 | F7: 340 | G7: 490 | H7: 650 | I7: 830 | J7: 1020 | K7: 1850
A8: Solar Products (Manufacturing) | C8: 0 | D8: 10 | E8: 30 | F8: 55 | G8: 90 | H8: 140 | I8: 200 | J8: 270 | K8: 670
A10: TOTAL REVENUE | C10: ='Income Statement'!E5 -> 172.6 | D10: ='Income Statement'!F5 -> 316.3 | E10: =SUM(E5:E8) -> 475 | F10: =SUM(F5:F8) -> 665 | G10: =SUM(G5:G8) -> 930 | H10: =SUM(H5:H8) -> 1255 | I10: =SUM(I5:I8) -> 1630 | J10: =SUM(J5:J8) -> 2040 | K10: =SUM(K5:K8) -> 3820
A12: REVENUE MIX (%)
A13: Electrical Products % | C13: =C5/C10 -> 0.49015064 | D13: =D5/D10 -> 0.20012646 | E13: =E5/E10 -> 0.16842105 | F13: =F5/F10 -> 0.14285714 | G13: =G5/G10 -> 0.12903226 | H13: =H5/H10 -> 0.12350598 | I13: =I5/I10 -> 0.12269939 | J13: =J5/J10 -> 0.12254902 | K13: =K5/K10 -> 0.10471204
A14: Electrical EPC % | C14: =C6/C10 -> 0.40556199 | D14: =D6/D10 -> 0.41100221 | E14: =E6/E10 -> 0.29473684 | F14: =F6/F10 -> 0.26315789 | G14: =G6/G10 -> 0.24731183 | H14: =H6/H10 -> 0.24701195 | I14: =I6/I10 -> 0.24539877 | J14: =J6/J10 -> 0.24509804 | K14: =K6/K10 -> 0.23560209
A15: Solar EPC % | C15: =C7/C10 -> 0.10428737 | D15: =D7/D10 -> 0.35725577 | E15: =E7/E10 -> 0.47368421 | F15: =F7/F10 -> 0.5112782 | G15: =G7/G10 -> 0.52688172 | H15: =H7/H10 -> 0.51792829 | I15: =I7/I10 -> 0.50920245 | J15: =J7/J10 -> 0.5 | K15: =K7/K10 -> 0.48429319
A16: Solar Products % | C16: =C8/C10 -> 0 | D16: =D8/D10 -> 0.031615555 | E16: =E8/E10 -> 0.063157895 | F16: =F8/F10 -> 0.082706767 | G16: =G8/G10 -> 0.096774194 | H16: =H8/H10 -> 0.11155378 | I16: =I8/I10 -> 0.12269939 | J16: =J8/J10 -> 0.13235294 | K16: =K8/K10 -> 0.17539267
A18: SEGMENT NOTES & OUTLOOK
A20: Electrical Products: | B20: Legacy core. Smart meter enclosures, distribution boxes. Benefits from RDSS rollout of 250M smart meters nationally. Stable 15-20% growth.
A21: Electrical EPC: | B21: Underground cabling, substation construction, 11kV feeder segregation. ₹200.9 Cr LOI from Jaipur Discom in Jan'26. RDSS a major driver.
A22: Solar EPC: | B22: Largest growth driver. MAHAGENCO ₹154Cr project (8.8MWac commissioned). MSEDCL ₹61Cr project. ₹9 trillion T&D investment tailwind.
A23: Solar Products: | B23: 1 GW solar module plant in Jaipur (₹100Cr capex). SIDBI-funded. Backward integration for captive use + third-party sales. Delayed but progressing.
A24: Key Risk: | B24: Solar plant execution delay, government policy changes on RDSS/tenders, receivable days remaining high (170 days), competition from larger players.
A25: Key Catalyst: | B25: NSE mainboard listing, solar plant commissioning, ₹1500Cr+ tender pipeline, Forbes Asia recognition, credit rating upgrades.
